Workbook

Sheet 1-8-2026
B3: Opening Petit cash | E3: 0
B4: Walk-in Today: Cash In USD | E4: 250
B5: Birthday Laura Ajamian | E5: 645
B6: Stephanie Jalwan D.P Birthday 9-8-2026 | E6: 300
E7: 0
E8: 0
B10: Marwaha & Lamp | F10: 15
B11: Manakich Zaatar | F11: 6
B12: Le Marchet Selectif | F12: 67
B13: Irtife2 w Tokhtit Baladiye | F13: 100
B14: Nour Haybe | F14: 26
B15: Nour Malek | F15: 26
B16: Le Marchet Selectif | F16: 20
B17: Amal Advance On Salary August | F17: 100
B18: Eva Maalouly | F18: 21
F19: 0
F20: 0
F21: 0
F22: 0
B23: Total | E23: =E3+E4+E5+E6+E7+E8-F13-F14-F15-F10-F11-F12-F17-F16-F18 -> 814

Sheet 2-8-2026
B3: Opening Petit cash | E3: 230
B4: Walk-in Today: Cash In USD | E4: 785
E5: 0
E6: 0
E7: 0
E8: 0
B10: Le Marchet Selectif | F10: 121
B11: Citern Water Little Hands (Old Inv) | F11: 80
B12: Citern Water Little Hands (New Inv) | F12: 20
B13: Nour Malek 2 Working day | F13: 40
B14: Brocoli (Geryes Malek ) Old Invoices | F14: 100
F15: 0
F16: 0
F17: 0
F18: 0
F19: 0
F20: 0
F21: 0
F22: 0
F23: 0
F24: 0
F25: 0
F26: 0
F27: 0
B28: Total | E28: =E3+E4+E5+E6+E7+E8-F13-F14-F18-F19-F20-F10-F11-F12 -> 654

Sheet 5-8-2026
B3: Opening Petit cash | E3: 0
B4: Walk-in Today: Cash In USD | E4: 0
B5: Kinder Camp | E5: 588
E6: 0
E7: 0
E8: 0
B10: Cleaning Supplies | F10: 30
B11: Shein Orders | F11: 125
B12: Lara Cleaning H Of Sunday | F12: 28
B13: Benzin Thaer | F13: 70
B14: Mini Market Pierre Mallah | F14: 8
B15: Spinneys | F15: 31
F16: 0
F17: 0
F18: 0
F19: 0
F20: 0
F21: 0
F22: 0
F23: 0
F24: 0
F25: 0
F26: 0
F27: 0
B28: Total | E28: =E3+E4+E5+E6+E7+E8-F13-F14-F18-F19-F20-F10-F11-F12-F15 -> 296

Sheet 6-8-2026
B3: Opening Petit cash | E3: 0
B4: Walk-in Today: Cash In USD | E4: 0
B5: College Melkart | E5: 372
E6: 0
E7: 0
E8: 0
F10: 0
F11: 0
F12: 0
F13: 0
F14: 0
F15: 0
F16: 0
F17: 0
F18: 0
F19: 0
F20: 0
F21: 0
... F27: 0
B28: Total | E28: =E3+E4+E5+E6+E7+E8-F13-F14-F18-F19-F20-F10-F11-F12-F15 -> 372

Sheet 7-8-26
B3: Opening Petit cash | E3: 20
B4: Walk-in Today: Cash In USD | E4: 0
B5: Modern Star Lebanon (Verdun&Hazmieh) | E5: 384
B6: Rabieh Nursery | E6: 648
E7: 0
E8: 0
B10: Nour Haybe | F10: 32
B11: Cynthia Helo | F11: 25
B12: Event Megastore ( Workshops & Birthdays ) | F12: 113
B13: Nour Haybe | F13: 26
B14: fairco International | F14: 151 | G14: Amani Saloum Birthday D.P
B15: fairco International | F15: 102 | G15: Amani Saloum Birthday D.P
B16: Spinneys Kitchen | F16: 77.73 | G16: Stephanie Jalwan Birthday D.P
B17: Spinneys Hygiene workshop | F17: 79.12 | G17: Stephanie Jalwan Birthday D.P
B18: Le Marchet Selectif | F18: 100 | G18: Stephanie Jalwan Birthday D.P
B19: Nour Malek | F19: 26
B20: Le Marchet Selectif | F20: 20
B21: Amal Advance On Salary August | F21: 100
B22: Eva Maalouly | F22: 21
B23: For Amal Burger Kibbe | F23: 100
F24: 0
F25: 0
F26: 0
F27: 0
B28: Total | E28: =E3+E4+E5+E6+E7+E8-F10-F11-F12-F13-F19-F20-F21-F22-F23 -> 589

Sheet 8-8-2026
B3: Opening Petit cash | E3: 0
B4: Walk-in Today: Cash In USD | E4: 250
B5: Gaelle Semaan Birthday | E5: 620
B6: Amani Saloum | E6: 330
E7: 0
E8: 0
B10: Thaer Invoices | F10: 41
B11: Imaco Garbage | F11: 30
B12: Fresh & More Vegtables & Fruits For 3 Birthdays | F12: 17
B13: Noour Malek | F13: 23
B14: Nour Haybe | F14: 36
F15: 0
F16: 0
F17: 0
F18: 0
F19: 0
F20: 0
F21: 0
F22: 0
F23: 0
F24: 0
F25: 0
F26: 0
F27: 0
B28: Total | E28: =E3+E4+E5+E6+E7+E8-F10-F11-F12-F13-F19-F20-F21-F22-F14 -> 1053

Sheet 9-8-2026
B3: Opening Petit cash | E3: 0
B4: Walk-in Today: Cash In USD | E4: 415
B5: Stephanie Jalwan | E5: 860
E6: 0
E7: 0
E8: 0
B10: Eva Maalouly | F10: 22
B11: Storium | F11: 38
B12: Citern Water | F12: 85
B13: Boucherie Ziad Burgers Kebbe (For # Birthdays) | F13: 58
B14: Nour Haybe | F14: 26
B15: Fresh & More | F15: 17
B16: Miro Salary | F16: 600
F17: 0
F18: 0
F19: 0
F20: 0
F21: 0
F22: 0
F23: 0
F24: 0
F25: 0
F26: 0
F27: 0
B28: Total | E28: =E3+E4+E5+E6+E7+E8-F10-F11-F12-F13-F19-F20-F21-F22-F14-F15 -> 1029

Sheet 12-8-2026
B3: Opening Petit cash | E3: 70
B4: Walk-in Today: Cash In USD | E4: 820
B5: Janette Alam D.P Birthday 26-8 | E5: 200
B6: Joanna Abdo D.P Birthday 19-9 | E6: 200
E7: 0
E8: 0
B10: Le Marchet Selectif | F10: 102
B11: La Valeur Kitchen | F11: 163
B12: LA valeur Fruits | F12: 35
B13: Eva Maalouly | F13: 18
B14: Cynthia | F14: 20
B15: Rim Water | F15: 127 | I15: 163.21
B16: Nchara For Farm | F16: 12
B17: Charbel Ghostin | F17: 150
B18: Marleine Advance On salary August | F18: 150
F19: 0
F20: 0
F21: 0
F22: 0
F23: 0
F24: 0
F25: 0
F26: 0
F27: 0
B28: Total | E28: =E4+E3-F10-F11-F12-F13-F14-F15-F16-F17-F18 -> 113

Sheet 14-8-2026
B4: Opening Petit cash | E4: 113
B5: Walk-in Today: Cash In USD | E5: 368
B6: Gaelle Abi Mansour D.P Birthday 13-9 | E6: 300
E7: 0
E8: 0
E9: 0
B11: Boucherie Ziad | F11: 19
B12: Nour Haybe | F12: 24
B13: Eva Maalouly | F13: 18
B14: Librarie Mallah (Flafy Clay, Peinture) | F14: 100
F15: 0
F16: 0
F17: 0
F18: 0
F19: 0
F20: 0
F21: 0
F22: 0
F23: 0
F24: 0
F25: 0
F26: 0
... F28: 0
B29: Total | E29: =E5+E4-F11-F12-F13-F14-F15-F16-F17-F18-F19 -> 320

Sheet 15-8-2026
B4: Opening Petit cash | E4: 190
B5: Walk-in Today: Cash In USD | E5: 112
B6: Fares Tahan Birthday | E6: 723
E7: 0
E8: 0
E9: 0
B11: Le Marchet Selectif ( Fa7em Ice water ,,,,)For Birthday | F11: 100
B12: Citern Water Littke Hands | F12: 80
B13: Fruits & Vegetables For Birthday 15-8 | F13: 12
B14: Moteur | F14: 310
B15: Storium Food Birthday Today | F15: 55
B16: Spinneys Food Birtjday Today | F16: 115
B17: Nour Haybe | F17: 28
B18: Eva Maalouly | F18: 25
F19: 0
F20: 0
F21: 0
F22: 0
F23: 0
F24: 0
F25: 0
F26: 0
F27: 0
F28: 0
B29: Remaining Cash | E29: =E5+E4-F11-F12-F13-F14-F15-F16-F17-F18-F19+E6 -> 300

Sheet 16-8-2026
B4: Opening Petit cash | E4: 0
B5: Walk-in Today: Cash In USD | E5: 154.25
E6: 0
E7: 0
E8: 0
E9: 0
B11: Remaining Cash For 16-8-2026 in Caisse | E11: =E5 -> 154.25

Sheet 17-8-2026
B4: Opening Petit cash | E4: 154
B5: Walk-in Today: Cash In USD | E5: 0
B6: Colinie Classes Orange | E6: 360
B7: Krystelle D.P Birthday 18-8-2026 | E7: 200
E8: 0
E9: 0
B11: Le Marchet Selectif ( kitchen & Orange ) | F11: 100
B12: Thaer Benzin | F12: 40
B13: Manakich (Old Invoice ) | F13: 47
F14: 0
F15: 0
F16: 0
F17: 0
B18: Remaining Cash | E18: =E4+E6-F11-F12-F13 -> 327

Sheet 18-8--2026
B4: Opening Petit cash | E4: 127
B5: Walk-in Today: Cash In USD | E5: 0
B6: Biirthday Krystelle | E6: 717
E7: 0
E8: 0
E9: 0
B11: Karam Bake Birthday 18-8 | F11: 57 | G11: From D. P Birthday Krystelle
B12: Boucherie Ziad ( Kebbe & Burgers) | F12: 143 | G12: From D. P Birthday Krystelle
B13: Nour Haybe | F13: 24
B14: Spinneys Bar Workshop | F14: 38
B15: Spinneys Kitchen Workshop Hygiene | F15: 69.21
B16: Spinneys Kitchen Workshop | F16: 56
F17: 0
F18: 0
F19: 0
F20: 0
B21: Remaining Cash | E21: =E4+E6-F13-F14-F15-F16 -> 656.79

Sheet 21-8-2026
B4: Opening Petit cash | E4: 50
B5: Walk-in Today: Cash In USD | E5: 538
B6: Sarine demak D.P Birthday | E6: 300
B7: Cynthia kreidy D.P Birthday | E7: 300
E8: 0
E9: 0
B11: Le Marchet Selectif (Old Invoices) | F11: 105
B12: Thaer Benzin | F12: 40
B13: Manakich | F13: 7
B14: Saab Doctors vet ( Dawa, Makanet 7le2a) | F14: 100
F15: 0
F16: 0
F17: 0
F18: 0
F19: 0
F20: 0
B21: Remaining Cash | E21: =E5-F11-F12-F13-F14-F15-F16-F17-F18-F19-F20+E4+E6+E7 -> 936

Sheet 22-8-2026
B4: Opening Petit cash | E4: 130
B5: Walk-in Today: Cash In USD | E5: 294
E6: 0
E7: 0
E8: 0
E9: 0
B11: Water Citern Little Hands | F11: 80
B12: Boucherie Ziad Kebbe Burgers | F12: 17
B13: Emdedet Water | F13: 200
B14: Eva | F14: 21
F15: 0
F16: 0
F17: 0
F18: 0
F19: 0
F20: 0
B21: Remaining Cash | E21: =E5-F11-F12-F13-F14-F15-F16-F17-F18-F19-F20+E4+E6+E7 -> 106

Sheet 23-8-2026
B4: Opening Petit cash | E4: 106
B5: Walk-in Today: Cash In USD | E5: 135
B6: Exchange From Thaer | E6: 0
E7: 0
E8: 0
E9: 0
B11: Joe Market Burger Bread | F11: 10
B12: Benzin & Oil Thaer | F12: 47
B13: Cynthia Working H | F13: 32
B14: Stickers Little Hands | F14: 12
B15: Saleh Plumber ( Mad Khat May ) | F15: 100
F16: 0
F17: 0
F18: 0
F19: 0
F20: 0
B21: Remaining Cash | E21: =E5-F11-F12-F13-F14-F15-F16-F17-F18-F19-F20+E4+E6+E7 -> 40

Sheet 25-8-2026
B4: Opening Petit cash | E4: 40
B5: Walk-in Today: Cash In USD | E5: 199
B6: Exchange From Thaer | E6: 0
E7: 0
E8: 0
E9: 0
B11: Adwat ( Ice Cube ) | F11: 30
B12: Storium ( Workshop, Kitchen, Bar ) | F12: 21.91
B13: Alaaf For Farm | F13: 98
B14: Youssef dawa Animal | F14: 77
F15: 0
F16: 0
F17: 0
F18: 0
F19: 0
F20: 0
B21: Remaining Cash | E21: =E5-F11-F12-F13-F14-F15-F16-F17-F18-F19-F20+E4+E6+E7 -> 12.09

Sheet 26-8-2026
B4: Opening Petit cash | E4: 0
B5: Walk-in Today: Cash In USD | E5: 145
B6: Summe r Camp Mar Chaaya | E6: 240
B7: Janette Alam | E7: 510
E8: 0
E9: 0
B11: Rim water | F11: 10
B12: Fruits For Birthday | F12: 21 | G12: Janet Alam Birthday D.P
B13: Boucherie Ziad Burger | F13: 18 | G13: Janet Alam Birthday D.P
B14: La Valeur Supermarket | F14: 41 | G14: Janet Alam Birthday D.P
B15: Karam Bake | F15: 37 | G15: Janet Alam Birthday D.P
B16: Nour Haybe | F16: 22 | G16: Janet Alam Birthday D.P
B17: Storium Saliba | F17: 25 | G17: Janet Alam Birthday D.P
B18: Le Marchet Selectif | F18: 36 | G18: Janet Alam Birthday D.P
F19: 0
F20: 0
B21: Remaining Cash | E21: =SUM(E4:E20)-F11 -> 885

Sheet 28-6-2026
B4: Opening Petit cash | E4: 85
B5: Walk-in Today: Cash In USD | E5: 0
B6: Birthday Marc | E6: 700
E7: 0
E8: 0
E9: 0
F11: 0
B12: Le Marchet Selectif | F12: 80 | G12: Marc Haber Birthday D.P
B13: Nour Haybe | F13: 21 | G13: Marc Haber Birthday D.P
B14: Storium Saliba Birthday Kitchen | F14: 61 | G14: Marc Haber Birthday D.P
B15: Kitchen Fruits | F15: 23 | G15: Marc Haber Birthday D.P
B16: Boucherie Ziad Burgers | F16: 39 | G16: Marc Haber Birthday D.P
B17: Boucherie Ziad Burgers | F17: 18 | G17: Marc Haber Birthday D.P
B18: Sunrise Market Cheese Bhar Tuna | F18: 41 | G18: Marc Haber Birthday D.P
F19: 0 | G19: Marc Haber Birthday D.P
F20: 0 | G20: Marc Haber Birthday D.P
B21: Remaining Cash | E21: =SUM(E4:E20)-F11 -> 785

Sheet 29-8-2026
B4: Opening Petit cash | E4: 85
B5: Walk-in Today: Cash In USD | E5: 157
B6: Sarine Dekmak Birthday | E6: 600
E7: 0
E8: 0
E9: 0
B11: EDL (Little Hands ) | F11: 51
B12: Mhamad Imdedet May | F12: 51
B13: Wissam Mansour Ashwe Coffe | F13: 100
B14: Nour haybe | F14: 21 | G14: Sarine Dekmak Birthday D.P
B15: Thaer | F15: 129 | G15: Sarine Dekmak Birthday D.P
B16: Karam Bake | F16: 51 | G16: Sarine Dekmak Birthday D.P
B17: Mallah Librarie ( Roll paper, Conson , Fluffy Clay …..) | F17: 70 | G17: Sarine Dekmak Birthday D.P
F18: 0 | G18: Sarine Dekmak Birthday D.P
F19: 0 | G19: Sarine Dekmak Birthday D.P
F20: 0
B21: Remaining Cash | E21: =SUM(E4:E20)-F11-F12-F13 -> 640

Sheet 30-8-2026
B4: Opening Petit cash | E4: 40
B5: Walk-in Today: Cash In USD | E5: 167
E6: 0
E7: 0
E8: 0
E9: 0
F11: 0
F12: 0
F13: 0
F14: 0
F15: 0
F16: 0
F17: 0
F18: 0
F19: 0
F20: 0
B21: Remaining Cash | E21: =SUM(E4:E20)-F11-F12-F13 -> 207

Sheet Total August
B1: Description | C1: In$ | D1: Exp $ | E1: Invoice Already Paid From D.P Birthday | F1: Cash With sanaa From sales | G1: Down Payment Birthday & Event | H1: Total$
A2: 1-8-2026 | B2: Remainig Cash From June 2026 ( Sanaa) | C2: 955 | H2: =C2 -> 955
B3: Remainig Cash From Birthday D.P June 2026 | G3: 550 | H3: =H2+C3-D3-F3-G3 -> 405
B4: Remainig Cash Flow From June 2026 ( Sanaa) | F4: 955 | H4: =H3+C4-D4-F4-G4 -> -550
B5: Walk-in | C5: ='1-8-2026'!E4 -> 250 | H5: =H4+C5-D5-F5-G5 -> -300
B6: Birthday kaylie | C6: 645 | H6: =H5+C6-D6-F6-G6 -> 345
B7: Cash Flow (Sanaa) | F7: 450 | H7: =H6+C7-D7-F7-G7 -> -105
B8: Marwaha & Lamp | D8: 15 | H8: =H7+C8-D8-F8-G8 -> -120
B9: Manakich Zaatar | D9: 6 | H9: =H8+C9-D9-F9-G9 -> -126
B10: Nour Malek | D10: 26 | H10: =H9+C10-D10-F10-G10 -> -152
B11: Le Marchet Selectif | D11: 20 | H11: =H10+C11-D11-F11-G11 -> -172
B12: Amal Advance On Salary August | D12: 100 | H12: =H11+C12-D12-F12-G12 -> -272
B13: Eva Maalouly | D13: 21 | H13: =H12+C13-D13-F13-G13 -> -293
B14: Le Marchet Selectif | D14: 67 | H14: =H13+C14-D14-F14-G14 -> -360
B15: Irtife2 w Tokhtit Baladiye | D15: 100 | H15: =H14+C15-D15-F15-G15 -> -460
B16: Nour Haybe | D16: 26 | H16: =H15+C16-D16-F16-G16 -> -486
B17: Stephanie Jalwan D.P Birthday 9-8-2026 | G17: 300 | H17: =H16+C17-D17-F17-G17 -> -786
A18: 2-8-2026 | B18: Walk-in | C18: ='2-8-2026'!E4 -> 785 | H18: =H17+C18-D18-F18-G18 -> -1
B19: Le Marchet Selectif | D19: 121 | H19: =H18+C19-D19-F19-G19 -> -122
B20: Citern Water Little Hands (Old Inv) | D20: 80 | H20: =H19+C20-D20-F20-G20 -> -202
B21: Citern Water Little Hands (New Inv) | D21: 20 | H21: =H20+C21-D21-F21-G21 -> -222
B22: Nour Malek 2 Working day | D22: 40 | H22: =H21+C22-D22-F22-G22 -> -262
B23: Brocoli (Geryes Malek ) Old Invoices | D23: 100 | H23: =H22+C23-D23-F23-G23 -> -362
B24: Cash Flow (Sanaa) | F24: 600 | H24: =H23+C24-D24-F24-G24 -> -962
A25: 5-8-2026 | B25: Cleaning Supplies | D25: 30 | H25: =H24+C25-D25-F25-G25 -> -992
B26: Shein Orders | D26: 125 | H26: =H25+C26-D26-F26-G26 -> -1117
B27: Lara Cleaning H Of Sunday | D27: 28 | H27: =H26+C27-D27-F27-G27 -> -1145
B28: Benzin Thaer | D28: 70 | H28: =H27+C28-D28-F28-G28 -> -1215
B29: Mini Market Pierre Mallah | D29: 8 | H29: =H28+C29-D29-F29-G29 -> -1223
B30: Spinneys | D30: 31 | H30: =H29+C30-D30-F30-G30 -> -1254
B31: Kinder Camp | C31: 588 | H31: =H30+C31-D31-F31-G31 -> -666
B32: Cash Flow (Sanaa) | F32: 300 | H32: =H31+C32-D32-F32-G32 -> -966
A33: 6-8-2026 | B33: College Melkart | C33: 372 | H33: =H32+C33-D33-F33-G33 -> -594
B34: Cash Flow (Sanaa) | F34: 350 | H34: =H33+C34-D34-F34-G34 -> -944
A35: 7-8-2026 | B35: Modern Star Lebanon (Verdun&Hazmieh) | C35: 384 | H35: =H34+C35-D35-F35-G35 -> -560
B36: Rabieh Nursery | C36: 648 | H36: =H35+C36-D36-F36-G36 -> 88
B37: Nour Haybe | D37: 32 | H37: =H36+C37-D37-F37-G37 -> 56
B38: Cynthia Helo | D38: 25 | H38: =H37+C38-D38-F38-G38 -> 31
B39: Event Megastore ( Workshops & Birthdays ) | D39: 113 | H39: =H38+C39-D39-F39-G39 -> -82
B40: Nour Malek | D40: 26 | H40: =H39+C40-D40-F40-G40 -> -108
B41: Le Marchet Selectif | D41: 20 | H41: =H40+C41-D41-F41-G41 -> -128
B42: Amal Advance On Salary August | D42: 100 | H42: =H41+C42-D42-F42-G42 -> -228
B43: Eva Maalouly | D43: 21 | H43: =H42+C43-D43-F43-G43 -> -249
B44: For Amal Burger Kibbe | D44: 100 | H44: =H43+C44-D44-F44-G44 -> -349
B45: fairco International | E45: 151 | H45: =H44+C45-D45-F45-G45 -> -349
B46: fairco International | E46: 102 | H46: =H45+C46-D46-F46-G46 -> -349
B47: Spinneys Kitchen | E47: 77.73 | H47: =H46+C47-D47-F47-G47 -> -349
B48: Spinneys Hygiene workshop | E48: 79.12 | H48: =H47+C48-D48-F48-G48 -> -349
B49: Le Marchet Selectif | E49: 100 | H49: =H48+C49-D49-F49-G49 -> -349
B50: Cash Flow (Sanaa) | F50: 600 | H50: =H49+C50-D50-F50-G50 -> -949
A51: 8-8-2026 | B51: Walk-in Today: Cash In USD | C51: 250 | H51: =H50+C51-D51-F51-G51 -> -699
B52: Gaelle Semaan Birthday | C52: 620 | H52: =H51+C52-D52-F52-G52 -> -79
B53: Amani Saloum | C53: 330 | H53: =H52+C53-D53-F53-G53 -> 251
B54: Thaer Invoices | D54: 41 | H54: =H53+C54-D54-F54-G54 -> 210
B55: Imaco Garbage | D55: 30 | H55: =H54+C55-D55-F55-G55 -> 180
B56: Fresh & More Vegtables & Fruits For 3 Birthdays | D56: 17 | H56: =H55+C56-D56-F56-G56 -> 163
B57: Noour Malek | D57: 23 | H57: =H56+C57-D57-F57-G57 -> 140
B58: Nour Haybe | D58: 36 | H58: =H57+C58-D58-F58-G58 -> 104
B59: Cash Flow (Sanaa) | F59: 1000 | H59: =H58+C59-D59-F59-G59 -> -896
H60: =H59+C60-D60-F60-G60 -> -896
A61: 9-8-2026 | B61: Walk-in Today: Cash In USD | C61: 415 | H61: =H60+C61-D61-F61-G61 -> -481
B62: Stephanie Jalwan | C62: 860 | H62: =H61+C62-D62-F62-G62 -> 379
B63: Eva Maalouly | D63: 22 | H63: =H62+C63-D63-F63-G63 -> 357
B64: Storium | D64: 38 | H64: =H63+C64-D64-F64-G64 -> 319
B65: Citern Water | D65: 85 | H65: =H64+C65-D65-F65-G65 -> 234
B66: Boucherie Ziad Burgers Kebbe (For # Birthdays) | D66: 58 | H66: =H65+C66-D66-F66-G66 -> 176
B67: Nour Haybe | D67: 26 | H67: =H66+C67-D67-F67-G67 -> 150
B68: Fresh & More | D68: 17 | H68: =H67+C68-D68-F68-G68 -> 133
B69: Miro Salary | D69: 600 | H69: =H68+C69-D69-F69-G69 -> -467
B70: Cash Flow (Sanaa) | F70: 350 | H70: =H69+C70-D70-F70-G70 -> -817
A71: 12-8-2026 | B71: Walk-in Today: Cash In USD | C71: 820 | H71: =H70+C71-D71-F71-G71 -> 3
B72: Janette Alam D.P Birthday 26-8 | G72: 200 | H72: =H71+C72-D72-F72-G72 -> -197
B73: Joanna Abdo D.P Birthday 19-9 | G73: 200 | H73: =H72+C73-D73-F73-G73 -> -397
B74: Le Marchet Selectif | D74: 102 | H74: =H73+C74-D74-F74-G74 -> -499
B75: La Valeur Kitchen | D75: 163 | H75: =H74+C75-D75-F75-G75 -> -662
B76: LA valeur Fruits | D76: 35 | H76: =H75+C76-D76-F76-G76 -> -697
B77: Eva Maalouly | D77: 18 | H77: =H76+C77-D77-F77-G77 -> -715
B78: Cynthia | D78: 20 | H78: =H77+C78-D78-F78-G78 -> -735
B79: Rim Water | D79: 127 | H79: =H78+C79-D79-F79-G79 -> -862
B80: Nchara For Farm | D80: 12 | H80: =H79+C80-D80-F80-G80 -> -874
B81: Charbel Ghostin | D81: 150 | H81: =H80+C81-D81-F81-G81 -> -1024
B82: Marleine Advance On salary August | D82: 150 | H82: =H81+C82-D82-F82-G82 -> -1174
A83: 14-8-2026 | B83: Walk-in Today: Cash In USD | C83: 368 | H83: =H82+C83-D83-F83-G83 -> -806
B84: Gaelle Abi Mansour D.P Birthday 13-9 | G84: 300 | H84: =H83+C84-D84-F84-G84 -> -1106
B85: Boucherie Ziad | D85: 19 | H85: =H84+C85-D85-F85-G85 -> -1125
B86: Nour Haybe | D86: 24 | H86: =H85+C86-D86-F86-G86 -> -1149
B87: Eva Maalouly | D87: 18 | H87: =H86+C87-D87-F87-G87 -> -1167
B88: Librarie Mallah (Flufy Clay, Peinture) | D88: 100 | H88: =H87+C88-D88-F88-G88 -> -1267
B89: Cash Flow (Sanaa) Via Wishe | F89: 180 | H89: =H88+C89-D89-F89-G89 -> -1447
H90: =H89+C90-D90-F90-G90 -> -1447
A91: 15-8-2026 | B91: Walk-in Today: Cash In USD | C91: 112 | H91: =H90+C91-D91-F91-G91 -> -1335
B92: Fares Tahan Birthday | C92: 723 | H92: =H91+C92-D92-F92-G92 -> -612
B93: Le Marchet Selectif ( Fa7em Ice water ,,,,)For Birthday | D93: 100 | H93: =H92+C93-D93-F93-G93 -> -712
B94: Citern Water Littke Hands | D94: 80 | H94: =H93+C94-D94-F94-G94 -> -792
B95: Fruits & Vegetables For Birthday 15-8 | D95: 12 | H95: =H94+C95-D95-F95-G95 -> -804
B96: Moteur | D96: 310 | H96: =H95+C96-D96-F96-G96 -> -1114
B97: Storium Food Birthday Today | D97: 55 | H97: =H96+C97-D97-F97-G97 -> -1169
B98: Spinneys Food Birtjday Today | D98: 115 | H98: =H97+C98-D98-F98-G98 -> -1284
B99: Nour Haybe | D99: 28 | H99: =H98+C99-D99-F99-G99 -> -1312
B100: Eva Maalouly | D100: 25 | H100: =H99+C100-D100-F100-G100 -> -1337
...
