Workbook

Sheet Daily Profitability
A1: M - July & August Daily Profitability | X1: Month List | Y1: Activity List | Z1: Category List | AA1: Expense Type List | AB1: Supplier List | AC1: Revenue Stream List
X2: All | Y2: All | Z2: All | AA2: All | AB2: All | AC2: All
A3: Month | B3: All | D3: Activity | E3: All | G3: Expense Category | H3: Food & Beverage | J3: Expense Type | K3: All | M3: Supplier | N3: All | P3: Revenue Stream | Q3: All | X3: July 2026 | Y3: Birthday | Z3: Cleaning & Waste | AA3: Cleaning & Sanitation | AB3: Agaric | AC3: Walk-in
A4: Total Income | C4: Expenses | E4: Revenue | G4: Net Benefit | I4: Net Margin | X4: August 2026 | Y4: Event | Z4: Disposables & Packaging | AA4: Decoration & Workshop Materials | AB4: Asab & Tools For Garden | AC4: Colonie
A5: =B13 -> 32749 | C5: =C13 -> 6652.6783 | E5: =D13 -> 32749 | G5: =E13 -> 26096.322 | I5: =F13 -> 0.79685858 | Y5: General Operations | Z5: Equipment & Tools | AA5: Electricity | AB5: Boucherie Ziad | AC5: Birthday
Y6: Nursery Visit | Z6: Food & Beverage | AA6: Food & Beverage | AB6: Chebl Bou Akl
Y7: Unspecified | Z7: Garden & Grounds | AA7: Garden & Landscaping | AB7: Disposable
Y8: Walk-in | Z8: Health & Safety | AA8: Internet | AB8: Divers
A9: Monthly Summary | G9: Definitions & Source Note | Y9: Workshop | Z9: Unclassified | AA9: Kitchen Equipment | AB9: EDL
A10: Month | B10: Total Income | C10: Expenses | D10: Revenue | E10: Net Benefit | F10: Net Margin | G10: Month controls the visible dates and selected totals. Revenue Stream filters income and Revenue. Activity, Expense Category, Expense Type and Supplier filter Expenses. The revenue and expense filters are independent. Total Income = Walk-in + Colonie + Birthday for the selected stream. Source Daily Expenses is blank, so Income and Revenue match. Net Benefit = Revenue − master expenses. July 1 has no income-source row and remains marked as missing. | Z10: Utilities & Office | AA10: Maintenance | AB10: Ets Melhem Yamine & Sons
A11: =IF($B$3="All","July 2026",$B$3) -> July 2026 | B11: =SUM(E17:E47) -> 19095 | C11: =SUM(F17:F47) -> 4921.815 | D11: =SUM(G17:G47) -> 19095 | E11: =D11-C11 -> 14173.185 | F11: =IFERROR(E11/D11,0) -> 0.74224588 | Z11: Workshop & Decoration Supplies | AA11: Other / Office | AB11: Event Megastore
A12: =IF($B$3="All","August 2026","") -> August 2026 | B12: =IF($B$3="All",SUM(E48:E78),"") -> 13654 | C12: =IF($B$3="All",SUM(F48:F78),"") -> 1730.8633 | D12: =IF($B$3="All",SUM(G48:G78),"") -> 13654 | E12: =IF(A12="","",D12-C12) -> 11923.137 | F12: =IF(A12="","",IFERROR(E12/D12,0)) -> 0.87323398 | AA12: Packaging & Disposables | AB12: Fadi
A13: Selected Total | B13: =SUM(B11:B12) -> 32749 | C13: =SUM(C11:C12) -> 6652.6783 | D13: =SUM(D11:D12) -> 32749 | E13: =SUM(E11:E12) -> 26096.322 | F13: =IFERROR(E13/D13,0) -> 0.79685858 | AA13: Waste Removal | AB13: Fairco International
AA14: Water | AB14: Forn Zakhia
A15: Daily Unified Table | AB15: Fresh & More
A16: Date | B16: Walk-in Income | C16: Colonie Income | D16: Birthday Income | E16: Total Income | F16: Expenses | G16: Revenue | H16: Net Benefit | I16: Net Margin | J16: Source Status | AB16: Imaco
A17: =IF($B$3="All",46204,IF(0<31,IF($B$3="July 2026",46204,46235)+0,"")) -> 46204 | B17: =IF(A17="","",IF(COUNTIFS('Income Source'!$B$5:$B$65,A17)=0,"",IF(OR($Q$3="All",$Q$3="Walk-in"),SUMIFS('Income Source'!$C$5:$C$65,'Income Source'!$B$5:$B$65,A17),0))) | C17: =IF(A17="","",IF(COUNTIFS('Income Source'!$B$5:$B$65,A17)=0,"",IF(OR($Q$3="All",$Q$3="Colonie"),SUMIFS('Income Source'!$D$5:$D$65,'Income Source'!$B$5:$B$65,A17),0))) | D17: =IF(A17="","",IF(COUNTIFS('Income Source'!$B$5:$B$65,A17)=0,"",IF(OR($Q$3="All",$Q$3="Birthday"),SUMIFS('Income Source'!$E$5:$E$65,'Income Source'!$B$5:$B$65,A17),0))) | E17: =IF(A17="","",IF(COUNTIFS('Income Source'!$B$5:$B$65,A17)=0,"",SUM(B17:D17))) | F17: =IF(A17="","",SUMIFS('Expense Source'!$M$5:$M$178,'Expense Source'!$D$5:$D$178,A17,'Expense Source'!$U$5:$U$178,1)) -> 0 | G17: =IF(A17="","",IF(COUNTIFS('Income Source'!$B$5:$B$65,A17)=0,"",IF($Q$3="All",SUMIFS('Income Source'!$G$5:$G$65,'Income Source'!$B$5:$B$65,A17),SUM(B17:D17)))) | H17: =IF(A17="","",IF(COUNTIFS('Income Source'!$B$5:$B$65,A17)=0,"",G17-F17)) | I17: =IF(OR(A17="",COUNTIFS('Income Source'!$B$5:$B$65,A17)=0,G17=0),"",H17/G17) | J17: =IF(A17="","",IF(COUNTIFS('Income Source'!$B$5:$B$65,A17)=0,"Revenue source missing",IF(ABS(E17-G17)>0.005,"Income/revenue mismatch","OK"))) -> Revenue source missing | AB17: Internet
A18: =IF($B$3="All",46205,IF(1<31,IF($B$3="July 2026",46204,46235)+1,"")) -> 46205 | B18: =IF(A18="","",IF(COUNTIFS('Income Source'!$B$5:$B$65,A18)=0,"",IF(OR($Q$3="All",$Q$3="Walk-in"),SUMIFS('Income Source'!$C$5:$C$65,'Income Source'!$B$5:$B$65,A18),0))) -> 0 | C18: =IF(A18="","",IF(COUNTIFS('Income Source'!$B$5:$B$65,A18)=0,"",IF(OR($Q$3="All",$Q$3="Colonie"),SUMIFS('Income Source'!$D$5:$D$65,'Income Source'!$B$5:$B$65,A18),0))) -> 520 | D18: =IF(A18="","",IF(COUNTIFS('Income Source'!$B$5:$B$65,A18)=0,"",IF(OR($Q$3="All",$Q$3="Birthday"),SUMIFS('Income Source'!$E$5:$E$65,'Income Source'!$B$5:$B$65,A18),0))) -> 0 | E18: =IF(A18="","",IF(COUNTIFS('Income Source'!$B$5:$B$65,A18)=0,"",SUM(B18:D18))) -> 520 | F18: =IF(A18="","",SUMIFS('Expense Source'!$M$5:$M$178,'Expense Source'!$D$5:$D$178,A18,'Expense Source'!$U$5:$U$178,1)) -> 0 | G18: =IF(A18="","",IF(COUNTIFS('Income Source'!$B$5:$B$65,A18)=0,"",IF($Q$3="All",SUMIFS('Income Source'!$G$5:$G$65,'Income Source'!$B$5:$B$65,A18),SUM(B18:D18)))) -> 520 | H18: =IF(A18="","",IF(COUNTIFS('Income Source'!$B$5:$B$65,A18)=0,"",G18-F18)) -> 520 | I18: =IF(OR(A18="",COUNTIFS('Income Source'!$B$5:$B$65,A18)=0,G18=0),"",H18/G18) -> 1 | J18: =IF(A18="","",IF(COUNTIFS('Income Source'!$B$5:$B$65,A18)=0,"Revenue source missing",IF(ABS(E18-G18)>0.005,"Income/revenue mismatch","OK"))) -> OK | AB18: Jamil Rezk
A19: =IF($B$3="All",46206,IF(2<31,IF($B$3="July 2026",46204,46235)+2,"")) -> 46206 | B19: =IF(A19="","",IF(COUNTIFS('Income Source'!$B$5:$B$65,A19)=0,"",IF(OR($Q$3="All",$Q$3="Walk-in"),SUMIFS('Income Source'!$C$5:$C$65,'Income Source'!$B$5:$B$65,A19),0))) -> 0 | C19: =IF(A19="","",IF(COUNTIFS('Income Source'!$B$5:$B$65,A19)=0,"",IF(OR($Q$3="All",$Q$3="Colonie"),SUMIFS('Income Source'!$D$5:$D$65,'Income Source'!$B$5:$B$65,A19),0))) -> 0 | D19: =IF(A19="","",IF(COUNTIFS('Income Source'!$B$5:$B$65,A19)=0,"",IF(OR($Q$3="All",$Q$3="Birthday"),SUMIFS('Income Source'!$E$5:$E$65,'Income Source'!$B$5:$B$65,A19),0))) -> 434 | E19: =IF(A19="","",IF(COUNTIFS('Income Source'!$B$5:$B$65,A19)=0,"",SUM(B19:D19))) -> 434 | F19: =IF(A19="","",SUMIFS('Expense Source'!$M$5:$M$178,'Expense Source'!$D$5:$D$178,A19,'Expense Source'!$U$5:$U$178,1)) -> 0 | G19: =IF(A19="","",IF(COUNTIFS('Income Source'!$B$5:$B$65,A19)=0,"",IF($Q$3="All",SUMIFS('Income Source'!$G$5:$G$65,'Income Source'!$B$5:$B$65,A19),SUM(B19:D19)))) -> 434 | H19: =IF(A19="","",IF(COUNTIFS('Income Source'!$B$5:$B$65,A19)=0,"",G19-F19)) -> 434 | I19: =IF(OR(A19="",COUNTIFS('Income Source'!$B$5:$B$65,A19)=0,G19=0),"",H19/G19) -> 1 | J19: =IF(A19="","",IF(COUNTIFS('Income Source'!$B$5:$B$65,A19)=0,"Revenue source missing",IF(ABS(E19-G19)>0.005,"Income/revenue mismatch","OK"))) -> OK | AB19: Joe Market
A20: =IF($B$3="All",46207,IF(3<31,IF($B$3="July 2026",46204,46235)+3,"")) -> 46207 | B20: =IF(A20="","",IF(COUNTIFS('Income Source'!$B$5:$B$65,A20)=0,"",IF(OR($Q$3="All",$Q$3="Walk-in"),SUMIFS('Income Source'!$C$5:$C$65,'Income Source'!$B$5:$B$65,A20),0))) -> 238 | C20: =IF(A20="","",IF(COUNTIFS('Income Source'!$B$5:$B$65,A20)=0,"",IF(OR($Q$3="All",$Q$3="Colonie"),SUMIFS('Income Source'!$D$5:$D$65,'Income Source'!$B$5:$B$65,A20),0))) -> 100 | D20: =IF(A20="","",IF(COUNTIFS('Income Source'!$B$5:$B$65,A20)=0,"",IF(OR($Q$3="All",$Q$3="Birthday"),SUMIFS('Income Source'!$E$5:$E$65,'Income Source'!$B$5:$B$65,A20),0))) -> 751 | E20: =IF(A20="","",IF(COUNTIFS('Income Source'!$B$5:$B$65,A20)=0,"",SUM(B20:D20))) -> 1089 | F20: =IF(A20="","",SUMIFS('Expense Source'!$M$5:$M$178,'Expense Source'!$D$5:$D$178,A20,'Expense Source'!$U$5:$U$178,1)) -> 106.63034 | G20: =IF(A20="","",IF(COUNTIFS('Income Source'!$B$5:$B$65,A20)=0,"",IF($Q$3="All",SUMIFS('Income Source'!$G$5:$G$65,'Income Source'!$B$5:$B$65,A20),SUM(B20:D20)))) -> 1089 | H20: =IF(A20="","",IF(COUNTIFS('Income Source'!$B$5:$B$65,A20)=0,"",G20-F20)) -> 982.36966 | I20: =IF(OR(A20="",COUNTIFS('Income Source'!$B$5:$B$65,A20)=0,G20=0),"",H20/G20) -> 0.90208417 | J20: =IF(A20="","",IF(COUNTIFS('Income Source'!$B$5:$B$65,A20)=0,"Revenue source missing",IF(ABS(E20-G20)>0.005,"Income/revenue mismatch","OK"))) -> OK | AB20: Karam Bake
A21: =IF($B$3="All",46208,IF(4<31,IF($B$3="July 2026",46204,46235)+4,"")) -> 46208 | B21: =IF(A21="","",IF(COUNTIFS('Income Source'!$B$5:$B$65,A21)=0,"",IF(OR($Q$3="All",$Q$3="Walk-in"),SUMIFS('Income Source'!$C$5:$C$65,'Income Source'!$B$5:$B$65,A21),0))) -> 241 | C21: =IF(A21="","",IF(COUNTIFS('Income Source'!$B$5:$B$65,A21)=0,"",IF(OR($Q$3="All",$Q$3="Colonie"),SUMIFS('Income Source'!$D$5:$D$65,'Income Source'!$B$5:$B$65,A21),0))) -> 0 | D21: =IF(A21="","",IF(COUNTIFS('Income Source'!$B$5:$B$65,A21)=0,"",IF(OR($Q$3="All",$Q$3="Birthday"),SUMIFS('Income Source'!$E$5:$E$65,'Income Source'!$B$5:$B$65,A21),0))) -> 750 | E21: =IF(A21="","",IF(COUNTIFS('Income Source'!$B$5:$B$65,A21)=0,"",SUM(B21:D21))) -> 991 | F21: =IF(A21="","",SUMIFS('Expense Source'!$M$5:$M$178,'Expense Source'!$D$5:$D$178,A21,'Expense Source'!$U$5:$U$178,1)) -> 510.71 | G21: =IF(A21="","",IF(COUNTIFS('Income Source'!$B$5:$B$65,A21)=0,"",IF($Q$3="All",SUMIFS('Income Source'!$G$5:$G$65,'Income Source'!$B$5:$B$65,A21),SUM(B21:D21)))) -> 991 | H21: =IF(A21="","",IF(COUNTIFS('Income Source'!$B$5:$B$65,A21)=0,"",G21-F21)) -> 480.29 | I21: =IF(OR(A21="",COUNTIFS('Income Source'!$B$5:$B$65,A21)=0,G21=0),"",H21/G21) -> 0.48465187 | J21: =IF(A21="","",IF(COUNTIFS('Income Source'!$B$5:$B$65,A21)=0,"Revenue source missing",IF(ABS(E21-G21)>0.005,"Income/revenue mismatch","OK"))) -> OK | AB21: La Valeur Market
A22: =IF($B$3="All",46209,IF(5<31,IF($B$3="July 2026",46204,46235)+5,"")) -> 46209 | B22: =IF(A22="","",IF(COUNTIFS('Income Source'!$B$5:$B$65,A22)=0,"",IF(OR($Q$3="All",$Q$3="Walk-in"),SUMIFS('Income Source'!$C$5:$C$65,'Income Source'!$B$5:$B$65,A22),0))) -> 0 | C22: =IF(A22="","",IF(COUNTIFS('Income Source'!$B$5:$B$65,A22)=0,"",IF(OR($Q$3="All",$Q$3="Colonie"),SUMIFS('Income Source'!$D$5:$D$65,'Income Source'!$B$5:$B$65,A22),0))) -> 0 | D22: =IF(A22="","",IF(COUNTIFS('Income Source'!$B$5:$B$65,A22)=0,"",IF(OR($Q$3="All",$Q$3="Birthday"),SUMIFS('Income Source'!$E$5:$E$65,'Income Source'!$B$5:$B$65,A22),0))) -> 0 | E22: =IF(A22="","",IF(COUNTIFS('Income Source'!$B$5:$B$65,A22)=0,"",SUM(B22:D22))) -> 0 | F22: =IF(A22="","",SUMIFS('Expense Source'!$M$5:$M$178,'Expense Source'!$D$5:$D$178,A22,'Expense Source'!$U$5:$U$178,1)) -> 0 | G22: =IF(A22="","",IF(COUNTIFS('Income Source'!$B$5:$B$65,A22)=0,"",IF($Q$3="All",SUMIFS('Income Source'!$G$5:$G$65,'Income Source'!$B$5:$B$65,A22),SUM(B22:D22)))) -> 0 | H22: =IF(A22="","",IF(COUNTIFS('Income Source'!$B$5:$B$65,A22)=0,"",G22-F22)) -> 0 | I22: =IF(OR(A22="",COUNTIFS('Income Source'!$B$5:$B$65,A22)=0,G22=0),"",H22/G22) | J22: =IF(A22="","",IF(COUNTIFS('Income Source'!$B$5:$B$65,A22)=0,"Revenue source missing",IF(ABS(E22-G22)>0.005,"Income/revenue mismatch","OK"))) -> OK | AB22: Le Charcutier
A23: =IF($B$3="All",46210,IF(6<31,IF($B$3="July 2026",46204,46235)+6,"")) -> 46210 | B23: =IF(A23="","",IF(COUNTIFS('Income Source'!$B$5:$B$65,A23)=0,"",IF(OR($Q$3="All",$Q$3="Walk-in"),SUMIFS('Income Source'!$C$5:$C$65,'Income Source'!$B$5:$B$65,A23),0))) -> 0 | C23: =IF(A23="","",IF(COUNTIFS('Income Source'!$B$5:$B$65,A23)=0,"",IF(OR($Q$3="All",$Q$3="Colonie"),SUMIFS('Income Source'!$D$5:$D$65,'Income Source'!$B$5:$B$65,A23),0))) -> 0 | D23: =IF(A23="","",IF(COUNTIFS('Income Source'!$B$5:$B$65,A23)=0,"",IF(OR($Q$3="All",$Q$3="Birthday"),SUMIFS('Income Source'!$E$5:$E$65,'Income Source'!$B$5:$B$65,A23),0))) -> 0 | E23: =IF(A23="","",IF(COUNTIFS('Income Source'!$B$5:$B$65,A23)=0,"",SUM(B23:D23))) -> 0 | F23: =IF(A23="","",SUMIFS('Expense Source'!$M$5:$M$178,'Expense Source'!$D$5:$D$178,A23,'Expense Source'!$U$5:$U$178,1)) -> 0 | G23: =IF(A23="","",IF(COUNTIFS('Income Source'!$B$5:$B$65,A23)=0,"",IF($Q$3="All",SUMIFS('Income Source'!$G$5:$G$65,'Income Source'!$B$5:$B$65,A23),SUM(B23:D23)))) -> 0 | H23: =IF(A23="","",IF(COUNTIFS('Income Source'!$B$5:$B$65,A23)=0,"",G23-F23)) -> 0 | I23: =IF(OR(A23="",COUNTIFS('Income Source'!$B$5:$B$65,A23)=0,G23=0),"",H23/G23) | J23: =IF(A23="","",IF(COUNTIFS('Income Source'!$B$5:$B$65,A23)=0,"Revenue source missing",IF(ABS(E23-G23)>0.005,"Income/revenue mismatch","OK"))) -> OK | AB23: Le Marche Selectif
A24: =IF($B$3="All",46211,IF(7<31,IF($B$3="July 2026",46204,46235)+7,"")) -> 46211 | B24: =IF(A24="","",IF(COUNTIFS('Income Source'!$B$5:$B$65,A24)=0,"",IF(OR($Q$3="All",$Q$3="Walk-in"),SUMIFS('Income Source'!$C$5:$C$65,'Income Source'!$B$5:$B$65,A24),0))) -> 0 | C24: =IF(A24="","",IF(COUNTIFS('Income Source'!$B$5:$B$65,A24)=0,"",IF(OR($Q$3="All",$Q$3="Colonie"),SUMIFS('Income Source'!$D$5:$D$65,'Income Source'!$B$5:$B$65,A24),0))) -> 760 | D24: =IF(A24="","",IF(COUNTIFS('Income Source'!$B$5:$B$65,A24)=0,"",IF(OR($Q$3="All",$Q$3="Birthday"),SUMIFS('Income Source'!$E$5:$E$65,'Income Source'!$B$5:$B$65,A24),0))) -> 625 | E24: =IF(A24="","",IF(COUNTIFS('Income Source'!$B$5:$B$65,A24)=0,"",SUM(B24:D24))) -> 1385 | F24: =IF(A24="","",SUMIFS('Expense Source'!$M$5:$M$178,'Expense Source'!$D$5:$D$178,A24,'Expense Source'!$U$5:$U$178,1)) -> 88.34 | G24: =IF(A24="","",IF(COUNTIFS('Income Source'!$B$5:$B$65,A24)=0,"",IF($Q$3="All",SUMIFS('Income Source'!$G$5:$G$65,'Income Source'!$B$5:$B$65,A24),SUM(B24:D24)))) -> 1385 | H24: =IF(A24="","",IF(COUNTIFS('Income Source'!$B$5:$B$65,A24)=0,"",G24-F24)) -> 1296.66 | I24: =IF(OR(A24="",COUNTIFS('Income Source'!$B$5:$B$65,A24)=0,G24=0),"",H24/G24) -> 0.93621661 | J24: =IF(A24="","",IF(COUNTIFS('Income Source'!$B$5:$B$65,A24)=0,"Revenue source missing",IF(ABS(E24-G24)>0.005,"Income/revenue mismatch","OK"))) -> OK | AB24: Librairie Mallah
A25: =IF($B$3="All",46212,IF(8<31,IF($B$3="July 2026",46204,46235)+8,"")) -> 46212 | B25: =IF(A25="","",IF(COUNTIFS('Income Source'!$B$5:$B$65,A25)=0,"",IF(OR($Q$3="All",$Q$3="Walk-in"),SUMIFS('Income Source'!$C$5:$C$65,'Income Source'!$B$5:$B$65,A25),0))) -> 0 | C25: =IF(A25="","",IF(COUNTIFS('Income Source'!$B$5:$B$65,A25)=0,"",IF(OR($Q$3="All",$Q$3="Colonie"),SUMIFS('Income Source'!$D$5:$D$65,'Income Source'!$B$5:$B$65,A25),0))) -> 528 | D25: =IF(A25="","",IF(COUNTIFS('Income Source'!$B$5:$B$65,A25)=0,"",IF(OR($Q$3="All",$Q$3="Birthday"),SUMIFS('Income Source'!$E$5:$E$65,'Income Source'!$B$5:$B$65,A25),0))) -> 0 | E25: =IF(A25="","",IF(COUNTIFS('Income Source'!$B$5:$B$65,A25)=0,"",SUM(B25:D25))) -> 528 | F25: =IF(A25="","",SUMIFS('Expense Source'!$M$5:$M$178,'Expense Source'!$D$5:$D$178,A25,'Expense Source'!$U$5:$U$178,1)) -> 0 | G25: =IF(A25="","",IF(COUNTIFS('Income Source'!$B$5:$B$65,A25)=0,"",IF($Q$3="All",SUMIFS('Income Source'!$G$5:$G$65,'Income Source'!$B$5:$B$65,A25),SUM(B25:D25)))) -> 528 | H25: =IF(A25="","",IF(COUNTIFS('Income Source'!$B$5:$B$65,A25)=0,"",G25-F25)) -> 528 | I25: =IF(OR(A25="",COUNTIFS('Income Source'!$B$5:$B$65,A25)=0,G25=0),"",H25/G25) -> 1 | J25: =IF(A25="","",IF(COUNTIFS('Income Source'!$B$5:$B$65,A25)=0,"Revenue source missing",IF(ABS(E25-G25)>0.005,"Income/revenue mismatch","OK"))) -> OK | AB25: Lteif Market
A26: =IF($B$3="All",46213,IF(9<31,IF($B$3="July 2026",46204,46235)+9,"")) -> 46213 | B26: =IF(A26="","",IF(COUNTIFS('Income Source'!$B$5:$B$65,A26)=0,"",IF(OR($Q$3="All",$Q$3="Walk-in"),SUMIFS('Income Source'!$C$5:$C$65,'Income Source'!$B$5:$B$65,A26),0))) -> 0 | C26: =IF(A26="","",IF(COUNTIFS('Income Source'!$B$5:$B$65,A26)=0,"",IF(OR($Q$3="All",$Q$3="Colonie"),SUMIFS('Income Source'!$D$5:$D$65,'Income Source'!$B$5:$B$65,A26),0))) -> 384 | D26: =IF(A26="","",IF(COUNTIFS('Income Source'!$B$5:$B$65,A26)=0,"",IF(OR($Q$3="All",$Q$3="Birthday"),SUMIFS('Income Source'!$E$5:$E$65,'Income Source'!$B$5:$B$65,A26),0))) -> 755 | E26: =IF(A26="","",IF(COUNTIFS('Income Source'!$B$5:$B$65,A26)=0,"",SUM(B26:D26))) -> 1139 | F26: =IF(A26="","",SUMIFS('Expense Source'!$M$5:$M$178,'Expense Source'!$D$5:$D$178,A26,'Expense Source'!$U$5:$U$178,1)) -> 625.79 | G26: =IF(A26="","",IF(COUNTIFS('Income Source'!$B$5:$B$65,A26)=0,"",IF($Q$3="All",SUMIFS('Income Source'!$G$5:$G$65,'Income Source'!$B$5:$B$65,A26),SUM(B26:D26)))) -> 1139 | H26: =IF(A26="","",IF(COUNTIFS('Income Source'!$B$5:$B$65,A26)=0,"",G26-F26)) -> 513.21 | I26: =IF(OR(A26="",COUNTIFS('Income Source'!$B$5:$B$65,A26)=0,G26=0),"",H26/G26) -> 0.45057946 | J26: =IF(A26="","",IF(COUNTIFS('Income Source'!$B$5:$B$65,A26)=0,"Revenue source missing",IF(ABS(E26-G26)>0.005,"Income/revenue mismatch","OK"))) -> OK | AB26: Luicci
A27: =IF($B$3="All",46214,IF(10<31,IF($B$3="July 2026",46204,46235)+10,"")) -> 46214 | B27: =IF(A27="","",IF(COUNTIFS('Income Source'!$B$5:$B$65,A27)=0,"",IF(OR($Q$3="All",$Q$3="Walk-in"),SUMIFS('Income Source'!$C$5:$C$65,'Income Source'!$B$5:$B$65,A27),0))) -> 453 | C27: =IF(A27="","",IF(COUNTIFS('Income Source'!$B$5:$B$65,A27)=0,"",IF(OR($Q$3="All",$Q$3="Colonie"),SUMIFS('Income Source'!$D$5:$D$65,'Income Source'!$B$5:$B$65,A27),0))) -> 0 | D27: =IF(A27="","",IF(COUNTIFS('Income Source'!$B$5:$B$65,A27)=0,"",IF(OR($Q$3="All",$Q$3="Birthday"),SUMIFS('Income Source'!$E$5:$E$65,'Income Source'!$B$5:$B$65,A27),0))) -> 1335 | E27: =IF(A27="","",IF(COUNTIFS('Income Source'!$B$5:$B$65,A27)=0,"",SUM(B27:D27))) -> 1788 | F27: =IF(A27="","",SUMIFS('Expense Source'!$M$5:$M$178,'Expense Source'!$D$5:$D$178,A27,'Expense Source'!$U$5:$U$178,1)) -> 182.25 | G27: =IF(A27="","",IF(COUNTIFS('Income Source'!$B$5:$B$65,A27)=0,"",IF($Q$3="All",SUMIFS('Income Source'!$G$5:$G$65,'Income Source'!$B$5:$B$65,A27),SUM(B27:D27)))) -> 1788 | H27: =IF(A27="","",IF(COUNTIFS('Income Source'!$B$5:$B$65,A27)=0,"",G27-F27)) -> 1605.75 | I27: =IF(OR(A27="",COUNTIFS('Income Source'!$B$5:$B$65,A27)=0,G27=0),"",H27/G27) -> 0.89807047 | J27: =IF(A27="","",IF(COUNTIFS('Income Source'!$B$5:$B$65,A27)=0,"Revenue source missing",IF(ABS(E27-G27)>0.005,"Income/revenue mismatch","OK"))) -> OK | AB27: Panino Bakery
A28: =IF($B$3="All",46215,IF(11<31,IF($B$3="July 2026",46204,46235)+11,"")) -> 46215 | B28: =IF(A28="","",IF(COUNTIFS('Income Source'!$B$5:$B$65,A28)=0,"",IF(OR($Q$3="All",$Q$3="Walk-in"),SUMIFS('Income Source'!$C$5:$C$65,'Income Source'!$B$5:$B$65,A28),0))) -> 370 | C28: =IF(A28="","",IF(COUNTIFS('Income Source'!$B$5:$B$65,A28)=0,"",IF(OR($Q$3="All",$Q$3="Colonie"),SUMIFS('Income Source'!$D$5:$D$65,'Income Source'!$B$5:$B$65,A28),0))) -> 0 | D28: =IF(A28="","",IF(COUNTIFS('Income Source'!$B$5:$B$65,A28)=0,"",IF(OR($Q$3="All",$Q$3="Birthday"),SUMIFS('Income Source'!$E$5:$E$65,'Income Source'!$B$5:$B$65,A28),0))) -> 550 | E28: =IF(A28="","",IF(COUNTIFS('Income Source'!$B$5:$B$65,A28)=0,"",SUM(B28:D28))) -> 920 | F28: =IF(A28="","",SUMIFS('Expense Source'!$M$5:$M$178,'Expense Source'!$D$5:$D$178,A28,'Expense Source'!$U$5:$U$178,1)) -> 193.1964 | G28: =IF(A28="","",IF(COUNTIFS('Income Source'!$B$5:$B$65,A28)=0,"",IF($Q$3="All",SUMIFS('Income Source'!$G$5:$G$65,'Income Source'!$B$5:$B$65,A28),SUM(B28:D28)))) -> 920 | H28: =IF(A28="","",IF(COUNTIFS('Income Source'!$B$5:$B$65,A28)=0,"",G28-F28)) -> 726.8036 | I28: =IF(OR(A28="",COUNTIFS('Income Source'!$B$5:$B$65,A28)=0,G28=0),"",H28/G28) -> 0.79000391 | J28: =IF(A28="","",IF(COUNTIFS('Income Source'!$B$5:$B$65,A28)=0,"Revenue source missing",IF(ABS(E28-G28)>0.005,"Income/revenue mismatch","OK"))) -> OK | AB28: Polavera
A29: =IF($B$3="All",46216,IF(12<31,IF($B$3="July 2026",46204,46235)+12,"")) -> 46216 | B29: =IF(A29="","",IF(COUNTIFS('Income Source'!$B$5:$B$65,A29)=0,"",IF(OR($Q$3="All",$Q$3="Walk-in"),SUMIFS('Income Source'!$C$5:$C$65,'Income Source'!$B$5:$B$65,A29),0))) -> 0 | C29: =IF(A29="","",IF(COUNTIFS('Income Source'!$B$5:$B$65,A29)=0,"",IF(OR($Q$3="All",$Q$3="Colonie"),SUMIFS('Income Source'!$D$5:$D$65,'Income Source'!$B$5:$B$65,A29),0))) -> 0 | D29: =IF(A29="","",IF(COUNTIFS('Income Source'!$B$5:$B$65,A29)=0,"",IF(OR($Q$3="All",$Q$3="Birthday"),SUMIFS('Income Source'!$E$5:$E$65,'Income Source'!$B$5:$B$65,A29),0))) -> 0 | E29: =IF(A29="","",IF(COUNTIFS('Income Source'!$B$5:$B$65,A29)=0,"",SUM(B29:D29))) -> 0 | F29: =IF(A29="","",SUMIFS('Expense Source'!$M$5:$M$178,'Expense Source'!$D$5:$D$178,A29,'Expense Source'!$U$5:$U$178,1)) -> 0 | G29: =IF(A29="","",IF(COUNTIFS('Income Source'!$B$5:$B$65,A29)=0,"",IF($Q$3="All",SUMIFS('Income Source'!$G$5:$G$65,'Income Source'!$B$5:$B$65,A29),SUM(B29:D29)))) -> 0 | H29: =IF(A29="","",IF(COUNTIFS('Income Source'!$B$5:$B$65,A29)=0,"",G29-F29)) -> 0 | I29: =IF(OR(A29="",COUNTIFS('Income Source'!$B$5:$B$65,A29)=0,G29=0),"",H29/G29) | J29: =IF(A29="","",IF(COUNTIFS('Income Source'!$B$5:$B$65,A29)=0,"Revenue source missing",IF(ABS(E29-G29)>0.005,"Income/revenue mismatch","OK"))) -> OK | AB29: Ramel Mgharbal, Trabeh
A30: =IF($B$3="All",46217,IF(13<31,IF($B$3="July 2026",46204,46235)+13,"")) -> 46217 | B30: =IF(A30="","",IF(COUNTIFS('Income Source'!$B$5:$B$65,A30)=0,"",IF(OR($Q$3="All",$Q$3="Walk-in"),SUMIFS('Income Source'!$C$5:$C$65,'Income Source'!$B$5:$B$65,A30),0))) -> 0 | C30: =IF(A30="","",IF(COUNTIFS('Income Source'!$B$5:$B$65,A30)=0,"",IF(OR($Q$3="All",$Q$3="Colonie"),SUMIFS('Income Source'!$D$5:$D$65,'Income Source'!$B$5:$B$65,A30),0))) -> 0 | D30: =IF(A30="","",IF(COUNTIFS('Income Source'!$B$5:$B$65,A30)=0,"",IF(OR($Q$3="All",$Q$3="Birthday"),SUMIFS('Income Source'!$E$5:$E$65,'Income Source'!$B$5:$B$65,A30),0))) -> 0 | E30: =IF(A30="","",IF(COUNTIFS('Income Source'!$B$5:$B$65,A30)=0,"",SUM(B30:D30))) -> 0 | F30: =IF(A30="","",SUMIFS('Expense Source'!$M$5:$M$178,'Expense Source'!$D$5:$D$178,A30,'Expense Source'!$U$5:$U$178,1)) -> 0 | G30: =IF(A30="","",IF(COUNTIFS('Income Source'!$B$5:$B$65,A30)=0,"",IF($Q$3="All",SUMIFS('Income Source'!$G$5:$G$65,'Income Source'!$B$5:$B$65,A30),SUM(B30:D30)))) -> 0 | H30: =IF(A30="","",IF(COUNTIFS('Income Source'!$B$5:$B$65,A30)=0,"",G30-F30)) -> 0 | I30: =IF(OR(A30="",COUNTIFS('Income Source'!$B$5:$B$65,A30)=0,G30=0),"",H30/G30) | J30: =IF(A30="","",IF(COUNTIFS('Income Source'!$B$5:$B$65,A30)=0,"Revenue source missing",IF(ABS(E30-G30)>0.005,"Income/revenue mismatch","OK"))) -> OK | AB30: Rim Water
A31: =IF($B$3="All",46218,IF(14<31,IF($B$3="July 2026",46204,46235)+14,"")) -> 46218 | B31: =IF(A31="","",IF(COUNTIFS('Income Source'!$B$5:$B$65,A31)=0,"",IF(OR($Q$3="All",$Q$3="Walk-in"),SUMIFS('Income Source'!$C$5:$C$65,'Income Source'!$B$5:$B$65,A31),0))) -> 0 | C31: =IF(A31="","",IF(COUNTIFS('Income Source'!$B$5:$B$65,A31)=0,"",IF(OR($Q$3="All",$Q$3="Colonie"),SUMIFS('Income Source'!$D$5:$D$65,'Income Source'!$B$5:$B$65,A31),0))) -> 0 | D31: =IF(A31="","",IF(COUNTIFS('Income Source'!$B$5:$B$65,A31)=0,"",IF(OR($Q$3="All",$Q$3="Birthday"),SUMIFS('Income Source'!$E$5:$E$65,'Income Source'!$B$5:$B$65,A31),0))) -> 0 | E31: =IF(A31="","",IF(COUNTIFS('Income Source'!$B$5:$B$65,A31)=0,"",SUM(B31:D31))) -> 0 | F31: =IF(A31="","",SUMIFS('Expense Source'!$M$5:$M$178,'Expense Source'!$D$5:$D$178,A31,'Expense Source'!$U$5:$U$178,1)) -> 0 | G31: =IF(A31="","",IF(COUNTIFS('Income Source'!$B$5:$B$65,A31)=0,"",IF($Q$3="All",SUMIFS('Income Source'!$G$5:$G$65,'Income Source'!$B$5:$B$65,A31),SUM(B31:D31)))) -> 0 | H31: =IF(A31="","",IF(COUNTIFS('Income Source'!$B$5:$B$65,A31)=0,"",G31-F31)) -> 0 | I31: =IF(OR(A31="",COUNTIFS('Income Source'!$B$5:$B$65,A31)=0,G31=0),"",H31/G31) | J31: =IF(A31="","",IF(COUNTIFS('Income Source'!$B$5:$B$65,A31)=0,"Revenue source missing",IF(ABS(E31-G31)>0.005,"Income/revenue mismatch","OK"))) -> OK | AB31: Spinneys
A32: =IF($B$3="All",46219,IF(15<31,IF($B$3="July 2026",46204,46235)+15,"")) -> 46219 | B32: =IF(A32="","",IF(COUNTIFS('Income Source'!$B$5:$B$65,A32)=0,"",IF(OR($Q$3="All",$Q$3="Walk-in"),SUMIFS('Income Source'!$C$5:$C$65,'Income Source'!$B$5:$B$65,A32),0))) -> 0 | C32: =IF(A32="","",IF(COUNTIFS('Income Source'!$B$5:$B$65,A32)=0,"",IF(OR($Q$3="All",$Q$3="Colonie"),SUMIFS('Income Source'!$D$5:$D$65,'Income Source'!$B$5:$B$65,A32),0))) -> 0 | D32: =IF(A32="","",IF(COUNTIFS('Income Source'!$B$5:$B$65,A32)=0,"",IF(OR($Q$3="All",$Q$3="Birthday"),SUMIFS('Income Source'!$E$5:$E$65,'Income Source'!$B$5:$B$65,A32),0))) -> 0 | E32: =IF(A32="","",IF(COUNTIFS('Income Source'!$B$5:$B$65,A32)=0,"",SUM(B32:D32))) -> 0 | F32: =IF(A32="","",SUMIFS('Expense Source'!$M$5:$M$178,'Expense Source'!$D$5:$D$178,A32,'Expense Source'!$U$5:$U$178,1)) -> 0 | G32: =IF(A32="","",IF(COUNTIFS('Income Source'!$B$5:$B$65,A32)=0,"",IF($Q$3="All",SUMIFS('Income Source'!$G$5:$G$65,'Income Source'!$B$5:$B$65,A32),SUM(B32:D32)))) -> 0 | H32: =IF(A32="","",IF(COUNTIFS('Income Source'!$B$5:$B$65,A32)=0,"",G32-F32)) -> 0 | I32: =IF(OR(A32="",COUNTIFS('Income Source'!$B$5:$B$65,A32)=0,G32=0),"",H32/G32) | J32: =IF(A32="","",IF(COUNTIFS('Income Source'!$B$5:$B$65,A32)=0,"Revenue source missing",IF(ABS(E32-G32)>0.005,"Income/revenue mismatch","OK"))) -> OK | AB32: St Joseph Pharmacy
A33: =IF($B$3="All",46220,IF(16<31,IF($B$3="July 2026",46204,46235)+16,"")) -> 46220 | B33: =IF(A33="","",IF(COUNTIFS('Income Source'!$B$5:$B$65,A33)=0,"",IF(OR($Q$3="All",$Q$3="Walk-in"),SUMIFS('Income Source'!$C$5:$C$65,'Income Source'!$B$5:$B$65,A33),0))) -> 284 | C33: =IF(A33="","",IF(COUNTIFS('Income Source'!$B$5:$B$65,A33)=0,"",IF(OR($Q$3="All",$Q$3="Colonie"),SUMIFS('Income Source'!$D$5:$D$65,'Income Source'!$B$5:$B$65,A33),0))) -> 0 | D33: =IF(A33="","",IF(COUNTIFS('Income Source'!$B$5:$B$65,A33)=0,"",IF(OR($Q$3="All",$Q$3="Birthday"),SUMIFS('Income Source'!$E$5:$E$65,'Income Source'!$B$5:$B$65,A33),0))) -> 520 | E33: =IF(A33="","",IF(COUNTIFS('Income Source'!$B$5:$B$65,A33)=0,"",SUM(B33:D33))) -> 804 | F33: =IF(A33="","",SUMIFS('Expense Source'!$M$5:$M$178,'Expense Source'!$D$5:$D$178,A33,'Expense Source'!$U$5:$U$178,1)) -> 732.31 | G33: =IF(A33="","",IF(COUNTIFS('Income Source'!$B$5:$B$65,A33)=0,"",IF($Q$3="All",SUMIFS('Income Source'!$G$5:$G$65,'Income Source'!$B$5:$B$65,A33),SUM(B33:D33)))) -> 804 | H33: =IF(A33="","",IF(COUNTIFS('Income Source'!$B$5:$B$65,A33)=0,"",G33-F33)) -> 71.69 | I33: =IF(OR(A33="",COUNTIFS('Income Source'!$B$5:$B$65,A33)=0,G33=0),"",H33/G33) -> 0.089166667 | J33: =IF(A33="","",IF(COUNTIFS('Income Source'!$B$5:$B$65,A33)=0,"Revenue source missing",IF(ABS(E33-G33)>0.005,"Income/revenue mismatch","OK"))) -> OK | AB33: Storium
A34: =IF($B$3="All",46221,IF(17<31,IF($B$3="July 2026",46204,46235)+17,"")) -> 46221 | B34: =IF(A34="","",IF(COUNTIFS('Income Source'!$B$5:$B$65,A34)=0,"",IF(OR($Q$3="All",$Q$3="Walk-in"),SUMIFS('Income Source'!$C$5:$C$65,'Income Source'!$B$5:$B$65,A34),0))) -> 330 | C34: =IF(A34="","",IF(COUNTIFS('Income Source'!$B$5:$B$65,A34)=0,"",IF(OR($Q$3="All",$Q$3="Colonie"),SUMIFS('Income Source'!$D$5:$D$65,'Income Source'!$B$5:$B$65,A34),0))) -> 0 | D34: =IF(A34="","",IF(COUNTIFS('Income Source'!$B$5:$B$65,A34)=0,"",IF(OR($Q$3="All",$Q$3="Birthday"),SUMIFS('Income Source'!$E$5:$E$65,'Income Source'!$B$5:$B$65,A34),0))) -> 1150 | E34: =IF(A34="","",IF(COUNTIFS('Income Source'!$B$5:$B$65,A34)=0,"",SUM(B34:D34))) -> 1480 | F34: =IF(A34="","",SUMIFS('Expense Source'!$M$5:$M$178,'Expense Source'!$D$5:$D$178,A34,'Expense Source'!$U$5:$U$178,1)) -> 218.049 | G34: =IF(A34="","",IF(COUNTIFS('Income Source'!$B$5:$B$65,A34)=0,"",IF($Q$3="All",SUMIFS('Income Source'!$G$5:$G$65,'Income Source'!$B$5:$B$65,A34),SUM(B34:D34)))) -> 1480 | H34: =IF(A34="","",IF(COUNTIFS('Income Source'!$B$5:$B$65,A34)=0,"",G34-F34)) -> 1261.951 | I34: =IF(OR(A34="",COUNTIFS('Income Source'!$B$5:$B$65,A34)=0,G34=0),"",H34/G34) -> 0.85266959 | J34: =IF(A34="","",IF(COUNTIFS('Income Source'!$B$5:$B$65,A34)=0,"Revenue source missing",IF(ABS(E34-G34)>0.005,"Income/revenue mismatch","OK"))) -> OK | AB34: Sunrise Market
A35: =IF($B$3="All",46222,IF(18<31,IF($B$3="July 2026",46204,46235)+18,"")) -> 46222 | B35: =IF(A35="","",IF(COUNTIFS('Income Source'!$B$5:$B$65,A35)=0,"",IF(OR($Q$3="All",$Q$3="Walk-in"),SUMIFS('Income Source'!$C$5:$C$65,'Income Source'!$B$5:$B$65,A35),0))) -> 77 | C35: =IF(A35="","",IF(COUNTIFS('Income Source'!$B$5:$B$65,A35)=0,"",IF(OR($Q$3="All",$Q$3="Colonie"),SUMIFS('Income Source'!$D$5:$D$65,'Income Source'!$B$5:$B$65,A35),0))) -> 0 | D35: =IF(A35="","",IF(COUNTIFS('Income Source'!$B$5:$B$65,A35)=0,"",IF(OR($Q$3="All",$Q$3="Birthday"),SUMIFS('Income Source'!$E$5:$E$65,'Income Source'!$B$5:$B$65,A35),0))) -> 525 | E35: =IF(A35="","",IF(COUNTIFS('Income Source'!$B$5:$B$65,A35)=0,"",SUM(B35:D35))) -> 602 | F35: =IF(A35="","",SUMIFS('Expense Source'!$M$5:$M$178,'Expense Source'!$D$5:$D$178,A35,'Expense Source'!$U$5:$U$178,1)) -> 124.49543 | G35: =IF(A35="","",IF(COUNTIFS('Income Source'!$B$5:$B$65,A35)=0,"",IF($Q$3="All",SUMIFS('Income Source'!$G$5:$G$65,'Income Source'!$B$5:$B$65,A35),SUM(B35:D35)))) -> 602 | H35: =IF(A35="","",IF(COUNTIFS('Income Source'!$B$5:$B$65,A35)=0,"",G35-F35)) -> 477.50457 | I35: =IF(OR(A35="",COUNTIFS('Income Source'!$B$5:$B$65,A35)=0,G35=0),"",H35/G35) -> 0.79319697 | J35: =IF(A35="","",IF(COUNTIFS('Income Source'!$B$5:$B$65,A35)=0,"Revenue source missing",IF(ABS(E35-G35)>0.005,"Income/revenue mismatch","OK"))) -> OK | AB35: Toni Nehme
A36: =IF($B$3="All",46223,IF(19<31,IF($B$3="July 2026",46204,46235)+19,"")) -> 46223 | B36: =IF(A36="","",IF(COUNTIFS('Income Source'!$B$5:$B$65,A36)=0,"",IF(OR($Q$3="All",$Q$3="Walk-in"),SUMIFS('Income Source'!$C$5:$C$65,'Income Source'!$B$5:$B$65,A36),0))) -> 0 | C36: =IF(A36="","",IF(COUNTIFS('Income Source'!$B$5:$B$65,A36)=0,"",IF(OR($Q$3="All",$Q$3="Colonie"),SUMIFS('Income Source'!$D$5:$D$65,'Income Source'!$B$5:$B$65,A36),0))) -> 0 | D36: =IF(A36="","",IF(COUNTIFS('Income Source'!$B$5:$B$65,A36)=0,"",IF(OR($Q$3="All",$Q$3="Birthday"),SUMIFS('Income Source'!$E$5:$E$65,'Income Source'!$B$5:$B$65,A36),0))) -> 0 | E36: =IF(A36="","",IF(COUNTIFS('Income Source'!$B$5:$B$65,A36)=0,"",SUM(B36:D36))) -> 0 | F36: =IF(A36="","",SUMIFS('Expense Source'!$M$5:$M$178,'Expense Source'!$D$5:$D$178,A36,'Expense Source'!$U$5:$U$178,1)) -> 45.39 | G36: =IF(A36="","",IF(COUNTIFS('Income Source'!$B$5:$B$65,A36)=0,"",IF($Q$3="All",SUMIFS('Income Source'!$G$5:$G$65,'Income Source'!$B$5:$B$65,A36),SUM(B36:D36)))) -> 0 | H36: =IF(A36="","",IF(COUNTIFS('Income Source'!$B$5:$B$65,A36)=0,"",G36-F36)) -> -45.39 | I36: =IF(OR(A36="",COUNTIFS('Income Source'!$B$5:$B$65,A36)=0,G36=0),"",H36/G36) | J36: =IF(A36="","",IF(COUNTIFS('Income Source'!$B$5:$B$65,A36)=0,"Revenue source missing",IF(ABS(E36-G36)>0.005,"Income/revenue mismatch","OK"))) -> OK | AB36: Toni Tohme Station
A37: =IF($B$3="All",46224,IF(20<31,IF($B$3="July 2026",46204,46235)+20,"")) -> 46224 | B37: =IF(A37="","",IF(COUNTIFS('Income Source'!$B$5:$B$65,A37)=0,"",IF(OR($Q$3="All",$Q$3="Walk-in"),SUMIFS('Income Source'!$C$5:$C$65,'Income Source'!$B$5:$B$65,A37),0))) -> 0 | C37: =IF(A37="","",IF(COUNTIFS('Income Source'!$B$5:$B$65,A37)=0,"",IF(OR($Q$3="All",$Q$3="Colonie"),SUMIFS('Income Source'!$D$5:$D$65,'Income Source'!$B$5:$B$65,A37),0))) -> 0 | D37: =IF(A37="","",IF(COUNTIFS('Income Source'!$B$5:$B$65,A37)=0,"",IF(OR($Q$3="All",$Q$3="Birthday"),SUMIFS('Income Source'!$E$5:$E$65,'Income Source'!$B$5:$B$65,A37),0))) -> 0 | E37: =IF(A37="","",IF(COUNTIFS('Income Source'!$B$5:$B$65,A37)=0,"",SUM(B37:D37))) -> 0 | F37: =IF(A37="","",SUMIFS('Expense Source'!$M$5:$M$178,'Expense Source'!$D$5:$D$178,A37,'Expense Source'!$U$5:$U$178,1)) -> 0 | G37: =IF(A37="","",IF(COUNTIFS('Income Source'!$B$5:$B$65,A37)=0,"",IF($Q$3="All",SUMIFS('Income Source'!$G$5:$G$65,'Income Source'!$B$5:$B$65,A37),SUM(B37:D37)))) -> 0 | H37: =IF(A37="","",IF(COUNTIFS('Income Source'!$B$5:$B$65,A37)=0,"",G37-F37)) -> 0 | I37: =IF(OR(A37="",COUNTIFS('Income Source'!$B$5:$B$65,A37)=0,G37=0),"",H37/G37) | J37: =IF(A37="","",IF(COUNTIFS('Income Source'!$B$5:$B$65,A37)=0,"Revenue source missing",IF(ABS(E37-G37)>0.005,"Income/revenue mismatch","OK"))) -> OK | AB37: Unspecified
A38: =IF($B$3="All",46225,IF(21<31,IF($B$3="July 2026",46204,46235)+21,"")) -> 46225 | B38: =IF(A38="","",IF(COUNTIFS('Income Source'!$B$5:$B$65,A38)=0,"",IF(OR($Q$3="All",$Q$3="Walk-in"),SUMIFS('Income Source'!$C$5:$C$65,'Income Source'!$B$5:$B$65,A38),0))) -> 0 | C38: =IF(A38="","",IF(COUNTIFS('Income Source'!$B$5:$B$65,A38)=0,"",IF(OR($Q$3="All",$Q$3="Colonie"),SUMIFS('Income Source'!$D$5:$D$65,'Income Source'!$B$5:$B$65,A38),0))) -> 660 | D38: =IF(A38="","",IF(COUNTIFS('Income Source'!$B$5:$B$65,A38)=0,"",IF(OR($Q$3="All",$Q$3="Birthday"),SUMIFS('Income Source'!$E$5:$E$65,'Income Source'!$B$5:$B$65,A38),0))) -> 0 | E38: =IF(A38="","",IF(COUNTIFS('Income Source'!$B$5:$B$65,A38)=0,"",SUM(B38:D38))) -> 660 | F38: =IF(A38="","",SUMIFS('Expense Source'!$M$5:$M$178,'Expense Source'!$D$5:$D$178,A38,'Expense Source'!$U$5:$U$178,1)) -> 0 | G38: =IF(A38="","",IF(COUNTIFS('Income Source'!$B$5:$B$65,A38)=0,"",IF($Q$3="All",SUMIFS('Income Source'!$G$5:$G$65,'Income Source'!$B$5:$B$65,A38),SUM(B38:D38)))) -> 660 | H38: =IF(A38="","",IF(COUNTIFS('Income Source'!$B$5:$B$65,A38)=0,"",G38-F38)) -> 660 | I38: =IF(OR(A38="",COUNTIFS('Income Source'!$B$5:$B$65,A38)=0,G38=0),"",H38/G38) -> 1 | J38: =IF(A38="","",IF(COUNTIFS('Income Source'!$B$5:$B$65,A38)=0,"Revenue source missing",IF(ABS(E38-G38)>0.005,"Income/revenue mismatch","OK"))) -> OK | AB38: Youssef Malek
A39: =IF($B$3="All",46226,IF(22<31,IF($B$3="July 2026",46204,46235)+22,"")) -> 46226 | B39: =IF(A39="","",IF(COUNTIFS('Income Source'!$B$5:$B$65,A39)=0,"",IF(OR($Q$3="All",$Q$3="Walk-in"),SUMIFS('Income Source'!$C$5:$C$65,'Income Source'!$B$5:$B$65,A39),0))) -> 0 | C39: =IF(A39="","",IF(COUNTIFS('Income Source'!$B$5:$B$65,A39)=0,"",IF(OR($Q$3="All",$Q$3="Colonie"),SUMIFS('Income Source'!$D$5:$D$65,'Income Source'!$B$5:$B$65,A39),0))) -> 0 | D39: =IF(A39="","",IF(COUNTIFS('Income Source'!$B$5:$B$65,A39)=0,"",IF(OR($Q$3="All",$Q$3="Birthday"),SUMIFS('Income Source'!$E$5:$E$65,'Income Source'!$B$5:$B$65,A39),0))) -> 0 | E39: =IF(A39="","",IF(COUNTIFS('Income Source'!$B$5:$B$65,A39)=0,"",SUM(B39:D39))) -> 0 | F39: =IF(A39="","",SUMIFS('Expense Source'!$M$5:$M$178,'Expense Source'!$D$5:$D$178,A39,'Expense Source'!$U$5:$U$178,1)) -> 93.51 | G39: =IF(A39="","",IF(COUNTIFS('Income Source'!$B$5:$B$65,A39)=0,"",IF($Q$3="All",SUMIFS('Income Source'!$G$5:$G$65,'Income Source'!$B$5:$B$65,A39),SUM(B39:D39)))) -> 0 | H39: =IF(A39="","",IF(COUNTIFS('Income Source'!$B$5:$B$65,A39)=0,"",G39-F39)) -> -93.51 | I39: =IF(OR(A39="",COUNTIFS('Income Source'!$B$5:$B$65,A39)=0,G39=0),"",H39/G39) | J39: =IF(A39="","",IF(COUNTIFS('Income Source'!$B$5:$B$65,A39)=0,"Revenue source missing",IF(ABS(E39-G39)>0.005,"Income/revenue mismatch","OK"))) -> OK
A40: =IF($B$3="All",46227,IF(23<31,IF($B$3="July 2026",46204,46235)+23,"")) -> 46227 | B40: =IF(A40="","",IF(COUNTIFS('Income Source'!$B$5:$B$65,A40)=0,"",IF(OR($Q$3="All",$Q$3="Walk-in"),SUMIFS('Income Source'!$C$5:$C$65,'Income Source'!$B$5:$B$65,A40),0))) -> 228 | C40: =IF(A40="","",IF(COUNTIFS('Income Source'!$B$5:$B$65,A40)=0,"",IF(OR($Q$3="All",$Q$3="Colonie"),SUMIFS('Income Source'!$D$5:$D$65,'Income Source'!$B$5:$B$65,A40),0))) -> 0 | D40: =IF(A40="","",IF(COUNTIFS('Income Source'!$B$5:$B$65,A40)=0,"",IF(OR($Q$3="All",$Q$3="Birthday"),SUMIFS('Income Source'!$E$5:$E$65,'Income Source'!$B$5:$B$65,A40),0))) -> 450 | E40: =IF(A40="","",IF(COUNTIFS('Income Source'!$B$5:$B$65,A40)=0,"",SUM(B40:D40))) -> 678 | F40: =IF(A40="","",SUMIFS('Expense Source'!$M$5:$M$178,'Expense Source'!$D$5:$D$178,A40,'Expense Source'!$U$5:$U$178,1)) -> 348.93438 | G40: =IF(A40="","",IF(COUNTIFS('Income Source'!$B$5:$B$65,A40)=0,"",IF($Q$3="All",SUMIFS('Income Source'!$G$5:$G$65,'Income Source'!$B$5:$B$65,A40),SUM(B40:D40)))) -> 678 | H40: =IF(A40="","",IF(COUNTIFS('Income Source'!$B$5:$B$65,A40)=0,"",G40-F40)) -> 329.06562 | I40: =IF(OR(A40="",COUNTIFS('Income Source'!$B$5:$B$65,A40)=0,G40=0),"",H40/G40) -> 0.48534752 | J40: =IF(A40="","",IF(COUNTIFS('Income Source'!$B$5:$B$65,A40)=0,"Revenue source missing",IF(ABS(E40-G40)>0.005,"Income/revenue mismatch","OK"))) -> OK
A41: =IF($B$3="All",46228,IF(24<31,IF($B$3="July 2026",46204,46235)+24,"")) -> 46228 | B41: =IF(A41="","",IF(COUNTIFS('Income Source'!$B$5:$B$65,A41)=0,"",IF(OR($Q$3="All",$Q$3="Walk-in"),SUMIFS('Income Source'!$C$5:$C$65,'Income Source'!$B$5:$B$65,A41),0))) -> 191 | C41: =IF(A41="","",IF(COUNTIFS('Income Source'!$B$5:$B$65,A41)=0,"",IF(OR($Q$3="All",$Q$3="Colonie"),SUMIFS('Income Source'!$D$5:$D$65,'Income Source'!$B$5:$B$65,A41),0))) -> 0 | D41: =IF(A41="","",IF(COUNTIFS('Income Source'!$B$5:$B$65,A41)=0,"",IF(OR($Q$3="All",$Q$3="Birthday"),SUMIFS('Income Source'!$E$5:$E$65,'Income Source'!$B$5:$B$65,A41),0))) -> 650 | E41: =IF(A41="","",IF(COUNTIFS('Income Source'!$B$5:$B$65,A41)=0,"",SUM(B41:D41))) -> 841 | F41: =IF(A41="","",SUMIFS('Expense Source'!$M$5:$M$178,'Expense Source'!$D$5:$D$178,A41,'Expense Source'!$U$5:$U$178,1)) -> 351.88944 | G41: =IF(A41="","",IF(COUNTIFS('Income Source'!$B$5:$B$65,A41)=0,"",IF($Q$3="All",SUMIFS('Income Source'!$G$5:$G$65,'Income Source'!$B$5:$B$65,A41),SUM(B41:D41)))) -> 841 | H41: =IF(A41="","",IF(COUNTIFS('Income Source'!$B$5:$B$65,A41)=0,"",G41-F41)) -> 489.11056 | I41: =IF(OR(A41="",COUNTIFS('Income Source'!$B$5:$B$65,A41)=0,G41=0),"",H41/G41) -> 0.58158212 | J41: =IF(A41="","",IF(COUNTIFS('Income Source'!$B$5:$B$65,A41)=0,"Revenue source missing",IF(ABS(E41-G41)>0.005,"Income/revenue mismatch","OK"))) -> OK
A42: =IF($B$3="All",46229,IF(25<31,IF($B$3="July 2026",46204,46235)+25,"")) -> 46229 | B42: =IF(A42="","",IF(COUNTIFS('Income Source'!$B$5:$B$65,A42)=0,"",IF(OR($Q$3="All",$Q$3="Walk-in"),SUMIFS('Income Source'!$C$5:$C$65,'Income Source'!$B$5:$B$65,A42),0))) -> 0 | C42: =IF(A42="","",IF(COUNTIFS('Income Source'!$B$5:$B$65,A42)=0,"",IF(OR($Q$3="All",$Q$3="Colonie"),SUMIFS('Income Source'!$D$5:$D$65,'Income Source'!$B$5:$B$65,A42),0))) -> 0 | D42: =IF(A42="","",IF(COUNTIFS('Income Source'!$B$5:$B$65,A42)=0,"",IF(OR($Q$3="All",$Q$3="Birthday"),SUMIFS('Income Source'!$E$5:$E$65,'Income Source'!$B$5:$B$65,A42),0))) -> 1690 | E42: =IF(A42="","",IF(COUNTIFS('Income Source'!$B$5:$B$65,A42)=0,"",SUM(B42:D42))) -> 1690 | F42: =IF(A42="","",SUMIFS('Expense Source'!$M$5:$M$178,'Expense Source'!$D$5:$D$178,A42,'Expense Source'!$U$5:$U$178,1)) -> 0 | G42: =IF(A42="","",IF(COUNTIFS('Income Source'!$B$5:$B$65,A42)=0,"",IF($Q$3="All",SUMIFS('Income Source'!$G$5:$G$65,'Income Source'!$B$5:$B$65,A42),SUM(B42:D42)))) -> 1690 | H42: =IF(A42="","",IF(COUNTIFS('Income Source'!$B$5:$B$65,A42)=0,"",G42-F42)) -> 1690 | I42: =IF(OR(A42="",COUNTIFS('Income Source'!$B$5:$B$65,A42)=0,G42=0),"",H42/G42) -> 1 | J42: =IF(A42="","",IF(COUNTIFS('Income Source'!$B$5:$B$65,A42)=0,"Revenue source missing",IF(ABS(E42-G42)>0.005,"Income/revenue mismatch","OK"))) -> OK
A43: =IF($B$3="All",46230,IF(26<31,IF($B$3="July 2026",46204,46235)+26,"")) -> 46230 | B43: =IF(A43="","",IF(COUNTIFS('Income Source'!$B$5:$B$65,A43)=0,"",IF(OR($Q$3="All",$Q$3="Walk-in"),SUMIFS('Income Source'!$C$5:$C$65,'Income Source'!$B$5:$B$65,A43),0))) -> 0 | C43: =IF(A43="","",IF(COUNTIFS('Income Source'!$B$5:$B$65,A43)=0,"",IF(OR($Q$3="All",$Q$3="Colonie"),SUMIFS('Income Source'!$D$5:$D$65,'Income Source'!$B$5:$B$65,A43),0))) -> 0 | D43: =IF(A43="","",IF(COUNTIFS('Income Source'!$B$5:$B$65,A43)=0,"",IF(OR($Q$3="All",$Q$3="Birthday"),SUMIFS('Income Source'!$E$5:$E$65,'Income Source'!$B$5:$B$65,A43),0))) -> 1477 | E43: =IF(A43="","",IF(COUNTIFS('Income Source'!$B$5:$B$65,A43)=0,"",SUM(B43:D43))) -> 1477 | F43: =IF(A43="","",SUMIFS('Expense Source'!$M$5:$M$178,'Expense Source'!$D$5:$D$178,A43,'Expense Source'!$U$5:$U$178,1)) -> 948.5 | G43: =IF(A43="","",IF(COUNTIFS('Income Source'!$B$5:$B$65,A43)=0,"",IF($Q$3="All",SUMIFS('Income Source'!$G$5:$G$65,'Income Source'!$B$5:$B$65,A43),SUM(B43:D43)))) -> 1477 | H43: =IF(A43="","",IF(COUNTIFS('Income Source'!$B$5:$B$65,A43)=0,"",G43-F43)) -> 528.5 | I43: =IF(OR(A43="",COUNTIFS('Income Source'!$B$5:$B$65,A43)=0,G43=0),"",H43/G43) -> 0.35781991 | J43: =IF(A43="","",IF(COUNTIFS('Income Source'!$B$5:$B$65,A43)=0,"Revenue source missing",IF(ABS(E43-G43)>0.005,"Income/revenue mismatch","OK"))) -> OK
A44: =IF($B$3="All",46231,IF(27<31,IF($B$3="July 2026",46204,46235)+27,"")) -> 46231 | B44: =IF(A44="","",IF(COUNTIFS('Income Source'!$B$5:$B$65,A44)=0,"",IF(OR($Q$3="All",$Q$3="Walk-in"),SUMIFS('Income Source'!$C$5:$C$65,'Income Source'!$B$5:$B$65,A44),0))) -> 0 | C44: =IF(A44="","",IF(COUNTIFS('Income Source'!$B$5:$B$65,A44)=0,"",IF(OR($Q$3="All",$Q$3="Colonie"),SUMIFS('Income Source'!$D$5:$D$65,'Income Source'!$B$5:$B$65,A44),0))) -> 204 | D44: =IF(A44="","",IF(COUNTIFS('Income Source'!$B$5:$B$65,A44)=0,"",IF(OR($Q$3="All",$Q$3="Birthday"),SUMIFS('Income Source'!$E$5:$E$65,'Income Source'!$B$5:$B$65,A44),0))) -> 0 | E44: =IF(A44="","",IF(COUNTIFS('Income Source'!$B$5:$B$65,A44)=0,"",SUM(B44:D44))) -> 204 | F44: =IF(A44="","",SUMIFS('Expense Source'!$M$5:$M$178,'Expense Source'!$D$5:$D$178,A44,'Expense Source'!$U$5:$U$178,1)) -> 0 | G44: =IF(A44="","",IF(COUNTIFS('Income Source'!$B$5:$B$65,A44)=0,"",IF($Q$3="All",SUMIFS('Income Source'!$G$5:$G$65,'Income Source'!$B$5:$B$65,A44),SUM(B44:D44)))) -> 204 | H44: =IF(A44="","",IF(COUNTIFS('Income Source'!$B$5:$B$65,A44)=0,"",G44-F44)) -> 204 | I44: =IF(OR(A44="",COUNTIFS('Income Source'!$B$5:$B$65,A44)=0,G44=0),"",H44/G44) -> 1 | J44: =IF(A44="","",IF(COUNTIFS('Income Source'!$B$5:$B$65,A44)=0,"Revenue source missing",IF(ABS(E44-G44)>0.005,"Income/revenue mismatch","OK"))) -> OK
A45: =IF($B$3="All",46232,IF(28<31,IF($B$3="July 2026",46204,46235)+28,"")) -> 46232 | B45: =IF(A45="","",IF(COUNTIFS('Income Source'!$B$5:$B$65,A45)=0,"",IF(OR($Q$3="All",$Q$3="Walk-in"),SUMIFS('Income Source'!$C$5:$C$65,'Income Source'!$B$5:$B$65,A45),0))) -> 0 | C45: =IF(A45="","",IF(COUNTIFS('Income Source'!$B$5:$B$65,A45)=0,"",IF(OR($Q$3="All",$Q$3="Colonie"),SUMIFS('Income Source'!$D$5:$D$65,'Income Source'!$B$5:$B$65,A45),0))) -> 0 | D45: =IF(A45="","",IF(COUNTIFS('Income Source'!$B$5:$B$65,A45)=0,"",IF(OR($Q$3="All",$Q$3="Birthday"),SUMIFS('Income Source'!$E$5:$E$65,'Income Source'!$B$5:$B$65,A45),0))) -> 950 | E45: =IF(A45="","",IF(COUNTIFS('Income Source'!$B$5:$B$65,A45)=0,"",SUM(B45:D45))) -> 950 | F45: =IF(A45="","",SUMIFS('Expense Source'!$M$5:$M$178,'Expense Source'!$D$5:$D$178,A45,'Expense Source'!$U$5:$U$178,1)) -> 253.74 | G45: =IF(A45="","",IF(COUNTIFS('Income Source'!$B$5:$B$65,A45)=0,"",IF($Q$3="All",SUMIFS('Income Source'!$G$5:$G$65,'Income Source'!$B$5:$B$65,A45),SUM(B45:D45)))) -> 950 | H45: =IF(A45="","",IF(COUNTIFS('Income Source'!$B$5:$B$65,A45)=0,"",G45-F45)) -> 696.26 | I45: =IF(OR(A45="",COUNTIFS('Income Source'!$B$5:$B$65,A45)=0,G45=0),"",H45/G45) -> 0.73290526 | J45: =IF(A45="","",IF(COUNTIFS('Income Source'!$B$5:$B$65,A45)=0,"Revenue source missing",IF(ABS(E45-G45)>0.005,"Income/revenue mismatch","OK"))) -> OK
A46: =IF($B$3="All",46233,IF(29<31,IF($B$3="July 2026",46204,46235)+29,"")) -> 46233 | B46: =IF(A46="","",IF(COUNTIFS('Income Source'!$B$5:$B$65,A46)=0,"",IF(OR($Q$3="All",$Q$3="Walk-in"),SUMIFS('Income Source'!$C$5:$C$65,'Income Source'!$B$5:$B$65,A46),0))) -> 0 | C46: =IF(A46="","",IF(COUNTIFS('Income Source'!$B$5:$B$65,A46)=0,"",IF(OR($Q$3="All",$Q$3="Colonie"),SUMIFS('Income Source'!$D$5:$D$65,'Income Source'!$B$5:$B$65,A46),0))) -> 228 | D46: =IF(A46="","",IF(COUNTIFS('Income Source'!$B$5:$B$65,A46)=0,"",IF(OR($Q$3="All",$Q$3="Birthday"),SUMIFS('Income Source'!$E$5:$E$65,'Income Source'!$B$5:$B$65,A46),0))) -> 0 | E46: =IF(A46="","",IF(COUNTIFS('Income Source'!$B$5:$B$65,A46)=0,"",SUM(B46:D46))) -> 228 | F46: =IF(A46="","",SUMIFS('Expense Source'!$M$5:$M$178,'Expense Source'!$D$5:$D$178,A46,'Expense Source'!$U$5:$U$178,1)) -> 0 | G46: =IF(A46="","",IF(COUNTIFS('Income Source'!$B$5:$B$65,A46)=0,"",IF($Q$3="All",SUMIFS('Income Source'!$G$5:$G$65,'Income Source'!$B$5:$B$65,A46),SUM(B46:D46)))) -> 228 | H46: =IF(A46="","",IF(COUNTIFS('Income Source'!$B$5:$B$65,A46)=0,"",G46-F46)) -> 228 | I46: =IF(OR(A46="",COUNTIFS('Income Source'!$B$5:$B$65,A46)=0,G46=0),"",H46/G46) -> 1 | J46: =IF(A46="","",IF(COUNTIFS('Income Source'!$B$5:$B$65,A46)=0,"Revenue source missing",IF(ABS(E46-G46)>0.005,"Income/revenue mismatch","OK"))) -> OK
A47: =IF($B$3="All",46234,IF(30<31,IF($B$3="July 2026",46204,46235)+30,"")) -> 46234 | B47: =IF(A47="","",IF(COUNTIFS('Income Source'!$B$5:$B$65,A47)=0,"",IF(OR($Q$3="All",$Q$3="Walk-in"),SUMIFS('Income Source'!$C$5:$C$65,'Income Source'!$B$5:$B$65,A47),0))) -> 166 | C47: =IF(A47="","",IF(COUNTIFS('Income Source'!$B$5:$B$65,A47)=0,"",IF(OR($Q$3="All",$Q$3="Colonie"),SUMIFS('Income Source'!$D$5:$D$65,'Income Source'!$B$5:$B$65,A47),0))) -> 336 | D47: =IF(A47="","",IF(COUNTIFS('Income Source'!$B$5:$B$65,A47)=0,"",IF(OR($Q$3="All",$Q$3="Birthday"),SUMIFS('Income Source'!$E$5:$E$65,'Income Source'!$B$5:$B$65,A47),0))) -> 185 | E47: =IF(A47="","",IF(COUNTIFS('Income Source'!$B$5:$B$65,A47)=0,"",SUM(B47:D47))) -> 687 | F47: =IF(A47="","",SUMIFS('Expense Source'!$M$5:$M$178,'Expense Source'!$D$5:$D$178,A47,'Expense Source'!$U$5:$U$178,1)) -> 98.08 | G47: =IF(A47="","",IF(COUNTIFS('Income Source'!$B$5:$B$65,A47)=0,"",IF($Q$3="All",SUMIFS('Income Source'!$G$5:$G$65,'Income Source'!$B$5:$B$65,A47),SUM(B47:D47)))) -> 687 | H47: =IF(A47="","",IF(COUNTIFS('Income Source'!$B$5:$B$65,A47)=0,"",G47-F47)) -> 588.92 | I47: =IF(OR(A47="",COUNTIFS('Income Source'!$B$5:$B$65,A47)=0,G47=0),"",H47/G47) -> 0.85723435 | J47: =IF(A47="","",IF(COUNTIFS('Income Source'!$B$5:$B$65,A47)=0,"Revenue source missing",IF(ABS(E47-G47)>0.005,"Income/revenue mismatch","OK"))) -> OK
A48: =IF($B$3="All",46235,IF(31<31,IF($B$3="July 2026",46204,46235)+31,"")) -> 46235 | B48: =IF(A48="","",IF(COUNTIFS('Income Source'!$B$5:$B$65,A48)=0,"",IF(OR($Q$3="All",$Q$3="Walk-in"),SUMIFS('Income Source'!$C$5:$C$65,'Income Source'!$B$5:$B$65,A48),0))) -> 250 | C48: =IF(A48="","",IF(COUNTIFS('Income Source'!$B$5:$B$65,A48)=0,"",IF(OR($Q$3="All",$Q$3="Colonie"),SUMIFS('Income Source'!$D$5:$D$65,'Income Source'!$B$5:$B$65,A48),0))) -> 0 | D48: =IF(A48="","",IF(COUNTIFS('Income Source'!$B$5:$B$65,A48)=0,"",IF(OR($Q$3="All",$Q$3="Birthday"),SUMIFS('Income Source'!$E$5:$E$65,'Income Source'!$B$5:$B$65,A48),0))) -> 945 | E48: =IF(A48="","",IF(COUNTIFS('Income Source'!$B$5:$B$65,A48)=0,"",SUM(B48:D48))) -> 1195 | F48: =IF(A48="","",SUMIFS('Expense Source'!$M$5:$M$178,'Expense Source'!$D$5:$D$178,A48,'Expense Source'!$U$5:$U$178,1)) -> 0 | G48: =IF(A48="","",IF(COUNTIFS('Income Source'!$B$5:$B$65,A48)=0,"",IF($Q$3="All",SUMIFS('Income Source'!$G$5:$G$65,'Income Source'!$B$5:$B$65,A48),SUM(B48:D48)))) -> 1195 | H48: =IF(A48="","",IF(COUNTIFS('Income Source'!$B$5:$B$65,A48)=0,"",G48-F48)) -> 1195 | I48: =IF(OR(A48="",COUNTIFS('Income Source'!$B$5:$B$65,A48)=0,G48=0),"",H48/G48) -> 1 | J48: =IF(A48="","",IF(COUNTIFS('Income Source'!$B$5:$B$65,A48)=0,"Revenue source missing",IF(ABS(E48-G48)>0.005,"Income/revenue mismatch","OK"))) -> OK
A49: =IF($B$3="All",46236,IF(32<31,IF($B$3="July 2026",46204,46235)+32,"")) -> 46236 | B49: =IF(A49="","",IF(COUNTIFS('Income Source'!$B$5:$B$65,A49)=0,"",IF(OR($Q$3="All",$Q$3="Walk-in"),SUMIFS('Income Source'!$C$5:$C$65,'Income Source'!$B$5:$B$65,A49),0))) -> 785 | C49: =IF(A49="","",IF(COUNTIFS('Income Source'!$B$5:$B$65,A49)=0,"",IF(OR($Q$3="All",$Q$3="Colonie"),SUMIFS('Income Source'!$D$5:$D$65,'Income Source'!$B$5:$B$65,A49),0))) -> 0 | D49: =IF(A49="","",IF(COUNTIFS('Income Source'!$B$5:$B$65,A49)=0,"",IF(OR($Q$3="All",$Q$3="Birthday"),SUMIFS('Income Source'!$E$5:$E$65,'Income Source'!$B$5:$B$65,A49),0))) -> 0 | E49: =IF(A49="","",IF(COUNTIFS('Income Source'!$B$5:$B$65,A49)=0,"",SUM(B49:D49))) -> 785 | F49: =IF(A49="","",SUMIFS('Expense Source'!$M$5:$M$178,'Expense Source'!$D$5:$D$178,A49,'Expense Source'!$U$5:$U$178,1)) -> 102.60199 | G49: =IF(A49="","",IF(COUNTIFS('Income Source'!$B$5:$B$65,A49)=0,"",IF($Q$3="All",SUMIFS('Income Source'!$G$5:$G$65,'Income Source'!$B$5:$B$65,A49),SUM(B49:D49)))) -> 785 | H49: =IF(A49="","",IF(COUNTIFS('Income Source'!$B$5:$B$65,A49)=0,"",G49-F49)) -> 682.39801 | I49: =IF(OR(A49="",COUNTIFS('Income Source'!$B$5:$B$65,A49)=0,G49=0),"",H49/G49) -> 0.86929683 | J49: =IF(A49="","",IF(COUNTIFS('Income Source'!$B$5:$B$65,A49)=0,"Revenue source missing",IF(ABS(E49-G49)>0.005,"Income/revenue mismatch","OK"))) -> OK
A50: =IF($B$3="All",46237,IF(33<31,IF($B$3="July 2026",46204,46235)+33,"")) -> 46237 | B50: =IF(A50="","",IF(COUNTIFS('Income Source'!$B$5:$B$65,A50)=0,"",IF(OR($Q$3="All",$Q$3="Walk-in"),SUMIFS('Income Source'!$C$5:$C$65,'Income Source'!$B$5:$B$65,A50),0))) -> 0 | C50: =IF(A50="","",IF(COUNTIFS('Income Source'!$B$5:$B$65,A50)=0,"",IF(OR($Q$3="All",$Q$3="Colonie"),SUMIFS('Income Source'!$D$5:$D$65,'Income Source'!$B$5:$B$65,A50),0))) -> 0 | D50: =IF(A50="","",IF(COUNTIFS('Income Source'!$B$5:$B$65,A50)=0,"",IF(OR($Q$3="All",$Q$3="Birthday"),SUMIFS('Income Source'!$E$5:$E$65,'Income Source'!$B$5:$B$65,A50),0))) -> 0 | E50: =IF(A50="","",IF(COUNTIFS('Income Source'!$B$5:$B$65,A50)=0,"",SUM(B50:D50))) -> 0 | F50: =IF(A50="","",SUMIFS('Expense Source'!$M$5:$M$178,'Expense Source'!$D$5:$D$178,A50,'Expense Source'!$U$5:$U$178,1)) -> 0 | G50: =IF(A50="","",IF(COUNTIFS('Income Source'!$B$5:$B$65,A50)=0,"",IF($Q$3="All",SUMIFS('Income Source'!$G$5:$G$65,'Income Source'!$B$5:$B$65,A50),SUM(B50:D50)))) -> 0 | H50: =IF(A50="","",IF(COUNTIFS('Income Source'!$B$5:$B$65,A50)=0,"",G50-F50)) -> 0 | I50: =IF(OR(A50="",COUNTIFS('Income Source'!$B$5:$B$65,A50)=0,G50=0),"",H50/G50) | J50: =IF(A50="","",IF(COUNTIFS('Income Source'!$B$5:$B$65,A50)=0,"Revenue source missing",IF(ABS(E50-G50)>0.005,"Income/revenue mismatch","OK"))) -> OK
A51: =IF($B$3="All",46238,IF(34<31,IF($B$3="July 2026",46204,46235)+34,"")) -> 46238 | B51: =IF(A51="","",IF(COUNTIFS('Income Source'!$B$5:$B$65,A51)=0,"",IF(OR($Q$3="All",$Q$3="Walk-in"),SUMIFS('Income Source'!$C$5:$C$65,'Income Source'!$B$5:$B$65,A51),0))) -> 0 | C51: =IF(A51="","",IF(COUNTIFS('Income Source'!$B$5:$B$65,A51)=0,"",IF(OR($Q$3="All",$Q$3="Colonie"),SUMIFS('Income Source'!$D$5:$D$65,'Income Source'!$B$5:$B$65,A51),0))) -> 0 | D51: =IF(A51="","",IF(COUNTIFS('Income Source'!$B$5:$B$65,A51)=0,"",IF(OR($Q$3="All",$Q$3="Birthday"),SUMIFS('Income Source'!$E$5:$E$65,'Income Source'!$B$5:$B$65,A51),0))) -> 0 | E51: =IF(A51="","",IF(COUNTIFS('Income Source'!$B$5:$B$65,A51)=0,"",SUM(B51:D51))) -> 0 | F51: =IF(A51="","",SUMIFS('Expense Source'!$M$5:$M$178,'Expense Source'!$D$5:$D$178,A51,'Expense Source'!$U$5:$U$178,1)) -> 0 | G51: =IF(A51="","",IF(COUNTIFS('Income Source'!$B$5:$B$65,A51)=0,"",IF($Q$3="All",SUMIFS('Income Source'!$G$5:$G$65,'Income Source'!$B$5:$B$65,A51),SUM(B51:D51)))) -> 0 | H51: =IF(A51="","",IF(COUNTIFS('Income Source'!$B$5:$B$65,A51)=0,"",G51-F51)) -> 0 | I51: =IF(OR(A51="",COUNTIFS('Income Source'!$B$5:$B$65,A51)=0,G51=0),"",H51/G51) | J51: =IF(A51="","",IF(COUNTIFS('Income Source'!$B$5:$B$65,A51)=0,"Revenue source missing",IF(ABS(E51-G51)>0.005,"Income/revenue mismatch","OK"))) -> OK
A52: =IF($B$3="All",46239,IF(35<31,IF($B$3="July 2026",46204,46235)+35,"")) -> 46239 | B52: =IF(A52="","",IF(COUNTIFS('Income Source'!$B$5:$B$65,A52)=0,"",IF(OR($Q$3="All",$Q$3="Walk-in"),SUMIFS('Income Source'!$C$5:$C$65,'Income Source'!$B$5:$B$65,A52),0))) -> 0 | C52: =IF(A52="","",IF(COUNTIFS('Income Source'!$B$5:$B$65,A52)=0,"",IF(OR($Q$3="All",$Q$3="Colonie"),SUMIFS('Income Source'!$D$5:$D$65,'Income Source'!$B$5:$B$65,A52),0))) -> 388 | D52: =IF(A52="","",IF(COUNTIFS('Income Source'!$B$5:$B$65,A52)=0,"",IF(OR($Q$3="All",$Q$3="Birthday"),SUMIFS('Income Source'!$E$5:$E$65,'Income Source'!$B$5:$B$65,A52),0))) -> 0 | E52: =IF(A52="","",IF(COUNTIFS('Income Source'!$B$5:$B$65,A52)=0,"",SUM(B52:D52))) -> 388 | F52: =IF(A52="","",SUMIFS('Expense Source'!$M$5:$M$178,'Expense Source'!$D$5:$D$178,A52,'Expense Source'!$U$5:$U$178,1)) -> 0 | G52: =IF(A52="","",IF(COUNTIFS('Income Source'!$B$5:$B$65,A52)=0,"",IF($Q$3="All",SUMIFS('Income Source'!$G$5:$G$65,'Income Source'!$B$5:$B$65,A52),SUM(B52:D52)))) -> 388 | H52: =IF(A52="","",IF(COUNTIFS('Income Source'!$B$5:$B$65,A52)=0,"",G52-F52)) -> 388 | I52: =IF(OR(A52="",COUNTIFS('Income Source'!$B$5:$B$65,A52)=0,G52=0),"",H52/G52) -> 1 | J52: =IF(A52="","",IF(COUNTIFS('Income Source'!$B$5:$B$65,A52)=0,"Revenue source missing",IF(ABS(E52-G52)>0.005,"Income/revenue mismatch","OK"))) -> OK
A53: =IF($B$3="All",46240,IF(36<31,IF($B$3="July 2026",46204,46235)+36,"")) -> 46240 | B53: =IF(A53="","",IF(COUNTIFS('Income Source'!$B$5:$B$65,A53)=0,"",IF(OR($Q$3="All",$Q$3="Walk-in"),SUMIFS('Income Source'!$C$5:$C$65,'Income Source'!$B$5:$B$65,A53),0))) -> 0 | C53: =IF(A53="","",IF(COUNTIFS('Income Source'!$B$5:$B$65,A53)=0,"",IF(OR($Q$3="All",$Q$3="Colonie"),SUMIFS('Income Source'!$D$5:$D$65,'Income Source'!$B$5:$B$65,A53),0))) -> 372 | D53: =IF(A53="","",IF(COUNTIFS('Income Source'!$B$5:$B$65,A53)=0,"",IF(OR($Q$3="All",$Q$3="Birthday"),SUMIFS('Income Source'!$E$5:$E$65,'Income Source'!$B$5:$B$65,A53),0))) -> 0 | E53: =IF(A53="","",IF(COUNTIFS('Income Source'!$B$5:$B$65,A53)=0,"",SUM(B53:D53))) -> 372 | F53: =IF(A53="","",SUMIFS('Expense Source'!$M$5:$M$178,'Expense Source'!$D$5:$D$178,A53,'Expense Source'!$U$5:$U$178,1)) -> 0 | G53: =IF(A53="","",IF(COUNTIFS('Income Source'!$B$5:$B$65,A53)=0,"",IF($Q$3="All",SUMIFS('Income Source'!$G$5:$G$65,'Income Source'!$B$5:$B$65,A53),SUM(B53:D53)))) -> 372 | H53: =IF(A53="","",IF(COUNTIFS('Income Source'!$B$5:$B$65,A53)=0,"",G53-F53)) -> 372 | I53: =IF(OR(A53="",COUNTIFS('Income Source'!$B$5:$B$65,A53)=0,G53=0),"",H53/G53) -> 1 | J53: =IF(A53="","",IF(COUNTIFS('Income Source'!$B$5:$B$65,A53)=0,"Revenue source missing",IF(ABS(E53-G53)>0.005,"Income/revenue mismatch","OK"))) -> OK
A54: =IF($B$3="All",46241,IF(37<31,IF($B$3="July 2026",46204,46235)+37,"")) -> 46241 | B54: =IF(A54="","",IF(COUNTIFS('Income Source'!$B$5:$B$65,A54)=0,"",IF(OR($Q$3="All",$Q$3="Walk-in"),SUMIFS('Income Source'!$C$5:$C$65,'Income Source'!$B$5:$B$65,A54),0))) -> 0 | C54: =IF(A54="","",IF(COUNTIFS('Income Source'!$B$5:$B$65,A54)=0,"",IF(OR($Q$3="All",$Q$3="Colonie"),SUMIFS('Income Source'!$D$5:$D$65,'Income Source'!$B$5:$B$65,A54),0))) -> 0 | D54: =IF(A54="","",IF(COUNTIFS('Income Source'!$B$5:$B$65,A54)=0,"",IF(OR($Q$3="All",$Q$3="Birthday"),SUMIFS('Income Source'!$E$5:$E$65,'Income Source'!$B$5:$B$65,A54),0))) -> 0 | E54: =IF(A54="","",IF(COUNTIFS('Income Source'!$B$5:$B$65,A54)=0,"",SUM(B54:D54))) -> 0 | F54: =IF(A54="","",SUMIFS('Expense Source'!$M$5:$M$178,'Expense Source'!$D$5:$D$178,A54,'Expense Source'!$U$5:$U$178,1)) -> 109.58652 | G54: =IF(A54="","",IF(COUNTIFS('Income Source'!$B$5:$B$65,A54)=0,"",IF($Q$3="All",SUMIFS('Income Source'!$G$5:$G$65,'Income Source'!$B$5:$B$65,A54),SUM(B54:D54)))) -> 0 | H54: =IF(A54="","",IF(COUNTIFS('Income Source'!$B$5:$B$65,A54)=0,"",G54-F54)) -> -109.58652 | I54: =IF(OR(A54="",COUNTIFS('Income Source'!$B$5:$B$65,A54)=0,G54=0),"",H54/G54) | J54: =IF(A54="","",IF(COUNTIFS('Income Source'!$B$5:$B$65,A54)=0,"Revenue source missing",IF(ABS(E54-G54)>0.005,"Income/revenue mismatch","OK"))) -> OK
A55: =IF($B$3="All",46242,IF(38<31,IF($B$3="July 2026",46204,46235)+38,"")) -> 46242 | B55: =IF(A55="","",IF(COUNTIFS('Income Source'!$B$5:$B$65,A55)=0,"",IF(OR($Q$3="All",$Q$3="Walk-in"),SUMIFS('Income Source'!$C$5:$C$65,'Income Source'!$B$5:$B$65,A55),0))) -> 250 | C55: =IF(A55="","",IF(COUNTIFS('Income Source'!$B$5:$B$65,A55)=0,"",IF(OR($Q$3="All",$Q$3="Colonie"),SUMIFS('Income Source'!$D$5:$D$65,'Income Source'!$B$5:$B$65,A55),0))) -> 950 | D55: =IF(A55="","",IF(COUNTIFS('Income Source'!$B$5:$B$65,A55)=0,"",IF(OR($Q$3="All",$Q$3="Birthday"),SUMIFS('Income Source'!$E$5:$E$65,'Income Source'!$B$5:$B$65,A55),0))) -> 0 | E55: =IF(A55="","",IF(COUNTIFS('Income Source'!$B$5:$B$65,A55)=0,"",SUM(B55:D55))) -> 1200 | F55: =IF(A55="","",SUMIFS('Expense Source'!$M$5:$M$178,'Expense Source'!$D$5:$D$178,A55,'Expense Source'!$U$5:$U$178,1)) -> 207.56213 | G55: =IF(A55="","",IF(COUNTIFS('Income Source'!$B$5:$B$65,A55)=0,"",IF($Q$3="All",SUMIFS('Income Source'!$G$5:$G$65,'Income Source'!$B$5:$B$65,A55),SUM(B55:D55)))) -> 1200 | H55: =IF(A55="","",IF(COUNTIFS('Income Source'!$B$5:$B$65,A55)=0,"",G55-F55)) -> 992.43787 | I55: =IF(OR(A55="",COUNTIFS('Income Source'!$B$5:$B$65,A55)=0,G55=0),"",H55/G55) -> 0.82703155 | J55: =IF(A55="","",IF(COUNTIFS('Income Source'!$B$5:$B$65,A55)=0,"Revenue source missing",IF(ABS(E55-G55)>0.005,"Income/revenue mismatch","OK"))) -> OK
A56: =IF($B$3="All",46243,IF(39<31,IF($B$3="July 2026",46204,46235)+39,"")) -> 46243 | B56: =IF(A56="","",IF(COUNTIFS('Income Source'!$B$5:$B$65,A56)=0,"",IF(OR($Q$3="All",$Q$3="Walk-in"),SUMIFS('Income Source'!$C$5:$C$65,'Income Source'!$B$5:$B$65,A56),0))) -> 415 | C56: =IF(A56="","",IF(COUNTIFS('Income Source'!$B$5:$B$65,A56)=0,"",IF(OR($Q$3="All",$Q$3="Colonie"),SUMIFS('Income Source'!$D$5:$D$65,'Income Source'!$B$5:$B$65,A56),0))) -> 860 | D56: =IF(A56="","",IF(COUNTIFS('Income Source'!$B$5:$B$65,A56)=0,"",IF(OR($Q$3="All",$Q$3="Birthday"),SUMIFS('Income Source'!$E$5:$E$65,'Income Source'!$B$5:$B$65,A56),0))) -> 0 | E56: =IF(A56="","",IF(COUNTIFS('Income Source'!$B$5:$B$65,A56)=0,"",SUM(B56:D56))) -> 1275 | F56: =IF(A56="","",SUMIFS('Expense Source'!$M$5:$M$178,'Expense Source'!$D$5:$D$178,A56,'Expense Source'!$U$5:$U$178,1)) -> 206.02566 | G56: =IF(A56="","",IF(COUNTIFS('Income Source'!$B$5:$B$65,A56)=0,"",IF($Q$3="All",SUMIFS('Income Source'!$G$5:$G$65,'Income Source'!$B$5:$B$65,A56),SUM(B56:D56)))) -> 1275 | H56: =IF(A56="","",IF(COUNTIFS('Income Source'!$B$5:$B$65,A56)=0,"",G56-F56)) -> 1068.9743 | I56: =IF(OR(A56="",COUNTIFS('Income Source'!$B$5:$B$65,A56)=0,G56=0),"",H56/G56) -> 0.83841125 | J56: =IF(A56="","",IF(COUNTIFS('Income Source'!$B$5:$B$65,A56)=0,"Revenue source missing",IF(ABS(E56-G56)>0.005,"Income/revenue mismatch","OK"))) -> OK
A57: =IF($B$3="All",46244,IF(40<31,IF($B$3="July 2026",46204,46235)+40,"")) -> 46244 | B57: =IF(A57="","",IF(COUNTIFS('Income Source'!$B$5:$B$65,A57)=0,"",IF(OR($Q$3="All",$Q$3="Walk-in"),SUMIFS('Income Source'!$C$5:$C$65,'Income Source'!$B$5:$B$65,A57),0))) -> 820 | C57: =IF(A57="","",IF(COUNTIFS('Income Source'!$B$5:$B$65,A57)=0,"",IF(OR($Q$3="All",$Q$3="Colonie"),SUMIFS('Income Source'!$D$5:$D$65,'Income Source'!$B$5:$B$65,A57),0))) -> 400 | D57: =IF(A57="","",IF(COUNTIFS('Income Source'!$B$5:$B$65,A57)=0,"",IF(OR($Q$3="All",$Q$3="Birthday"),SUMIFS('Income Source'!$E$5:$E$65,'Income Source'!$B$5:$B$65,A57),0))) -> 0 | E57: =IF(A57="","",IF(COUNTIFS('Income Source'!$B$5:$B$65,A57)=0,"",SUM(B57:D57))) -> 1220 | F57: =IF(A57="","",SUMIFS('Expense Source'!$M$5:$M$178,'Expense Source'!$D$5:$D$178,A57,'Expense Source'!$U$5:$U$178,1)) -> 0 | G57: =IF(A57="","",IF(COUNTIFS('Income Source'!$B$5:$B$65,A57)=0,"",IF($Q$3="All",SUMIFS('Income Source'!$G$5:$G$65,'Income Source'!$B$5:$B$65,A57),SUM(B57:D57)))) -> 1220 | H57: =IF(A57="","",IF(COUNTIFS('Income Source'!$B$5:$B$65,A57)=0,"",G57-F57)) -> 1220 | I57: =IF(OR(A57="",COUNTIFS('Income Source'!$B$5:$B$65,A57)=0,G57=0),"",H57/G57) -> 1 | J57: =IF(A57="","",IF(COUNTIFS('Income Source'!$B$5:$B$65,A57)=0,"Revenue source missing",IF(ABS(E57-G57)>0.005,"Income/revenue mismatch","OK"))) -> OK
A58: =IF($B$3="All",46245,IF(41<31,IF($B$3="July 2026",46204,46235)+41,"")) -> 46245 | B58: =IF(A58="","",IF(COUNTIFS('Income Source'!$B$5:$B$65,A58)=0,"",IF(OR($Q$3="All",$Q$3="Walk-in"),SUMIFS('Income Source'!$C$5:$C$65,'Income Source'!$B$5:$B$65,A58),0))) -> 0 | C58: =IF(A58="","",IF(COUNTIFS('Income Source'!$B$5:$B$65,A58)=0,"",IF(OR($Q$3="All",$Q$3="Colonie"),SUMIFS('Income Source'!$D$5:$D$65,'Income Source'!$B$5:$B$65,A58),0))) -> 0 | D58: =IF(A58="","",IF(COUNTIFS('Income Source'!$B$5:$B$65,A58)=0,"",IF(OR($Q$3="All",$Q$3="Birthday"),SUMIFS('Income Source'!$E$5:$E$65,'Income Source'!$B$5:$B$65,A58),0))) -> 0 | E58: =IF(A58="","",IF(COUNTIFS('Income Source'!$B$5:$B$65,A58)=0,"",SUM(B58:D58))) -> 0 | F58: =IF(A58="","",SUMIFS('Expense Source'!$M$5:$M$178,'Expense Source'!$D$5:$D$178,A58,'Expense Source'!$U$5:$U$178,1)) -> 0 | G58: =IF(A58="","",IF(COUNTIFS('Income Source'!$B$5:$B$65,A58)=0,"",IF($Q$3="All",SUMIFS('Income Source'!$G$5:$G$65,'Income Source'!$B$5:$B$65,A58),SUM(B58:D58)))) -> 0 | H58: =IF(A58="","",IF(COUNTIFS('Income Source'!$B$5:$B$65,A58)=0,"",G58-F58)) -> 0 | I58: =IF(OR(A58="",COUNTIFS('Income Source'!$B$5:$B$65,A58)=0,G58=0),"",H58/G58) | J58: =IF(A58="","",IF(COUNTIFS('Income Source'!$B$5:$B$65,A58)=0,"Revenue source missing",IF(ABS(E58-G58)>0.005,"Income/revenue mismatch","OK"))) -> OK
A59: =IF($B$3="All",46246,IF(42<31,IF($B$3="July 2026",46204,46235)+42,"")) -> 46246 | B59: =IF(A59="","",IF(COUNTIFS('Income Source'!$B$5:$B$65,A59)=0,"",IF(OR($Q$3="All",$Q$3="Walk-in"),SUMIFS('Income Source'!$C$5:$C$65,'Income Source'!$B$5:$B$65,A59),0))) -> 0 | C59: =IF(A59="","",IF(COUNTIFS('Income Source'!$B$5:$B$65,A59)=0,"",IF(OR($Q$3="All",$Q$3="Colonie"),SUMIFS('Income Source'!$D$5:$D$65,'Income Source'!$B$5:$B$65,A59),0))) -> 0 | D59: =IF(A59="","",IF(COUNTIFS('Income Source'!$B$5:$B$65,A59)=0,"",IF(OR($Q$3="All",$Q$3="Birthday"),SUMIFS('Income Source'!$E$5:$E$65,'Income Source'!$B$5:$B$65,A59),0))) -> 0 | E59: =IF(A59="","",IF(COUNTIFS('Income Source'!$B$5:$B$65,A59)=0,"",SUM(B59:D59))) -> 0 | F59: =IF(A59="","",SUMIFS('Expense Source'!$M$5:$M$178,'Expense Source'!$D$5:$D$178,A59,'Expense Source'!$U$5:$U$178,1)) -> 520.63072 | G59: =IF(A59="","",IF(COUNTIFS('Income Source'!$B$5:$B$65,A59)=0,"",IF($Q$3="All",SUMIFS('Income Source'!$G$5:$G$65,'Income Source'!$B$5:$B$65,A59),SUM(B59:D59)))) -> 0 | H59: =IF(A59="","",IF(COUNTIFS('Income Source'!$B$5:$B$65,A59)=0,"",G59-F59)) -> -520.63072 | I59: =IF(OR(A59="",COUNTIFS('Income Source'!$B$5:$B$65,A59)=0,G59=0),"",H59/G59) | J59: =IF(A59="","",IF(COUNTIFS('Income Source'!$B$5:$B$65,A59)=0,"Revenue source missing",IF(ABS(E59-G59)>0.005,"Income/revenue mismatch","OK"))) -> OK
A60: =IF($B$3="All",46247,IF(43<31,IF($B$3="July 2026",46204,46235)+43,"")) -> 46247 | B60: =IF(A60="","",IF(COUNTIFS('Income Source'!$B$5:$B$65,A60)=0,"",IF(OR($Q$3="All",$Q$3="Walk-in"),SUMIFS('Income Source'!$C$5:$C$65,'Income Source'!$B$5:$B$65,A60),0))) -> 0 | C60: =IF(A60="","",IF(COUNTIFS('Income Source'!$B$5:$B$65,A60)=0,"",IF(OR($Q$3="All",$Q$3="Colonie"),SUMIFS('Income Source'!$D$5:$D$65,'Income Source'!$B$5:$B$65,A60),0))) -> 0 | D60: =IF(A60="","",IF(COUNTIFS('Income Source'!$B$5:$B$65,A60)=0,"",IF(OR($Q$3="All",$Q$3="Birthday"),SUMIFS('Income Source'!$E$5:$E$65,'Income Source'!$B$5:$B$65,A60),0))) -> 0 | E60: =IF(A60="","",IF(COUNTIFS('Income Source'!$B$5:$B$65,A60)=0,"",SUM(B60:D60))) -> 0 | F60: =IF(A60="","",SUMIFS('Expense Source'!$M$5:$M$178,'Expense Source'!$D$5:$D$178,A60,'Expense Source'!$U$5:$U$178,1)) -> 31.794444 | G60: =IF(A60="","",IF(COUNTIFS('Income Source'!$B$5:$B$65,A60)=0,"",IF($Q$3="All",SUMIFS('Income Source'!$G$5:$G$65,'Income Source'!$B$5:$B$65,A60),SUM(B60:D60)))) -> 0 | H60: =IF(A60="","",IF(COUNTIFS('Income Source'!$B$5:$B$65,A60)=0,"",G60-F60)) -> -31.794444 | I60: =IF(OR(A60="",COUNTIFS('Income Source'!$B$5:$B$65,A60)=0,G60=0),"",H60/G60) | J60: =IF(A60="","",IF(COUNTIFS('Income Source'!$B$5:$B$65,A60)=0,"Revenue source missing",IF(ABS(E60-G60)>0.005,"Income/revenue mismatch","OK"))) -> OK
A61: =IF($B$3="All",46248,IF(44<31,IF($B$3="July 2026",46204,46235)+44,"")) -> 46248 | B61: =IF(A61="","",IF(COUNTIFS('Income Source'!$B$5:$B$65,A61)=0,"",IF(OR($Q$3="All",$Q$3="Walk-in"),SUMIFS('Income Source'!$C$5:$C$65,'Income Source'!$B$5:$B$65,A61),0))) -> 368 | C61: =IF(A61="","",IF(COUNTIFS('Income Source'!$B$5:$B$65,A61)=0,"",IF(OR($Q$3="All",$Q$3="Colonie"),SUMIFS('Income Source'!$D$5:$D$65,'Income Source'!$B$5:$B$65,A61),0))) -> 300 | D61: =IF(A61="","",IF(COUNTIFS('Income Source'!$B$5:$B$65,A61)=0,"",IF(OR($Q$3="All",$Q$3="Birthday"),SUMIFS('Income Source'!$E$5:$E$65,'Income Source'!$B$5:$B$65,A61),0))) -> 0 | E61: =IF(A61="","",IF(COUNTIFS('Income Source'!$B$5:$B$65,A61)=0,"",SUM(B61:D61))) -> 668 | F61: =IF(A61="","",SUMIFS('Expense Source'!$M$5:$M$178,'Expense Source'!$D$5:$D$178,A61,'Expense Source'!$U$5:$U$178,1)) -> 0 | G61: =IF(A61="","",IF(COUNTIFS('Income Source'!$B$5:$B$65,A61)=0,"",IF($Q$3="All",SUMIFS('Income Source'!$G$5:$G$65,'Income Source'!$B$5:$B$65,A61),SUM(B61:D61)))) -> 668 | H61: =IF(A61="","",IF(COUNTIFS('Income Source'!$B$5:$B$65,A61)=0,"",G61-F61)) -> 668 | I61: =IF(OR(A61="",COUNTIFS('Income Source'!$B$5:$B$65,A61)=0,G61=0),"",H61/G61) -> 1 | J61: =IF(A61="","",IF(COUNTIFS('Income Source'!$B$5:$B$65,A61)=0,"Revenue source missing",IF(ABS(E61-G61)>0.005,"Income/revenue mismatch","OK"))) -> OK
A62: =IF($B$3="All",46249,IF(45<31,IF($B$3="July 2026",46204,46235)+45,"")) -> 46249 | B62: =IF(A62="","",IF(COUNTIFS('Income Source'!$B$5:$B$65,A62)=0,"",IF(OR($Q$3="All",$Q$3="Walk-in"),SUMIFS('Income Source'!$C$5:$C$65,'Income Source'!$B$5:$B$65,A62),0))) -> 112 | C62: =IF(A62="","",IF(COUNTIFS('Income Source'!$B$5:$B$65,A62)=0,"",IF(OR($Q$3="All",$Q$3="Colonie"),SUMIFS('Income Source'!$D$5:$D$65,'Income Source'!$B$5:$B$65,A62),0))) -> 723 | D62: =IF(A62="","",IF(COUNTIFS('Income Source'!$B$5:$B$65,A62)=0,"",IF(OR($Q$3="All",$Q$3="Birthday"),SUMIFS('Income Source'!$E$5:$E$65,'Income Source'!$B$5:$B$65,A62),0))) -> 0 | E62: =IF(A62="","",IF(COUNTIFS('Income Source'!$B$5:$B$65,A62)=0,"",SUM(B62:D62))) -> 835 | F62: =IF(A62="","",SUMIFS('Expense Source'!$M$5:$M$178,'Expense Source'!$D$5:$D$178,A62,'Expense Source'!$U$5:$U$178,1)) -> 180.33684 | G62: =IF(A62="","",IF(COUNTIFS('Income Source'!$B$5:$B$65,A62)=0,"",IF($Q$3="All",SUMIFS('Income Source'!$G$5:$G$65,'Income Source'!$B$5:$B$65,A62),SUM(B62:D62)))) -> 835 | H62: =IF(A62="","",IF(COUNTIFS('Income Source'!$B$5:$B$65,A62)=0,"",G62-F62)) -> 654.66316 | I62: =IF(OR(A62="",COUNTIFS('Income Source'!$B$5:$B$65,A62)=0,G62=0),"",H62/G62) -> 0.78402773 | J62: =IF(A62="","",IF(COUNTIFS('Income Source'!$B$5:$B$65,A62)=0,"Revenue source missing",IF(ABS(E62-G62)>0.005,"Income/revenue mismatch","OK"))) -> OK
A63: =IF($B$3="All",46250,IF(46<31,IF($B$3="July 2026",46204,46235)+46,"")) -> 46250 | B63: =IF(A63="","",IF(COUNTIFS('Income Source'!$B$5:$B$65,A63)=0,"",IF(OR($Q$3="All",$Q$3="Walk-in"),SUMIFS('Income Source'!$C$5:$C$65,'Income Source'!$B$5:$B$65,A63),0))) -> 154 | C63: =IF(A63="","",IF(COUNTIFS('Income Source'!$B$5:$B$65,A63)=0,"",IF(OR($Q$3="All",$Q$3="Colonie"),SUMIFS('Income Source'!$D$5:$D$65,'Income Source'!$B$5:$B$65,A63),0))) -> 0 | D63: =IF(A63="","",IF(COUNTIFS('Income Source'!$B$5:$B$65,A63)=0,"",IF(OR($Q$3="All",$Q$3="Birthday"),SUMIFS('Income Source'!$E$5:$E$65,'Income Source'!$B$5:$B$65,A63),0))) -> 0 | E63: =IF(A63="","",IF(COUNTIFS('Income Source'!$B$5:$B$65,A63)=0,"",SUM(B63:D63))) -> 154 | F63: =IF(A63="","",SUMIFS('Expense Source'!$M$5:$M$178,'Expense Source'!$D$5:$D$178,A63,'Expense Source'!$U$5:$U$178,1)) -> 13.8 | G63: =IF(A63="","",IF(COUNTIFS('Income Source'!$B$5:$B$65,A63)=0,"",IF($Q$3="All",SUMIFS('Income Source'!$G$5:$G$65,'Income Source'!$B$5:$B$65,A63),SUM(B63:D63)))) -> 154 | H63: =IF(A63="","",IF(COUNTIFS('Income Source'!$B$5:$B$65,A63)=0,"",G63-F63)) -> 140.2 | I63: =IF(OR(A63="",COUNTIFS('Income Source'!$B$5:$B$65,A63)=0,G63=0),"",H63/G63) -> 0.91038961 | J63: =IF(A63="","",IF(COUNTIFS('Income Source'!$B$5:$B$65,A63)=0,"Revenue source missing",IF(ABS(E63-G63)>0.005,"Income/revenue mismatch","OK"))) -> OK
A64: =IF($B$3="All",46251,IF(47<31,IF($B$3="July 2026",46204,46235)+47,"")) -> 46251 | B64: =IF(A64="","",IF(COUNTIFS('Income Source'!$B$5:$B$65,A64)=0,"",IF(OR($Q$3="All",$Q$3="Walk-in"),SUMIFS('Income Source'!$C$5:$C$65,'Income Source'!$B$5:$B$65,A64),0))) -> 0 | C64: =IF(A64="","",IF(COUNTIFS('Income Source'!$B$5:$B$65,A64)=0,"",IF(OR($Q$3="All",$Q$3="Colonie"),SUMIFS('Income Source'!$D$5:$D$65,'Income Source'!$B$5:$B$65,A64),0))) -> 560 | D64: =IF(A64="","",IF(COUNTIFS('Income Source'!$B$5:$B$65,A64)=0,"",IF(OR($Q$3="All",$Q$3="Birthday"),SUMIFS('Income Source'!$E$5:$E$65,'Income Source'!$B$5:$B$65,A64),0))) -> 0 | E64: =IF(A64="","",IF(COUNTIFS('Income Source'!$B$5:$B$65,A64)=0,"",SUM(B64:D64))) -> 560 | F64: =IF(A64="","",SUMIFS('Expense Source'!$M$5:$M$178,'Expense Source'!$D$5:$D$178,A64,'Expense Source'!$U$5:$U$178,1)) -> 5.8333333 | G64: =IF(A64="","",IF(COUNTIFS('Income Source'!$B$5:$B$65,A64)=0,"",IF($Q$3="All",SUMIFS('Income Source'!$G$5:$G$65,'Income Source'!$B$5:$B$65,A64),SUM(B64:D64)))) -> 560 | H64: =IF(A64="","",IF(COUNTIFS('Income Source'!$B$5:$B$65,A64)=0,"",G64-F64)) -> 554.16667 | I64: =IF(OR(A64="",COUNTIFS('Income Source'!$B$5:$B$65,A64)=0,G64=0),"",H64/G64) -> 0.98958333 | J64: =IF(A64="","",IF(COUNTIFS('Income Source'!$B$5:$B$65,A64)=0,"Revenue source missing",IF(ABS(E64-G64)>0.005,"Income/revenue mismatch","OK"))) -> OK
A65: =IF($B$3="All",46252,IF(48<31,IF($B$3="July 2026",46204,46235)+48,"")) -> 46252 | B65: =IF(A65="","",IF(COUNTIFS('Income Source'!$B$5:$B$65,A65)=0,"",IF(OR($Q$3="All",$Q$3="Walk-in"),SUMIFS('Income Source'!$C$5:$C$65,'Income Source'!$B$5:$B$65,A65),0))) -> 0 | C65: =IF(A65="","",IF(COUNTIFS('Income Source'!$B$5:$B$65,A65)=0,"",IF(OR($Q$3="All",$Q$3="Colonie"),SUMIFS('Income Source'!$D$5:$D$65,'Income Source'!$B$5:$B$65,A65),0))) -> 0 | D65: =IF(A65="","",IF(COUNTIFS('Income Source'!$B$5:$B$65,A65)=0,"",IF(OR($Q$3="All",$Q$3="Birthday"),SUMIFS('Income Source'!$E$5:$E$65,'Income Source'!$B$5:$B$65,A65),0))) -> 717 | E65: =IF(A65="","",IF(COUNTIFS('Income Source'!$B$5:$B$65,A65)=0,"",SUM(B65:D65))) -> 717 | F65: =IF(A65="","",SUMIFS('Expense Source'!$M$5:$M$178,'Expense Source'!$D$5:$D$178,A65,'Expense Source'!$U$5:$U$178,1)) -> 144.89633 | G65: =IF(A65="","",IF(COUNTIFS('Income Source'!$B$5:$B$65,A65)=0,"",IF($Q$3="All",SUMIFS('Income Source'!$G$5:$G$65,'Income Source'!$B$5:$B$65,A65),SUM(B65:D65)))) -> 717 | H65: =IF(A65="","",IF(COUNTIFS('Income Source'!$B$5:$B$65,A65)=0,"",G65-F65)) -> 572.10367 | I65: =IF(OR(A65="",COUNTIFS('Income Source'!$B$5:$B$65,A65)=0,G65=0),"",H65/G65) -> 0.79791307 | J65: =IF(A65="","",IF(COUNTIFS('Income Source'!$B$5:$B$65,A65)=0,"Revenue source missing",IF(ABS(E65-G65)>0.005,"Income/revenue mismatch","OK"))) -> OK
A66: =IF($B$3="All",46253,IF(49<31,IF($B$3="July 2026",46204,46235)+49,"")) -> 46253 | B66: =IF(A66="","",IF(COUNTIFS('Income Source'!$B$5:$B$65,A66)=0,"",IF(OR($Q$3="All",$Q$3="Walk-in"),SUMIFS('Income Source'!$C$5:$C$65,'Income Source'!$B$5:$B$65,A66),0))) -> 0 | C66: =IF(A66="","",IF(COUNTIFS('Income Source'!$B$5:$B$65,A66)=0,"",IF(OR($Q$3="All",$Q$3="Colonie"),SUMIFS('Income Source'!$D$5:$D$65,'Income Source'!$B$5:$B$65,A66),0))) -> 0 | D66: =IF(A66="","",IF(COUNTIFS('Income Source'!$B$5:$B$65,A66)=0,"",IF(OR($Q$3="All",$Q$3="Birthday"),SUMIFS('Income Source'!$E$5:$E$65,'Income Source'!$B$5:$B$65,A66),0))) -> 0 | E66: =IF(A66="","",IF(COUNTIFS('Income Source'!$B$5:$B$65,A66)=0,"",SUM(B66:D66))) -> 0 | F66: =IF(A66="","",SUMIFS('Expense Source'!$M$5:$M$178,'Expense Source'!$D$5:$D$178,A66,'Expense Source'!$U$5:$U$178,1)) -> 0 | G66: =IF(A66="","",IF(COUNTIFS('Income Source'!$B$5:$B$65,A66)=0,"",IF($Q$3="All",SUMIFS('Income Source'!$G$5:$G$65,'Income Source'!$B$5:$B$65,A66),SUM(B66:D66)))) -> 0 | H66: =IF(A66="","",IF(COUNTIFS('Income Source'!$B$5:$B$65,A66)=0,"",G66-F66)) -> 0 | I66: =IF(OR(A66="",COUNTIFS('Income Source'!$B$5:$B$65,A66)=0,G66=0),"",H66/G66) | J66: =IF(A66="","",IF(COUNTIFS('Income Source'!$B$5:$B$65,A66)=0,"Revenue source missing",IF(ABS(E66-G66)>0.005,"Income/revenue mismatch","OK"))) -> OK
A67: =IF($B$3="All",46254,IF(50<31,IF($B$3="July 2026",46204,46235)+50,"")) -> 46254 | B67: =IF(A67="","",IF(COUNTIFS('Income Source'!$B$5:$B$65,A67)=0,"",IF(OR($Q$3="All",$Q$3="Walk-in"),SUMIFS('Income Source'!$C$5:$C$65,'Income Source'!$B$5:$B$65,A67),0))) -> 0 | C67: =IF(A67="","",IF(COUNTIFS('Income Source'!$B$5:$B$65,A67)=0,"",IF(OR($Q$3="All",$Q$3="Colonie"),SUMIFS('Income Source'!$D$5:$D$65,'Income Source'!$B$5:$B$65,A67),0))) -> 0 | D67: =IF(A67="","",IF(COUNTIFS('Income Source'!$B$5:$B$65,A67)=0,"",IF(OR($Q$3="All",$Q$3="Birthday"),SUMIFS('Income Source'!$E$5:$E$65,'Income Source'!$B$5:$B$65,A67),0))) -> 0 | E67: =IF(A67="","",IF(COUNTIFS('Income Source'!$B$5:$B$65,A67)=0,"",SUM(B67:D67))) -> 0 | F67: =IF(A67="","",SUMIFS('Expense Source'!$M$5:$M$178,'Expense Source'!$D$5:$D$178,A67,'Expense Source'!$U$5:$U$178,1)) -> 0 | G67: =IF(A67="","",IF(COUNTIFS('Income Source'!$B$5:$B$65,A67)=0,"",IF($Q$3="All",SUMIFS('Income Source'!$G$5:$G$65,'Income Source'!$B$5:$B$65,A67),SUM(B67:D67)))) -> 0 | H67: =IF(A67="","",IF(COUNTIFS('Income Source'!$B$5:$B$65,A67)=0,"",G67-F67)) -> 0 | I67: =IF(OR(A67="",COUNTIFS('Income Source'!$B$5:$B$65,A67)=0,G67=0),"",H67/G67) | J67: =IF(A67="","",IF(COUNTIFS('Income Source'!$B$5:$B$65,A67)=0,"Revenue source missing",IF(ABS(E67-G67)>0.005,"Income/revenue mismatch","OK"))) -> OK
A68: =IF($B$3="All",46255,IF(51<31,IF($B$3="July 2026",46204,46235)+51,"")) -> 46255 | B68: =IF(A68="","",IF(COUNTIFS('Income Source'!$B$5:$B$65,A68)=0,"",IF(OR($Q$3="All",$Q$3="Walk-in"),SUMIFS('Income Source'!$C$5:$C$65,'Income Source'!$B$5:$B$65,A68),0))) -> 538 | C68: =IF(A68="","",IF(COUNTIFS('Income Source'!$B$5:$B$65,A68)=0,"",IF(OR($Q$3="All",$Q$3="Colonie"),SUMIFS('Income Source'!$D$5:$D$65,'Income Source'!$B$5:$B$65,A68),0))) -> 0 | D68: =IF(A68="","",IF(COUNTIFS('Income Source'!$B$5:$B$65,A68)=0,"",IF(OR($Q$3="All",$Q$3="Birthday"),SUMIFS('Income Source'!$E$5:$E$65,'Income Source'!$B$5:$B$65,A68),0))) -> 600 | E68: =IF(A68="","",IF(COUNTIFS('Income Source'!$B$5:$B$65,A68)=0,"",SUM(B68:D68))) -> 1138 | F68: =IF(A68="","",SUMIFS('Expense Source'!$M$5:$M$178,'Expense Source'!$D$5:$D$178,A68,'Expense Source'!$U$5:$U$178,1)) -> 0 | G68: =IF(A68="","",IF(COUNTIFS('Income Source'!$B$5:$B$65,A68)=0,"",IF($Q$3="All",SUMIFS('Income Source'!$G$5:$G$65,'Income Source'!$B$5:$B$65,A68),SUM(B68:D68)))) -> 1138 | H68: =IF(A68="","",IF(COUNTIFS('Income Source'!$B$5:$B$65,A68)=0,"",G68-F68)) -> 1138 | I68: =IF(OR(A68="",COUNTIFS('Income Source'!$B$5:$B$65,A68)=0,G68=0),"",H68/G68) -> 1 | J68: =IF(A68="","",IF(COUNTIFS('Income Source'!$B$5:$B$65,A68)=0,"Revenue source missing",IF(ABS(E68-G68)>0.005,"Income/revenue mismatch","OK"))) -> OK
A69: =IF($B$3="All",46256,IF(52<31,IF($B$3="July 2026",46204,46235)+52,"")) -> 46256 | B69: =IF(A69="","",IF(COUNTIFS('Income Source'!$B$5:$B$65,A69)=0,"",IF(OR($Q$3="All",$Q$3="Walk-in"),SUMIFS('Income Source'!$C$5:$C$65,'Income Source'!$B$5:$B$65,A69),0))) -> 294 | C69: =IF(A69="","",IF(COUNTIFS('Income Source'!$B$5:$B$65,A69)=0,"",IF(OR($Q$3="All",$Q$3="Colonie"),SUMIFS('Income Source'!$D$5:$D$65,'Income Source'!$B$5:$B$65,A69),0))) -> 0 | D69: =IF(A69="","",IF(COUNTIFS('Income Source'!$B$5:$B$65,A69)=0,"",IF(OR($Q$3="All",$Q$3="Birthday"),SUMIFS('Income Source'!$E$5:$E$65,'Income Source'!$B$5:$B$65,A69),0))) -> 0 | E69: =IF(A69="","",IF(COUNTIFS('Income Source'!$B$5:$B$65,A69)=0,"",SUM(B69:D69))) -> 294 | F69: =IF(A69="","",SUMIFS('Expense Source'!$M$5:$M$178,'Expense Source'!$D$5:$D$178,A69,'Expense Source'!$U$5:$U$178,1)) -> 0 | G69: =IF(A69="","",IF(COUNTIFS('Income Source'!$B$5:$B$65,A69)=0,"",IF($Q$3="All",SUMIFS('Income Source'!$G$5:$G$65,'Income Source'!$B$5:$B$65,A69),SUM(B69:D69)))) -> 294 | H69: =IF(A69="","",IF(COUNTIFS('Income Source'!$B$5:$B$65,A69)=0,"",G69-F69)) -> 294 | I69: =IF(OR(A69="",COUNTIFS('Income Source'!$B$5:$B$65,A69)=0,G69=0),"",H69/G69) -> 1 | J69: =IF(A69="","",IF(COUNTIFS('Income Source'!$B$5:$B$65,A69)=0,"Revenue source missing",IF(ABS(E69-G69)>0.005,"Income/revenue mismatch","OK"))) -> OK
A70: =IF($B$3="All",46257,IF(53<31,IF($B$3="July 2026",46204,46235)+53,"")) -> 46257 | B70: =IF(A70="","",IF(COUNTIFS('Income Source'!$B$5:$B$65,A70)=0,"",IF(OR($Q$3="All",$Q$3="Walk-in"),SUMIFS('Income Source'!$C$5:$C$65,'Income Source'!$B$5:$B$65,A70),0))) -> 135 | C70: =IF(A70="","",IF(COUNTIFS('Income Source'!$B$5:$B$65,A70)=0,"",IF(OR($Q$3="All",$Q$3="Colonie"),SUMIFS('Income Source'!$D$5:$D$65,'Income Source'!$B$5:$B$65,A70),0))) -> 0 | D70: =IF(A70="","",IF(COUNTIFS('Income Source'!$B$5:$B$65,A70)=0,"",IF(OR($Q$3="All",$Q$3="Birthday"),SUMIFS('Income Source'!$E$5:$E$65,'Income Source'!$B$5:$B$65,A70),0))) -> 0 | E70: =IF(A70="","",IF(COUNTIFS('Income Source'!$B$5:$B$65,A70)=0,"",SUM(B70:D70))) -> 135 | F70: =IF(A70="","",SUMIFS('Expense Source'!$M$5:$M$178,'Expense Source'!$D$5:$D$178,A70,'Expense Source'!$U$5:$U$178,1)) -> 0 | G70: =IF(A70="","",IF(COUNTIFS('Income Source'!$B$5:$B$65,A70)=0,"",IF($Q$3="All",SUMIFS('Income Source'!$G$5:$G$65,'Income Source'!$B$5:$B$65,A70),SUM(B70:D70)))) -> 135 | H70: =IF(A70="","",IF(COUNTIFS('Income Source'!$B$5:$B$65,A70)=0,"",G70-F70)) -> 135 | I70: =IF(OR(A70="",COUNTIFS('Income Source'!$B$5:$B$65,A70)=0,G70=0),"",H70/G70) -> 1 | J70: =IF(A70="","",IF(COUNTIFS('Income Source'!$B$5:$B$65,A70)=0,"Revenue source missing",IF(ABS(E70-G70)>0.005,"Income/revenue mismatch","OK"))) -> OK
A71: =IF($B$3="All",46258,IF(54<31,IF($B$3="July 2026",46204,46235)+54,"")) -> 46258 | B71: =IF(A71="","",IF(COUNTIFS('Income Source'!$B$5:$B$65,A71)=0,"",IF(OR($Q$3="All",$Q$3="Walk-in"),SUMIFS('Income Source'!$C$5:$C$65,'Income Source'!$B$5:$B$65,A71),0))) -> 0 | C71: =IF(A71="","",IF(COUNTIFS('Income Source'!$B$5:$B$65,A71)=0,"",IF(OR($Q$3="All",$Q$3="Colonie"),SUMIFS('Income Source'!$D$5:$D$65,'Income Source'!$B$5:$B$65,A71),0))) -> 0 | D71: =IF(A71="","",IF(COUNTIFS('Income Source'!$B$5:$B$65,A71)=0,"",IF(OR($Q$3="All",$Q$3="Birthday"),SUMIFS('Income Source'!$E$5:$E$65,'Income Source'!$B$5:$B$65,A71),0))) -> 0 | E71: =IF(A71="","",IF(COUNTIFS('Income Source'!$B$5:$B$65,A71)=0,"",SUM(B71:D71))) -> 0 | F71: =IF(A71="","",SUMIFS('Expense Source'!$M$5:$M$178,'Expense Source'!$D$5:$D$178,A71,'Expense Source'!$U$5:$U$178,1)) -> 0 | G71: =IF(A71="","",IF(COUNTIFS('Income Source'!$B$5:$B$65,A71)=0,"",IF($Q$3="All",SUMIFS('Income Source'!$G$5:$G$65,'Income Source'!$B$5:$B$65,A71),SUM(B71:D71)))) -> 0 | H71: =IF(A71="","",IF(COUNTIFS('Income Source'!$B$5:$B$65,A71)=0,"",G71-F71)) -> 0 | I71: =IF(OR(A71="",COUNTIFS('Income Source'!$B$5:$B$65,A71)=0,G71=0),"",H71/G71) | J71: =IF(A71="","",IF(COUNTIFS('Income Source'!$B$5:$B$65,A71)=0,"Revenue source missing",IF(ABS(E71-G71)>0.005,"Income/revenue mismatch","OK"))) -> OK
A72: =IF($B$3="All",46259,IF(55<31,IF($B$3="July 2026",46204,46235)+55,"")) -> 46259 | B72: =IF(A72="","",IF(COUNTIFS('Income Source'!$B$5:$B$65,A72)=0,"",IF(OR($Q$3="All",$Q$3="Walk-in"),SUMIFS('Income Source'!$C$5:$C$65,'Income Source'!$B$5:$B$65,A72),0))) -> 199 | C72: =IF(A72="","",IF(COUNTIFS('Income Source'!$B$5:$B$65,A72)=0,"",IF(OR($Q$3="All",$Q$3="Colonie"),SUMIFS('Income Source'!$D$5:$D$65,'Income Source'!$B$5:$B$65,A72),0))) -> 0 | D72: =IF(A72="","",IF(COUNTIFS('Income Source'!$B$5:$B$65,A72)=0,"",IF(OR($Q$3="All",$Q$3="Birthday"),SUMIFS('Income Source'!$E$5:$E$65,'Income Source'!$B$5:$B$65,A72),0))) -> 0 | E72: =IF(A72="","",IF(COUNTIFS('Income Source'!$B$5:$B$65,A72)=0,"",SUM(B72:D72))) -> 199 | F72: =IF(A72="","",SUMIFS('Expense Source'!$M$5:$M$178,'Expense Source'!$D$5:$D$178,A72,'Expense Source'!$U$5:$U$178,1)) -> 0 | G72: =IF(A72="","",IF(COUNTIFS('Income Source'!$B$5:$B$65,A72)=0,"",IF($Q$3="All",SUMIFS('Income Source'!$G$5:$G$65,'Income Source'!$B$5:$B$65,A72),SUM(B72:D72)))) -> 199 | H72: =IF(A72="","",IF(COUNTIFS('Income Source'!$B$5:$B$65,A72)=0,"",G72-F72)) -> 199 | I72: =IF(OR(A72="",COUNTIFS('Income Source'!$B$5:$B$65,A72)=0,G72=0),"",H72/G72) -> 1 | J72: =IF(A72="","",IF(COUNTIFS('Income Source'!$B$5:$B$65,A72)=0,"Revenue source missing",IF(ABS(E72-G72)>0.005,"Income/revenue mismatch","OK"))) -> OK
A73: =IF($B$3="All",46260,IF(56<31,IF($B$3="July 2026",46204,46235)+56,"")) -> 46260 | B73: =IF(A73="","",IF(COUNTIFS('Income Source'!$B$5:$B$65,A73)=0,"",IF(OR($Q$3="All",$Q$3="Walk-in"),SUMIFS('Income Source'!$C$5:$C$65,'Income Source'!$B$5:$B$65,A73),0))) -> 145 | C73: =IF(A73="","",IF(COUNTIFS('Income Source'!$B$5:$B$65,A73)=0,"",IF(OR($Q$3="All",$Q$3="Colonie"),SUMIFS('Income Source'!$D$5:$D$65,'Income Source'!$B$5:$B$65,A73),0))) -> 240 | D73: =IF(A73="","",IF(COUNTIFS('Income Source'!$B$5:$B$65,A73)=0,"",IF(OR($Q$3="All",$Q$3="Birthday"),SUMIFS('Income Source'!$E$5:$E$65,'Income Source'!$B$5:$B$65,A73),0))) -> 510 | E73: =IF(A73="","",IF(COUNTIFS('Income Source'!$B$5:$B$65,A73)=0,"",SUM(B73:D73))) -> 895 | F73: =IF(A73="","",SUMIFS('Expense Source'!$M$5:$M$178,'Expense Source'!$D$5:$D$178,A73,'Expense Source'!$U$5:$U$178,1)) -> 125.17441 | G73: =IF(A73="","",IF(COUNTIFS('Income Source'!$B$5:$B$65,A73)=0,"",IF($Q$3="All",SUMIFS('Income Source'!$G$5:$G$65,'Income Source'!$B$5:$B$65,A73),SUM(B73:D73)))) -> 895 | H73: =IF(A73="","",IF(COUNTIFS('Income Source'!$B$5:$B$65,A73)=0,"",G73-F73)) -> 769.82559 | I73: =IF(OR(A73="",COUNTIFS('Income Source'!$B$5:$B$65,A73)=0,G73=0),"",H73/G73) -> 0.86014033 | J73: =IF(A73="","",IF(COUNTIFS('Income Source'!$B$5:$B$65,A73)=0,"Revenue source missing",IF(ABS(E73-G73)>0.005,"Income/revenue mismatch","OK"))) -> OK
A74: =IF($B$3="All",46261,IF(57<31,IF($B$3="July 2026",46204,46235)+57,"")) -> 46261 | B74: =IF(A74="","",IF(COUNTIFS('Income Source'!$B$5:$B$65,A74)=0,"",IF(OR($Q$3="All",$Q$3="Walk-in"),SUMIFS('Income Source'!$C$5:$C$65,'Income Source'!$B$5:$B$65,A74),0))) -> 0 | C74: =IF(A74="","",IF(COUNTIFS('Income Source'!$B$5:$B$65,A74)=0,"",IF(OR($Q$3="All",$Q$3="Colonie"),SUMIFS('Income Source'!$D$5:$D$65,'Income Source'!$B$5:$B$65,A74),0))) -> 0 | D74: =IF(A74="","",IF(COUNTIFS('Income Source'!$B$5:$B$65,A74)=0,"",IF(OR($Q$3="All",$Q$3="Birthday"),SUMIFS('Income Source'!$E$5:$E$65,'Income Source'!$B$5:$B$65,A74),0))) -> 0 | E74: =IF(A74="","",IF(COUNTIFS('Income Source'!$B$5:$B$65,A74)=0,"",SUM(B74:D74))) -> 0 | F74: =IF(A74="","",SUMIFS('Expense Source'!$M$5:$M$178,'Expense Source'!$D$5:$D$178,A74,'Expense Source'!$U$5:$U$178,1)) -> 0 | G74: =IF(A74="","",IF(COUNTIFS('Income Source'!$B$5:$B$65,A74)=0,"",IF($Q$3="All",SUMIFS('Income Source'!$G$5:$G$65,'Income Source'!$B$5:$B$65,A74),SUM(B74:D74)))) -> 0 | H74: =IF(A74="","",IF(COUNTIFS('Income Source'!$B$5:$B$65,A74)=0,"",G74-F74)) -> 0 | I74: =IF(OR(A74="",COUNTIFS('Income Source'!$B$5:$B$65,A74)=0,G74=0),"",H74/G74) | J74: =IF(A74="","",IF(COUNTIFS('Income Source'!$B$5:$B$65,A74)=0,"Revenue source missing",IF(ABS(E74-G74)>0.005,"Income/revenue mismatch","OK"))) -> OK
A75: =IF($B$3="All",46262,IF(58<31,IF($B$3="July 2026",46204,46235)+58,"")) -> 46262 | B75: =IF(A75="","",IF(COUNTIFS('Income Source'!$B$5:$B$65,A75)=0,"",IF(OR($Q$3="All",$Q$3="Walk-in"),SUMIFS('Income Source'!$C$5:$C$65,'Income Source'!$B$5:$B$65,A75),0))) -> 0 | C75: =IF(A75="","",IF(COUNTIFS('Income Source'!$B$5:$B$65,A75)=0,"",IF(OR($Q$3="All",$Q$3="Colonie"),SUMIFS('Income Source'!$D$5:$D$65,'Income Source'!$B$5:$B$65,A75),0))) -> 0 | D75: =IF(A75="","",IF(COUNTIFS('Income Source'!$B$5:$B$65,A75)=0,"",IF(OR($Q$3="All",$Q$3="Birthday"),SUMIFS('Income Source'!$E$5:$E$65,'Income Source'!$B$5:$B$65,A75),0))) -> 700 | E75: =IF(A75="","",IF(COUNTIFS('Income Source'!$B$5:$B$65,A75)=0,"",SUM(B75:D75))) -> 700 | F75: =IF(A75="","",SUMIFS('Expense Source'!$M$5:$M$178,'Expense Source'!$D$5:$D$178,A75,'Expense Source'!$U$5:$U$178,1)) -> 0 | G75: =IF(A75="","",IF(COUNTIFS('Income Source'!$B$5:$B$65,A75)=0,"",IF($Q$3="All",SUMIFS('Income Source'!$G$5:$G$65,'Income Source'!$B$5:$B$65,A75),SUM(B75:D75)))) -> 700 | H75: =IF(A75="","",IF(COUNTIFS('Income Source'!$B$5:$B$65,A75)=0,"",G75-F75)) -> 700 | I75: =IF(OR(A75="",COUNTIFS('Income Source'!$B$5:$B$65,A75)=0,G75=0),"",H75/G75) -> 1 | J75: =IF(A75="","",IF(COUNTIFS('Income Source'!$B$5:$B$65,A75)=0,"Revenue source missing",IF(ABS(E75-G75)>0.005,"Income/revenue mismatch","OK"))) -> OK
A76: =IF($B$3="All",46263,IF(59<31,IF($B$3="July 2026",46204,46235)+59,"")) -> 46263 | B76: =IF(A76="","",IF(COUNTIFS('Income Source'!$B$5:$B$65,A76)=0,"",IF(OR($Q$3="All",$Q$3="Walk-in"),SUMIFS('Income Source'!$C$5:$C$65,'Income Source'!$B$5:$B$65,A76),0))) -> 157 | C76: =IF(A76="","",IF(COUNTIFS('Income Source'!$B$5:$B$65,A76)=0,"",IF(OR($Q$3="All",$Q$3="Colonie"),SUMIFS('Income Source'!$D$5:$D$65,'Income Source'!$B$5:$B$65,A76),0))) -> 0 | D76: =IF(A76="","",IF(COUNTIFS('Income Source'!$B$5:$B$65,A76)=0,"",IF(OR($Q$3="All",$Q$3="Birthday"),SUMIFS('Income Source'!$E$5:$E$65,'Income Source'!$B$5:$B$65,A76),0))) -> 600 | E76: =IF(A76="","",IF(COUNTIFS('Income Source'!$B$5:$B$65,A76)=0,"",SUM(B76:D76))) -> 757 | F76: =IF(A76="","",SUMIFS('Expense Source'!$M$5:$M$178,'Expense Source'!$D$5:$D$178,A76,'Expense Source'!$U$5:$U$178,1)) -> 82.620899 | G76: =IF(A76="","",IF(COUNTIFS('Income Source'!$B$5:$B$65,A76)=0,"",IF($Q$3="All",SUMIFS('Income Source'!$G$5:$G$65,'Income Source'!$B$5:$B$65,A76),SUM(B76:D76)))) -> 757 | H76: =IF(A76="","",IF(COUNTIFS('Income Source'!$B$5:$B$65,A76)=0,"",G76-F76)) -> 674.3791 | I76: =IF(OR(A76="",COUNTIFS('Income Source'!$B$5:$B$65,A76)=0,G76=0),"",H76/G76) -> 0.89085747 | J76: =IF(A76="","",IF(COUNTIFS('Income Source'!$B$5:$B$65,A76)=0,"Revenue source missing",IF(ABS(E76-G76)>0.005,"Income/revenue mismatch","OK"))) -> OK
A77: =IF($B$3="All",46264,IF(60<31,IF($B$3="July 2026",46204,46235)+60,"")) -> 46264 | B77: =IF(A77="","",IF(COUNTIFS('Income Source'!$B$5:$B$65,A77)=0,"",IF(OR($Q$3="All",$Q$3="Walk-in"),SUMIFS('Income Source'!$C$5:$C$65,'Income Source'!$B$5:$B$65,A77),0))) -> 167 | C77: =IF(A77="","",IF(COUNTIFS('Income Source'!$B$5:$B$65,A77)=0,"",IF(OR($Q$3="All",$Q$3="Colonie"),SUMIFS('Income Source'!$D$5:$D$65,'Income Source'!$B$5:$B$65,A77),0))) -> 0 | D77: =IF(A77="","",IF(COUNTIFS('Income Source'!$B$5:$B$65,A77)=0,"",IF(OR($Q$3="All",$Q$3="Birthday"),SUMIFS('Income Source'!$E$5:$E$65,'Income Source'!$B$5:$B$65,A77),0))) -> 0 | E77: =IF(A77="","",IF(COUNTIFS('Income Source'!$B$5:$B$65,A77)=0,"",SUM(B77:D77))) -> 167 | F77: =IF(A77="","",SUMIFS('Expense Source'!$M$5:$M$178,'Expense Source'!$D$5:$D$178,A77,'Expense Source'!$U$5:$U$178,1)) -> 0 | G77: =IF(A77="","",IF(COUNTIFS('Income Source'!$B$5:$B$65,A77)=0,"",IF($Q$3="All",SUMIFS('Income Source'!$G$5:$G$65,'Income Source'!$B$5:$B$65,A77),SUM(B77:D77)))) -> 167 | H77: =IF(A77="","",IF(COUNTIFS('Income Source'!$B$5:$B$65,A77)=0,"",G77-F77)) -> 167 | I77: =IF(OR(A77="",COUNTIFS('Income Source'!$B$5:$B$65,A77)=0,G77=0),"",H77/G77) -> 1 | J77: =IF(A77="","",IF(COUNTIFS('Income Source'!$B$5:$B$65,A77)=0,"Revenue source missing",IF(ABS(E77-G77)>0.005,"Income/revenue mismatch","OK"))) -> OK
A78: =IF($B$3="All",46265,IF(61<31,IF($B$3="July 2026",46204,46235)+61,"")) -> 46265 | B78: =IF(A78="","",IF(COUNTIFS('Income Source'!$B$5:$B$65,A78)=0,"",IF(OR($Q$3="All",$Q$3="Walk-in"),SUMIFS('Income Source'!$C$5:$C$65,'Income Source'!$B$5:$B$65,A78),0))) -> 0 | C78: =IF(A78="","",IF(COUNTIFS('Income Source'!$B$5:$B$65,A78)=0,"",IF(OR($Q$3="All",$Q$3="Colonie"),SUMIFS('Income Source'!$D$5:$D$65,'Income Source'!$B$5:$B$65,A78),0))) -> 0 | D78: =IF(A78="","",IF(COUNTIFS('Income Source'!$B$5:$B$65,A78)=0,"",IF(OR($Q$3="All",$Q$3="Birthday"),SUMIFS('Income Source'!$E$5:$E$65,'Income Source'!$B$5:$B$65,A78),0))) -> 0 | E78: =IF(A78="","",IF(COUNTIFS('Income Source'!$B$5:$B$65,A78)=0,"",SUM(B78:D78))) -> 0 | F78: =IF(A78="","",SUMIFS('Expense Source'!$M$5:$M$178,'Expense Source'!$D$5:$D$178,A78,'Expense Source'!$U$5:$U$178,1)) -> 0 | G78: =IF(A78="","",IF(COUNTIFS('Income Source'!$B$5:$B$65,A78)=0,"",IF($Q$3="All",SUMIFS('Income Source'!$G$5:$G$65,'Income Source'!$B$5:$B$65,A78),SUM(B78:D78)))) -> 0 | H78: =IF(A78="","",IF(COUNTIFS('Income Source'!$B$5:$B$65,A78)=0,"",G78-F78)) -> 0 | I78: =IF(OR(A78="",COUNTIFS('Income Source'!$B$5:$B$65,A78)=0,G78=0),"",H78/G78) | J78: =IF(A78="","",IF(COUNTIFS('Income Source'!$B$5:$B$65,A78)=0,"Revenue source missing",IF(ABS(E78-G78)>0.005,"Income/revenue mismatch","OK"))) -> OK

Sheet Income Source
A1: M - July & August Income Source
A4: Source Sheet | B4: Date | C4: Walk-in | D4: Colonie | E4: Birthday | F4: Source Daily Expenses | G4: Source Revenue | H4: Source Check
A5: July | B5: 46205 | C5: 0 | D5: 520 | E5: 0 | G5: 520 | H5: =IF(ABS(G5-(SUM(C5:E5)-F5))<0.005,"OK","Check") -> OK
A6: July | B6: 46206 | C6: 0 | D6: 0 | E6: 434 | G6: 434 | H6: =IF(ABS(G6-(SUM(C6:E6)-F6))<0.005,"OK","Check") -> OK
A7: July | B7: 46207 | C7: 238 | D7: 100 | E7: 751 | G7: 1089 | H7: =IF(ABS(G7-(SUM(C7:E7)-F7))<0.005,"OK","Check") -> OK
A8: July | B8: 46208 | C8: 241 | D8: 0 | E8: 750 | G8: 991 | H8: =IF(ABS(G8-(SUM(C8:E8)-F8))<0.005,"OK","Check") -> OK
A9: July | B9: 46209 | G9: 0 | H9: =IF(ABS(G9-(SUM(C9:E9)-F9))<0.005,"OK","Check") -> OK
A10: July | B10: 46210 | G10: 0 | H10: =IF(ABS(G10-(SUM(C10:E10)-F10))<0.005,"OK","Check") -> OK
A11: July | B11: 46211 | D11: 760 | E11: 625 | G11: 1385 | H11: =IF(ABS(G11-(SUM(C11:E11)-F11))<0.005,"OK","Check") -> OK
A12: July | B12: 46212 | D12: 528 | G12: 528 | H12: =IF(ABS(G12-(SUM(C12:E12)-F12))<0.005,"OK","Check") -> OK
A13: July | B13: 46213 | D13: 384 | E13: 755 | G13: 1139 | H13: =IF(ABS(G13-(SUM(C13:E13)-F13))<0.005,"OK","Check") -> OK
A14: July | B14: 46214 | C14: 453 | E14: 1335 | G14: 1788 | H14: =IF(ABS(G14-(SUM(C14:E14)-F14))<0.005,"OK","Check") -> OK
A15: July | B15: 46215 | C15: 370 | E15: 550 | G15: 920 | H15: =IF(ABS(G15-(SUM(C15:E15)-F15))<0.005,"OK","Check") -> OK
A16: July | B16: 46216 | G16: 0 | H16: =IF(ABS(G16-(SUM(C16:E16)-F16))<0.005,"OK","Check") -> OK
A17: July | B17: 46217 | G17: 0 | H17: =IF(ABS(G17-(SUM(C17:E17)-F17))<0.005,"OK","Check") -> OK
A18: July | B18: 46218 | G18: 0 | H18: =IF(ABS(G18-(SUM(C18:E18)-F18))<0.005,"OK","Check") -> OK
A19: July | B19: 46219 | G19: 0 | H19: =IF(ABS(G19-(SUM(C19:E19)-F19))<0.005,"OK","Check") -> OK
A20: July | B20: 46220 | C20: 284 | E20: 520 | G20: 804 | H20: =IF(ABS(G20-(SUM(C20:E20)-F20))<0.005,"OK","Check") -> OK
A21: July | B21: 46221 | C21: 330 | E21: 1150 | G21: 1480 | H21: =IF(ABS(G21-(SUM(C21:E21)-F21))<0.005,"OK","Check") -> OK
A22: July | B22: 46222 | C22: 77 | E22: 525 | G22: 602 | H22: =IF(ABS(G22-(SUM(C22:E22)-F22))<0.005,"OK","Check") -> OK
A23: July | B23: 46223 | G23: 0 | H23: =IF(ABS(G23-(SUM(C23:E23)-F23))<0.005,"OK","Check") -> OK
A24: July | B24: 46224 | G24: 0 | H24: =IF(ABS(G24-(SUM(C24:E24)-F24))<0.005,"OK","Check") -> OK
A25: July | B25: 46225 | D25: 660 | G25: 660 | H25: =IF(ABS(G25-(SUM(C25:E25)-F25))<0.005,"OK","Check") -> OK
A26: July | B26: 46226 | G26: 0 | H26: =IF(ABS(G26-(SUM(C26:E26)-F26))<0.005,"OK","Check") -> OK
A27: July | B27: 46227 | C27: 228 | E27: 450 | G27: 678 | H27: =IF(ABS(G27-(SUM(C27:E27)-F27))<0.005,"OK","Check") -> OK
A28: July | B28: 46228 | C28: 191 | E28: 650 | G28: 841 | H28: =IF(ABS(G28-(SUM(C28:E28)-F28))<0.005,"OK","Check") -> OK
A29: July | B29: 46229 | E29: 1690 | G29: 1690 | H29: =IF(ABS(G29-(SUM(C29:E29)-F29))<0.005,"OK","Check") -> OK
A30: July | B30: 46230 | E30: 1477 | G30: 1477 | H30: =IF(ABS(G30-(SUM(C30:E30)-F30))<0.005,"OK","Check") -> OK
A31: July | B31: 46231 | C31: 0 | D31: 204 | G31: 204 | H31: =IF(ABS(G31-(SUM(C31:E31)-F31))<0.005,"OK","Check") -> OK
A32: July | B32: 46232 | E32: 950 | G32: 950 | H32: =IF(ABS(G32-(SUM(C32:E32)-F32))<0.005,"OK","Check") -> OK
A33: July | B33: 46233 | D33: 228 | G33: 228 | H33: =IF(ABS(G33-(SUM(C33:E33)-F33))<0.005,"OK","Check") -> OK
A34: July | B34: 46234 | C34: 166 | D34: 336 | E34: 185 | G34: 687 | H34: =IF(ABS(G34-(SUM(C34:E34)-F34))<0.005,"OK","Check") -> OK
A35: August | B35: 46235 | C35: 250 | D35: 0 | E35: 945 | G35: 1195 | H35: =IF(ABS(G35-(SUM(C35:E35)-F35))<0.005,"OK","Check") -> OK
A36: August | B36: 46236 | C36: 785 | D36: 0 | E36: 0 | G36: 785 | H36: =IF(ABS(G36-(SUM(C36:E36)-F36))<0.005,"OK","Check") -> OK
A37: August | B37: 46237 | C37: 0 | D37: 0 | E37: 0 | G37: 0 | H37: =IF(ABS(G37-(SUM(C37:E37)-F37))<0.005,"OK","Check") -> OK
A38: August | B38: 46238 | C38: 0 | D38: 0 | E38: 0 | G38: 0 | H38: =IF(ABS(G38-(SUM(C38:E38)-F38))<0.005,"OK","Check") -> OK
A39: August | B39: 46239 | C39: 0 | D39: 388 | G39: 388 | H39: =IF(ABS(G39-(SUM(C39:E39)-F39))<0.005,"OK","Check") -> OK
A40: August | B40: 46240 | C40: 0 | D40: 372 | G40: 372 | H40: =IF(ABS(G40-(SUM(C40:E40)-F40))<0.005,"OK","Check") -> OK
A41: August | B41: 46241 | C41: 0 | D41: 0 | E41: 0 | G41: 0 | H41: =IF(ABS(G41-(SUM(C41:E41)-F41))<0.005,"OK","Check") -> OK
A42: August | B42: 46242 | C42: 250 | D42: 950 | E42: 0 | G42: 1200 | H42: =IF(ABS(G42-(SUM(C42:E42)-F42))<0.005,"OK","Check") -> OK
A43: August | B43: 46243 | C43: 415 | D43: 860 | E43: 0 | G43: 1275 | H43: =IF(ABS(G43-(SUM(C43:E43)-F43))<0.005,"OK","Check") -> OK
A44: August | B44: 46244 | C44: 820 | D44: 400 | E44: 0 | G44: 1220 | H44: =IF(ABS(G44-(SUM(C44:E44)-F44))<0.005,"OK","Check") -> OK
A45: August | B45: 46245 | C45: 0 | D45: 0 | E45: 0 | G45: 0 | H45: =IF(ABS(G45-(SUM(C45:E45)-F45))<0.005,"OK","Check") -> OK
A46: August | B46: 46246 | C46: 0 | D46: 0 | G46: 0 | H46: =IF(ABS(G46-(SUM(C46:E46)-F46))<0.005,"OK","Check") -> OK
A47: August | B47: 46247 | C47: 0 | G47: 0 | H47: =IF(ABS(G47-(SUM(C47:E47)-F47))<0.005,"OK","Check") -> OK
A48: August | B48: 46248 | C48: 368 | D48: 300 | G48: 668 | H48: =IF(ABS(G48-(SUM(C48:E48)-F48))<0.005,"OK","Check") -> OK
A49: August | B49: 46249 | C49: 112 | D49: 723 | G49: 835 | H49: =IF(ABS(G49-(SUM(C49:E49)-F49))<0.005,"OK","Check") -> OK
A50: August | B50: 46250 | C50: 154 | E50: 0 | G50: 154 | H50: =IF(ABS(G50-(SUM(C50:E50)-F50))<0.005,"OK","Check") -> OK
A51: August | B51: 46251 | C51: 0 | D51: 560 | E51: 0 | G51: 560 | H51: =IF(ABS(G51-(SUM(C51:E51)-F51))<0.005,"OK","Check") -> OK
A52: August | B52: 46252 | C52: 0 | E52: 717 | G52: 717 | H52: =IF(ABS(G52-(SUM(C52:E52)-F52))<0.005,"OK","Check") -> OK
A53: August | B53: 46253 | C53: 0 | G53: 0 | H53: =IF(ABS(G53-(SUM(C53:E53)-F53))<0.005,"OK","Check") -> OK
A54: August | B54: 46254 | C54: 0 | G54: 0 | H54: =IF(ABS(G54-(SUM(C54:E54)-F54))<0.005,"OK","Check") -> OK
A55: August | B55: 46255 | C55: 538 | D55: 0 | E55: 600 | G55: 1138 | H55: =IF(ABS(G55-(SUM(C55:E55)-F55))<0.005,"OK","Check") -> OK
A56: August | B56: 46256 | C56: 294 | G56: 294 | H56: =IF(ABS(G56-(SUM(C56:E56)-F56))<0.005,"OK","Check") -> OK
A57: August | B57: 46257 | C57: 135 | E57: 0 | G57: 135 | H57: =IF(ABS(G57-(SUM(C57:E57)-F57))<0.005,"OK","Check") -> OK
A58: August | B58: 46258 | C58: 0 | E58: 0 | G58: 0 | H58: =IF(ABS(G58-(SUM(C58:E58)-F58))<0.005,"OK","Check") -> OK
A59: August | B59: 46259 | C59: 199 | E59: 0 | G59: 199 | H59: =IF(ABS(G59-(SUM(C59:E59)-F59))<0.005,"OK","Check") -> OK
A60: August | B60: 46260 | C60: 145 | D60: 240 | E60: 510 | G60: 895 | H60: =IF(ABS(G60-(SUM(C60:E60)-F60))<0.005,"OK","Check") -> OK
A61: August | B61: 46261 | C61: 0 | D61: 0 | G61: 0 | H61: =IF(ABS(G61-(SUM(C61:E61)-F61))<0.005,"OK","Check") -> OK
A62: August | B62: 46262 | C62: 0 | E62: 700 | G62: 700 | H62: =IF(ABS(G62-(SUM(C62:E62)-F62))<0.005,"OK","Check") -> OK
A63: August | B63: 46263 | C63: 157 | D63: 0 | E63: 600 | G63: 757 | H63: =IF(ABS(G63-(SUM(C63:E63)-F63))<0.005,"OK","Check") -> OK
A64: August | B64: 46264 | C64: 167 | D64: 0 | E64: 0 | G64: 167 | H64: =IF(ABS(G64-(SUM(C64:E64)-F64))<0.005,"OK","Check") -> OK
A65: August | B65: 46265 | C65: 0 | G65: 0 | H65: =IF(ABS(G65-(SUM(C65:E65)-F65))<0.005,"OK","Check") -> OK
A67: Source Totals | C67: =SUM(C5:C65) -> 7367 | D67: =SUM(D5:D65) -> 8513 | E67: =SUM(E5:E65) -> 16869 | F67: =SUM(F5:F65) -> 0 | G67: =SUM(G5:G65) -> 32749 | H67: =IF(COUNTIF(H5:H65,"Check")=0,"OK","Check") -> OK

Sheet Expense Source
A1: M - Corrected Expense Source
A4: Expense ID | B4: Source Bill Key | C4: Source Invoice No. | D4: Date | E4: Month | F4: Activity Tags | G4: Activity Detail | H4: Source Category | I4: Expense Category | J4: Expense Type | K4: Supplier | L4: Description | M4: Amount USD | N4: Amount LBP | O4: Effective FX | P4: Source Sheet | Q4: Source Rows | R4: Review Flag | S4: Selected Flag | T4: Selected Bill Flag | U4: Profitability Flag
A5: 20260630-001 | B5: 20260630-001 | C5: 0 | D5: 46203 | E5: June 2026 | F5: Workshop | G5: Oui Oui Nursery Workshops | H5: Librairie | I5: Workshop & Decoration Supplies | J5: Decoration & Workshop Materials | K5: Librairie Mallah | L5: Divers | M5: 152.5 | N5: 0 | P5: 30- June | Q5: 4-7 | R5: Outside July period | S5: 0 | T5: 0 | U5: =IF(AND(OR('Daily Profitability'!$E$3="All",ISNUMBER(SEARCH('Daily Profitability'!$E$3,F5))),OR('Daily Profitability'!$H$3="All",I5='Daily Profitability'!$H$3),OR('Daily Profitability'!$K$3="All",J5='Daily Profitability'!$K$3),OR('Daily Profitability'!$N$3="All",K5='Daily Profitability'!$N$3)),1,0) -> 0
A6: 20260630-002 | B6: 20260630-002 | C6: Unrecorded | D6: 46203 | E6: June 2026 | F6: Workshop | G6: Oui Oui Nursery Workshops | H6: Office Expenses | I6: Utilities & Office | J6: Maintenance | K6: Unspecified | L6: Moteur June | M6: 295 | N6: 0 | P6: 30- June | Q6: 10 | R6: Supplier not recorded; outside July period | S6: 0 | T6: 0 | U6: =IF(AND(OR('Daily Profitability'!$E$3="All",ISNUMBER(SEARCH('Daily Profitability'!$E$3,F6))),OR('Daily Profitability'!$H$3="All",I6='Daily Profitability'!$H$3),OR('Daily Profitability'!$K$3="All",J6='Daily Profitability'!$K$3),OR('Daily Profitability'!$N$3="All",K6='Daily Profitability'!$N$3)),1,0) -> 0
A7: 20260704-001 | B7: 20260704-001 | C7: Unrecorded | D7: 46207 | E7: July 2026 | F7: Birthday | G7: Birthday & Burger Workshops Barbecue | H7: Garbage | I7: Cleaning & Waste | J7: Waste Removal | K7: Imaco | L7: Description not recorded | M7: 30 | N7: 0 | P7: 4- July | Q7: 4 | R7: OK | S7: 0 | T7: 0 | U7: =IF(AND(OR('Daily Profitability'!$E$3="All",ISNUMBER(SEARCH('Daily Profitability'!$E$3,F7))),OR('Daily Profitability'!$H$3="All",I7='Daily Profitability'!$H$3),OR('Daily Profitability'!$K$3="All",J7='Daily Profitability'!$K$3),OR('Daily Profitability'!$N$3="All",K7='Daily Profitability'!$N$3)),1,0) -> 0
A8: 20260704-002 | B8: 20260704-002 | C8: Unrecorded | D8: 46207 | E8: July 2026 | F8: Birthday | G8: Birthday & Burger Workshops Barbecue | H8: Kitchen | I8: Food & Beverage | J8: Food & Beverage | K8: Forn Zakhia | L8: Manakich | M8: 5.7303371 | N8: 510000 | O8: 89000 | P8: 4- July | Q8: 6 | R8: OK | S8: 0 | T8: 0 | U8: =IF(AND(OR('Daily Profitability'!$E$3="All",ISNUMBER(SEARCH('Daily Profitability'!$E$3,F8))),OR('Daily Profitability'!$H$3="All",I8='Daily Profitability'!$H$3),OR('Daily Profitability'!$K$3="All",J8='Daily Profitability'!$K$3),OR('Daily Profitability'!$N$3="All",K8='Daily Profitability'!$N$3)),1,0) -> 1
A9: 20260704-003 | B9: 20260704-003 | C9: 0 | D9: 46207 | E9: July 2026 | F9: Birthday | G9: Birthday & Burger Workshops Barbecue | H9: Kitchen | I9: Food & Beverage | J9: Food & Beverage | K9: Le Marche Selectif | L9: F&V, Ice,Mozarella,Sugar | M9: 100.9 | N9: 0 | P9: 4- July | Q9: 7 | R9: OK | S9: 0 | T9: 0 | U9: =IF(AND(OR('Daily Profitability'!$E$3="All",ISNUMBER(SEARCH('Daily Profitability'!$E$3,F9))),OR('Daily Profitability'!$H$3="All",I9='Daily Profitability'!$H$3),OR('Daily Profitability'!$K$3="All",J9='Daily Profitability'!$K$3),OR('Daily Profitability'!$N$3="All",K9='Daily Profitability'!$N$3)),1,0) -> 1
A10: 20260704-004 | B10: 20260704-004 | C10: Unrecorded | D10: 46207 | E10: July 2026 | F10: Birthday | G10: Birthday & Burger Workshops Barbecue | H10: Office Expenses | I10: Utilities & Office | J10: Water | K10: Toni Tohme Station | L10: Water Citern | M10: 80 | N10: 0 | P10: 4- July | Q10: 9 | R10: OK | S10: 0 | T10: 0 | U10: =IF(AND(OR('Daily Profitability'!$E$3="All",ISNUMBER(SEARCH('Daily Profitability'!$E$3,F10))),OR('Daily Profitability'!$H$3="All",I10='Daily Profitability'!$H$3),OR('Daily Profitability'!$K$3="All",J10='Daily Profitability'!$K$3),OR('Daily Profitability'!$N$3="All",K10='Daily Profitability'!$N$3)),1,0) -> 0
A11: 20260704-005 | B11: 20260704-005 | C11: 0 | D11: 46207 | E11: July 2026 | F11: Birthday | G11: Birthday & Burger Workshops Barbecue | H11: Office Expenses | I11: Utilities & Office | J11: Electricity | K11: EDL | L11: Electricity | M11: 51.08 | N11: 0 | P11: 4- July | Q11: 10 | R11: OK | S11: 0 | T11: 0 | U11: =IF(AND(OR('Daily Profitability'!$E$3="All",ISNUMBER(SEARCH('Daily Profitability'!$E$3,F11))),OR('Daily Profitability'!$H$3="All",I11='Daily Profitability'!$H$3),OR('Daily Profitability'!$K$3="All",J11='Daily Profitability'!$K$3),OR('Daily Profitability'!$N$3="All",K11='Daily Profitability'!$N$3)),1,0) -> 0
A12: 20260704-006 | B12: 20260704-006 | C12: Unrecorded | D12: 46207 | E12: July 2026 | F12: Birthday | G12: Birthday & Burger Workshops Barbecue | H12: Workshops | I12: Workshop & Decoration Supplies | J12: Decoration & Workshop Materials | K12: Spinneys | L12: Divers | M12: 37.27 | N12: 0 | P12: 4- July | Q12: 12 | R12: OK | S12: 0 | T12: 0 | U12: =IF(AND(OR('Daily Profitability'!$E$3="All",ISNUMBER(SEARCH('Daily Profitability'!$E$3,F12))),OR('Daily Profitability'!$H$3="All",I12='Daily Profitability'!$H$3),OR('Daily Profitability'!$K$3="All",J12='Daily Profitability'!$K$3),OR('Daily Profitability'!$N$3="All",K12='Daily Profitability'!$N$3)),1,0) -> 0
A13: 20260704-007 | B13: 20260704-007 | C13: 0 | D13: 46207 | E13: July 2026 | F13: Birthday | G13: Birthday & Burger Workshops Barbecue | H13: Workshops | I13: Workshop & Decoration Supplies | J13: Decoration & Workshop Materials | K13: Event Megastore | L13: Description not recorded | M13: 32.31 | N13: 0 | P13: 4- July | Q13: 13 | R13: OK | S13: 0 | T13: 0 | U13: =IF(AND(OR('Daily Profitability'!$E$3="All",ISNUMBER(SEARCH('Daily Profitability'!$E$3,F13))),OR('Daily Profitability'!$H$3="All",I13='Daily Profitability'!$H$3),OR('Daily Profitability'!$K$3="All",J13='Daily Profitability'!$K$3),OR('Daily Profitability'!$N$3="All",K13='Daily Profitability'!$N$3)),1,0) -> 0
A14: 20260705-001 | B14: 20260705-001 | C14: 0 | D14: 46208 | E14: July 2026 | F14: Birthday | G14: Birthday | H14: Kitchen | I14: Food & Beverage | J14: Food & Beverage | K14: Le Marche Selectif | L14: Fruits & Vegetables; Fahem Colomby; Water Rim Box of 2 litre | M14: 41.3 | N14: 0 | P14: 5-July | Q14: 3-5 | R14: OK | S14: 0 | T14: 0 | U14: =IF(AND(OR('Daily Profitability'!$E$3="All",ISNUMBER(SEARCH('Daily Profitability'!$E$3,F14))),OR('Daily Profitability'!$H$3="All",I14='Daily Profitability'!$H$3),OR('Daily Profitability'!$K$3="All",J14='Daily Profitability'!$K$3),OR('Daily Profitability'!$N$3="All",K14='Daily Profitability'!$N$3)),1,0) -> 1
A15: 20260705-002 | B15: 20260705-002 | C15: 0 | D15: 46208 | E15: July 2026 | F15: Birthday | G15: Birthday | H15: Kitchen | I15: Food & Beverage | J15: Food & Beverage | K15: Storium | L15: Balkis | M15: 28.79 | N15: 0 | P15: 5-July | Q15: 6 | R15: OK | S15: 0 | T15: 0 | U15: =IF(AND(OR('Daily Profitability'!$E$3="All",ISNUMBER(SEARCH('Daily Profitability'!$E$3,F15))),OR('Daily Profitability'!$H$3="All",I15='Daily Profitability'!$H$3),OR('Daily Profitability'!$K$3="All",J15='Daily Profitability'!$K$3),OR('Daily Profitability'!$N$3="All",K15='Daily Profitability'!$N$3)),1,0) -> 1
A16: 20260705-003 | B16: 20260705-003 | C16: 0 | D16: 46208 | E16: July 2026 | F16: Birthday | G16: Birthday | H16: Kitchen | I16: Food & Beverage | J16: Food & Beverage | K16: Le Marche Selectif | L16: Ice, F&v Vinigar, Olive Black, cheese,Chicken Breast, Fa7em Mozarella | M16: 177.87 | N16: 0 | P16: 5-July | Q16: 7 | R16: OK | S16: 0 | T16: 0 | U16: =IF(AND(OR('Daily Profitability'!$E$3="All",ISNUMBER(SEARCH('Daily Profitability'!$E$3,F16))),OR('Daily Profitability'!$H$3="All",I16='Daily Profitability'!$H$3),OR('Daily Profitability'!$K$3="All",J16='Daily Profitability'!$K$3),OR('Daily Profitability'!$N$3="All",K16='Daily Profitability'!$N$3)),1,0) -> 1
A17: 20260705-004 | B17: 20260705-004 | C17: 0 | D17: 46208 | E17: July 2026 | F17: Birthday | G17: Birthday | H17: Kitchen | I17: Food & Beverage | J17: Food & Beverage | K17: Spinneys | L17: Brasilian Beef & Prunell; Beer,Milk, Wipes, Cacao | M17: 199.47 | N17: 0 | P17: 5-July | Q17: 8-9 | R17: OK | S17: 0 | T17: 0 | U17: =IF(AND(OR('Daily Profitability'!$E$3="All",ISNUMBER(SEARCH('Daily Profitability'!$E$3,F17))),OR('Daily Profitability'!$H$3="All",I17='Daily Profitability'!$H$3),OR('Daily Profitability'!$K$3="All",J17='Daily Profitability'!$K$3),OR('Daily Profitability'!$N$3="All",K17='Daily Profitability'!$N$3)),1,0) -> 1
A18: 20260705-005 | B18: 20260705-005 | C18: 0 | D18: 46208 | E18: July 2026 | F18: Birthday | G18: Birthday | H18: Kitchen | I18: Food & Beverage | J18: Food & Beverage | K18: Karam Bake | L18: Description not recorded | M18: 63.28 | N18: 0 | P18: 5-July | Q18: 10 | R18: OK | S18: 0 | T18: 0 | U18: =IF(AND(OR('Daily Profitability'!$E$3="All",ISNUMBER(SEARCH('Daily Profitability'!$E$3,F18))),OR('Daily Profitability'!$H$3="All",I18='Daily Profitability'!$H$3),OR('Daily Profitability'!$K$3="All",J18='Daily Profitability'!$K$3),OR('Daily Profitability'!$N$3="All",K18='Daily Profitability'!$N$3)),1,0) -> 1
A19: 20260708-001 | B19: 20260708-001 | C19: Unrecorded | D19: 46211 | E19: July 2026 | F19: Birthday | G19: Birthday | H19: Office Expenses | I19: Utilities & Office | J19: Maintenance | K19: Ets Melhem Yamine & Sons | L19: Industrial Walls | M19: 160 | N19: 0 | P19: 8-July | Q19: 3 | R19: OK | S19: 0 | T19: 0 | U19: =IF(AND(OR('Daily Profitability'!$E$3="All",ISNUMBER(SEARCH('Daily Profitability'!$E$3,F19))),OR('Daily Profitability'!$H$3="All",I19='Daily Profitability'!$H$3),OR('Daily Profitability'!$K$3="All",J19='Daily Profitability'!$K$3),OR('Daily Profitability'!$N$3="All",K19='Daily Profitability'!$N$3)),1,0) -> 0
A20: 20260708-002 | B20: 20260708-002 | C20: Unrecorded | D20: 46211 | E20: July 2026 | F20: Birthday | G20: Birthday | H20: Workshops | I20: Workshop & Decoration Supplies | J20: Decoration & Workshop Materials | K20: Librairie Mallah | L20: Divers | M20: 18 | N20: 0 | P20: 8-July | Q20: 5 | R20: OK | S20: 0 | T20: 0 | U20: =IF(AND(OR('Daily Profitability'!$E$3="All",ISNUMBER(SEARCH('Daily Profitability'!$E$3,F20))),OR('Daily Profitability'!$H$3="All",I20='Daily Profitability'!$H$3),OR('Daily Profitability'!$K$3="All",J20='Daily Profitability'!$K$3),OR('Daily Profitability'!$N$3="All",K20='Daily Profitability'!$N$3)),1,0) -> 0
... A43: 20260712-003 | B43: 20260712-003 | C43: 0 | D43: 46215 | E43: July 2026 | F43: Unspecified | G43: No activity label recorded | H43: Kitchen | I43: Food & Beverage | J43: Food & Beverage | K43: Storium | L43: Fresh Juice Balkis | M43: 22.49 | N43: 0 | P43: July-12 | Q43: 5 | R43: OK | S43: 0 | T43: 0 | U43: =IF(AND(OR('Daily Profitability'!$E$3="All",ISNUMBER(SEARCH('Daily Profitability'!$E$3,F43))),OR('Daily Profitability'!$H$3="All",I43='Daily Profitability'!$H$3),OR('Daily Profitability'!$K$3="All",J43='Daily Profitability'!$K$3),OR('Daily Profitability'!$N$3="All",K43='Daily Profitability'!$N$3)),1,0) -> 1
A44: 20260712-004 | B44: 20260712-004 | C44: 0 | D44: 46215 | E44: July 2026 | F44: Unspecified | G44: No activity label recorded | H44: Kitchen | I44: Food & Beverage | J44: Food & Beverage | K44: Le Marche Selectif | L44: FRuit& Vege; Rim Water; Cold Ice; Labneh Khoury; tea; Persil; Bread White; Javel; Laban; Mozarella Wraped | M44: 84.076404 | N44: 7482800 | O44: 89000 | P44: July-12 | Q44: 7-16 | R44: OK | S44: 0 | T44: 0 | U44: =IF(AND(OR('Daily Profitability'!$E$3="All",ISNUMBER(SEARCH('Daily Profitability'!$E$3,F44))),OR('Daily Profitability'!$H$3="All",I44='Daily Profitability'!$H$3),OR('Daily Profitability'!$K$3="All",J44='Daily Profitability'!$K$3),OR('Daily Profitability'!$N$3="All",K44='Daily Profitability'!$N$3)),1,0) -> 1
A45: 20260712-005 | B45: 20260712-005 | C45: 0 | D45: 46215 | E45: July 2026 | F45: Unspecified | G45: No activity label recorded | H45: Kitchen | I45: Food & Beverage | J45: Food & Beverage | K45: Storium | L45: Cotton Wipes,Balkis Penne,Flowe | M45: 56.63 | N45: 0 | P45: July-12 | Q45: 17 | R45: OK | S45: 0 | T45: 0 | U45: =IF(AND(OR('Daily Profitability'!$E$3="All",ISNUMBER(SEARCH('Daily Profitability'!$E$3,F45))),OR('Daily Profitability'!$H$3="All",I45='Daily Profitability'!$H$3),OR('Daily Profitability'!$K$3="All",J45='Daily Profitability'!$K$3),OR('Daily Profitability'!$N$3="All",K45='Daily Profitability'!$N$3)),1,0) -> 1
A46: 20260712-006 | B46: 20260712-006 | C46: 0 | D46: 46215 | E46: July 2026 | F46: Unspecified | G46: No activity label recorded | H46: Workshops | I46: Workshop & Decoration Supplies | J46: Decoration & Workshop Materials | K46: Event Megastore | L46: Papier Crepon | M46: 5.1573034 | N46: 459000 | O46: 89000 | P46: July-12 | Q46: 25-26 | R46: OK | S46: 0 | T46: 0 | U46: =IF(AND(OR('Daily Profitability'!$E$3="All",ISNUMBER(SEARCH('Daily Profitability'!$E$3,F46))),OR('Daily Profitability'!$H$3="All",I46='Daily Profitability'!$H$3),OR('Daily Profitability'!$K$3="All",J46='Daily Profitability'!$K$3),OR('Daily Profitability'!$N$3="All",K46='Daily Profitability'!$N$3)),1,0) -> 0
A47: 20260712-007 | B47: 20260712-007 | C47: 0 | D47: 46215 | E47: July 2026 | F47: Unspecified | G47: No activity label recorded | H47: Workshops | I47: Workshop & Decoration Supplies | J47: Decoration & Workshop Materials | K47: Fairco International | L47: Wood Board | M47: 83.36 | N47: 0 | P47: July-12 | Q47: 30 | R47: OK | S47: 0 | T47: 0 | U47: =IF(AND(OR('Daily Profitability'!$E$3="All",ISNUMBER(SEARCH('Daily Profitability'!$E$3,F47))),OR('Daily Profitability'!$H$3="All",I47='Daily Profitability'!$H$3),OR('Daily Profitability'!$K$3="All",J47='Daily Profitability'!$K$3),OR('Daily Profitability'!$N$3="All",K47='Daily Profitability'!$N$3)),1,0) -> 0
A48: 20260717-001 | B48: 20260717-001 | C48: Unrecorded | D48: 46220 | E48: July 2026 | F48: Birthday | G48: Birthday | H48: Kitchen | I48: Food & Beverage | J48: Food & Beverage | K48: Karam Bake | L48: Mou3ajanet | M48: 51.33 | N48: 0 | P48: 17-July | Q48: 3 | R48: OK | S48: 0 | T48: 0 | U48: =IF(AND(OR('Daily Profitability'!$E$3="All",ISNUMBER(SEARCH('Daily Profitability'!$E$3,F48))),OR('Daily Profitability'!$H$3="All",I48='Daily Profitability'!$H$3),OR('Daily Profitability'!$K$3="All",J48='Daily Profitability'!$K$3),OR('Daily Profitability'!$N$3="All",K48='Daily Profitability'!$N$3)),1,0) -> 1
A49: 20260717-002 | B49: 20260717-002 | C49: 0 | D49: 46220 | E49: July 2026 | F49: Birthday | G49: Birthday | H49: Kitchen | I49: Food & Beverage | J49: Food & Beverage | K49: Spinneys | L49: Beirut Beer; Oui Oui Wipes; Rim Sparkling Water; Rim Sparkling Water Can; Domo Becarbonate sada; Domo Food Coloring; Sanita Classic; Souplex Powder; Sanita Zipper Bags; Quinoa; Vermicelle Pasta; Plein Soleil Tuna Oil; Sweet Corn; Pasta Fusilli; Extra Olive Oil; Adam Salt Fine; Origano spice; Mayonaise; Balsamic Vinegair; Ketchup Gallon 2 k; Tortillas; Devon Cheddar Chips; Croco Sticks; Croco Mix; Bjorg Choco Noir; Fruits & Vgtebales; Mozarella; President; Olive Slice; Aroma Pickles; Argal Pechuga; Ferrarini Padano | M49: 374.71 | N49: 27850538 | O49: 74325.58 | P49: 17-July | Q49: 5-36 | R49: OK | S49: 0 | T49: 0 | U49: =IF(AND(OR('Daily Profitability'!$E$3="All",ISNUMBER(SEARCH('Daily Profitability'!$E$3,F49))),OR('Daily Profitability'!$H$3="All",I49='Daily Profitability'!$H$3),OR('Daily Profitability'!$K$3="All",J49='Daily Profitability'!$K$3),OR('Daily Profitability'!$N$3="All",K49='Daily Profitability'!$N$3)),1,0) -> 1
A50: 20260717-003 | B50: 20260717-003 | C50: 0 | D50: 46220 | E50: July 2026 | F50: Birthday | G50: Birthday | H50: Workshops | I50: Workshop & Decoration Supplies | J50: Decoration & Workshop Materials | K50: Librairie Mallah | L50: Clay; Printing LAser,Clay,Peinture | M50: 92 | N50: 0 | P50: 17-July | Q50: 38-39 | R50: OK | S50: 0 | T50: 0 | U50: =IF(AND(OR('Daily Profitability'!$E$3="All",ISNUMBER(SEARCH('Daily Profitability'!$E$3,F50))),OR('Daily Profitability'!$H$3="All",I50='Daily Profitability'!$H$3),OR('Daily Profitability'!$K$3="All",J50='Daily Profitability'!$K$3),OR('Daily Profitability'!$N$3="All",K50='Daily Profitability'!$N$3)),1,0) -> 0
A51: 20260717-004 | B51: 20260717-004 | C51: 0 | D51: 46220 | E51: July 2026 | F51: Birthday | G51: Birthday | H51: Kitchen | I51: Food & Beverage | J51: Food & Beverage | K51: La Valeur Market | L51: Bread; Block Chocolate; Divers; Lurpak; Dark Chocolat; Coffe; Raisin Dark; Onion; Green Paper; Sun Flower oil; Walnuts; Mozarella Cheese; Pomi Tomato; Khoury Laban | M51: 101.28 | N51: 9100231 | O51: 89852.202 | P51: 17-July | Q51: 41-55 | R51: OK | S51: 0 | T51: 0 | U51: =IF(AND(OR('Daily Profitability'!$E$3="All",ISNUMBER(SEARCH('Daily Profitability'!$E$3,F51))),OR('Daily Profitability'!$H$3="All",I51='Daily Profitability'!$H$3),OR('Daily Profitability'!$K$3="All",J51='Daily Profitability'!$K$3),OR('Daily Profitability'!$N$3="All",K51='Daily Profitability'!$N$3)),1,0) -> 1
A52: 20260717-005 | B52: 20260717-005 | C52: Unrecorded | D52: 46220 | E52: July 2026 | F52: Birthday | G52: Birthday | H52: Office Expenses | I52: Disposables & Packaging | J52: Packaging & Disposables | K52: Disposable | L52: Froks.spoon, Meal Box, Juice Btl,Salad Boat, Plates Boat, Paper Boats, jars | M52: 134.75 | N52: 0 | P52: 17-July | Q52: 57 | R52: OK | S52: 0 | T52: 0 | U52: =IF(AND(OR('Daily Profitability'!$E$3="All",ISNUMBER(SEARCH('Daily Profitability'!$E$3,F52))),OR('Daily Profitability'!$H$3="All",I52='Daily Profitability'!$H$3),OR('Daily Profitability'!$K$3="All",J52='Daily Profitability'!$K$3),OR('Daily Profitability'!$N$3="All",K52='Daily Profitability'!$N$3)),1,0) -> 0
A53: 20260717-006 | B53: 20260717-006 | C53: Unrecorded | D53: 46220 | E53: July 2026 | F53: Birthday | G53: Birthday | H53: Kitchen | I53: Food & Beverage | J53: Food & Beverage | K53: Le Marche Selectif | L53: Cold Ice, Water Gallon &Small btls, Fruits , veg,Olive Oil , Sanita | M53: 185.9 | N53: 0 | P53: 17-July | Q53: 59 | R53: OK | S53: 0 | T53: 0 | U53: =IF(AND(OR('Daily Profitability'!$E$3="All",ISNUMBER(SEARCH('Daily Profitability'!$E$3,F53))),OR('Daily Profitability'!$H$3="All",I53='Daily Profitability'!$H$3),OR('Daily Profitability'!$K$3="All",J53='Daily Profitability'!$K$3),OR('Daily Profitability'!$N$3="All",K53='Daily Profitability'!$N$3)),1,0) -> 1
A54: 20260717-007 | B54: 20260717-007 | C54: 0 | D54: 46220 | E54: July 2026 | F54: Birthday | G54: Birthday | H54: Kitchen | I54: Food & Beverage | J54: Food & Beverage | K54: Boucherie Ziad | L54: Mafroume | M54: 19.09 | N54: 0 | P54: 17-July | Q54: 60 | R54: OK | S54: 0 | T54: 0 | U54: =IF(AND(OR('Daily Profitability'!$E$3="All",ISNUMBER(SEARCH('Daily Profitability'!$E$3,F54))),OR('Daily Profitability'!$H$3="All",I54='Daily Profitability'!$H$3),OR('Daily Profitability'!$K$3="All",J54='Daily Profitability'!$K$3),OR('Daily Profitability'!$N$3="All",K54='Daily Profitability'!$N$3)),1,0) -> 1
A55: 20260718-001 | B55: 20260718-001 | C55: 0 | D55: 46221 | E55: July 2026 | F55: Unspecified | G55: No activity label recorded | H55: Kitchen | I55: Food & Beverage | J55: Food & Beverage | K55: Spinneys | L55: Brasilian Beef; Local Beef Habra | M55: 51.219 | N55: 0 | P55: 18-july | Q55: 4-5 | R55: OK | S55: 0 | T55: 0 | U55: =IF(AND(OR('Daily Profitability'!$E$3="All",ISNUMBER(SEARCH('Daily Profitability'!$E$3,F55))),OR('Daily Profitability'!$H$3="All",I55='Daily Profitability'!$H$3),OR('Daily Profitability'!$K$3="All",J55='Daily Profitability'!$K$3),OR('Daily Profitability'!$N$3="All",K55='Daily Profitability'!$N$3)),1,0) -> 1
A56: 20260718-002 | B56: 20260718-002 | C56: 0 | D56: 46221 | E56: July 2026 | F56: Unspecified | G56: No activity label recorded | H56: Kitchen | I56: Food & Beverage | J56: Food & Beverage | K56: Spinneys | L56: Bakery | M56: 20.4 | N56: 0 | P56: 18-july | Q56: 7 | R56: OK | S56: 0 | T56: 0 | U56: =IF(AND(OR('Daily Profitability'!$E$3="All",ISNUMBER(SEARCH('Daily Profitability'!$E$3,F56))),OR('Daily Profitability'!$H$3="All",I56='Daily Profitability'!$H$3),OR('Daily Profitability'!$K$3="All",J56='Daily Profitability'!$K$3),OR('Daily Profitability'!$N$3="All",K56='Daily Profitability'!$N$3)),1,0) -> 1
A57: 20260718-003 | B57: 20260718-003 | C57: 0 | D57: 46221 | E57: July 2026 | F57: Unspecified | G57: No activity label recorded | H57: Kitchen | I57: Food & Beverage | J57: Food & Beverage | K57: Boucherie Ziad | L57: Burgers | M57: 37.09 | N57: 0 | P57: 18-july | Q57: 8 | R57: OK | S57: 0 | T57: 0 | U57: =IF(AND(OR('Daily Profitability'!$E$3="All",ISNUMBER(SEARCH('Daily Profitability'!$E$3,F57))),OR('Daily Profitability'!$H$3="All",I57='Daily Profitability'!$H$3),OR('Daily Profitability'!$K$3="All",J57='Daily Profitability'!$K$3),OR('Daily Profitability'!$N$3="All",K57='Daily Profitability'!$N$3)),1,0) -> 1
A58: 20260718-004 | B58: 20260718-004 | C58: 0 | D58: 46221 | E58: July 2026 | F58: Unspecified | G58: No activity label recorded | H58: Kitchen | I58: Food & Beverage | J58: Food & Beverage | K58: Le Marche Selectif | L58: Ice & Water | M58: 34.5 | N58: 0 | P58: 18-july | Q58: 9 | R58: OK | S58: 0 | T58: 0 | U58: =IF(AND(OR('Daily Profitability'!$E$3="All",ISNUMBER(SEARCH('Daily Profitability'!$E$3,F58))),OR('Daily Profitability'!$H$3="All",I58='Daily Profitability'!$H$3),OR('Daily Profitability'!$K$3="All",J58='Daily Profitability'!$K$3),OR('Daily Profitability'!$N$3="All",K58='Daily Profitability'!$N$3)),1,0) -> 1
A59: 20260718-005 | B59: 20260718-005 | C59: 0 | D59: 46221 | E59: July 2026 | F59: Unspecified | G59: No activity label recorded | H59: Kitchen | I59: Food & Beverage | J59: Food & Beverage | K59: Karam Bake | L59: Description not recorded | M59: 74.84 | N59: 0 | P59: 18-july | Q59: 10 | R59: OK | S59: 0 | T59: 0 | U59: =IF(AND(OR('Daily Profitability'!$E$3="All",ISNUMBER(SEARCH('Daily Profitability'!$E$3,F59))),OR('Daily Profitability'!$H$3="All",I59='Daily Profitability'!$H$3),OR('Daily Profitability'!$K$3="All",J59='Daily Profitability'!$K$3),OR('Daily Profitability'!$N$3="All",K59='Daily Profitability'!$N$3)),1,0) -> 1
A60: 20260719-001 | B60: 20260719-001 | C60: 0 | D60: 46222 | E60: July 2026 | F60: Birthday | G60: Birthday | H60: Kitchen | I60: Food & Beverage | J60: Food & Beverage | K60: Panino Bakery | L60: Muffin Cake; Mini Burgers | M60: 25.393258 | N60: 2260000 | O60: 89000 | P60: 19-July | Q60: 5-6 | R60: OK | S60: 0 | T60: 0 | U60: =IF(AND(OR('Daily Profitability'!$E$3="All",ISNUMBER(SEARCH('Daily Profitability'!$E$3,F60))),OR('Daily Profitability'!$H$3="All",I60='Daily Profitability'!$H$3),OR('Daily Profitability'!$K$3="All",J60='Daily Profitability'!$K$3),OR('Daily Profitability'!$N$3="All",K60='Daily Profitability'!$N$3)),1,0) -> 1
A61: 20260719-002 | B61: 20260719-002 | C61: 0 | D61: 46222 | E61: July 2026 | F61: Birthday | G61: Birthday | H61: Kitchen | I61: Food & Beverage | J61: Food & Beverage | K61: Boucherie Ziad | L61: Burgers; Delivery | M61: 37.573596 | N61: 3344050 | O61: 89000 | P61: 19-July | Q61: 7-8 | R61: OK | S61: 0 | T61: 0 | U61: =IF(AND(OR('Daily Profitability'!$E$3="All",ISNUMBER(SEARCH('Daily Profitability'!$E$3,F61))),OR('Daily Profitability'!$H$3="All",I61='Daily Profitability'!$H$3),OR('Daily Profitability'!$K$3="All",J61='Daily Profitability'!$K$3),OR('Daily Profitability'!$N$3="All",K61='Daily Profitability'!$N$3)),1,0) -> 1
A62: 20260719-003 | B62: 20260719-003 | C62: 0 | D62: 46222 | E62: July 2026 | F62: Birthday | G62: Birthday | H62: Kitchen | I62: Food & Beverage | J62: Food & Beverage | K62: Le Marche Selectif | L62: Divers; F&V; water Rim; Cold Ice | M62: 61.528573 | N62: 5476043 | O62: 89000 | P62: 19-July | Q62: 9-12 | R62: OK | S62: 0 | T62: 0 | U62: =IF(AND(OR('Daily Profitability'!$E$3="All",ISNUMBER(SEARCH('Daily Profitability'!$E$3,F62))),OR('Daily Profitability'!$H$3="All",I62='Daily Profitability'!$H$3),OR('Daily Profitability'!$K$3="All",J62='Daily Profitability'!$K$3),OR('Daily Profitability'!$N$3="All",K62='Daily Profitability'!$N$3)),1,0) -> 1
A63: 20260720-001 | B63: 20260720-001 | C63: 0 | D63: 46223 | E63: July 2026 | F63: Unspecified | G63: No activity label recorded | I63: Food & Beverage | J63: Food & Beverage | K63: Karam Bake | L63: Description not recorded | M63: 45.39 | N63: 0 | P63: 20-July | Q63: 5 | R63: Source category not recorded; classified from supplier | S63: 0 | T63: 0 | U63: =IF(AND(OR('Daily Profitability'!$E$3="All",ISNUMBER(SEARCH('Daily Profitability'!$E$3,F63))),OR('Daily Profitability'!$H$3="All",I63='Daily Profitability'!$H$3),OR('Daily Profitability'!$K$3="All",J63='Daily Profitability'!$K$3),OR('Daily Profitability'!$N$3="All",K63='Daily Profitability'!$N$3)),1,0) -> 1
A64: 20260721-001 | B64: 20260721-001 | C64: 0 | D64: 46224 | E64: July 2026 | F64: Nursery Visit | G64: Rabieh Nursery Visit | H64: Office Expenses | I64: Cleaning & Waste | J64: Cleaning & Sanitation | K64: Le Marche Selectif | L64: Spray 7acharat; Spontex & Ranbow | M64: 5.11 | N64: 0 | P64: 21-July | Q64: 4-5 | R64: OK | S64: 0 | T64: 0 | U64: =IF(AND(OR('Daily Profitability'!$E$3="All",ISNUMBER(SEARCH('Daily Profitability'!$E$3,F64))),OR('Daily Profitability'!$H$3="All",I64='Daily Profitability'!$H$3),OR('Daily Profitability'!$K$3="All",J64='Daily Profitability'!$K$3),OR('Daily Profitability'!$N$3="All",K64='Daily Profitability'!$N$3)),1,0) -> 0
A65: 20260721-002 | B65: 20260721-002 | C65: Unrecorded | D65: 46224 | E65: July 2026 | F65: Nursery Visit | G65: Rabieh Nursery Visit | H65: Workshops | I65: Workshop & Decoration Supplies | J65: Decoration & Workshop Materials | K65: Librairie Mallah | L65: Canson | M65: 29.88 | N65: 0 | P65: 21-July | Q65: 6 | R65: OK | S65: 0 | T65: 0 | U65: =IF(AND(OR('Daily Profitability'!$E$3="All",ISNUMBER(SEARCH('Daily Profitability'!$E$3,F65))),OR('Daily Profitability'!$H$3="All",I65='Daily Profitability'!$H$3),OR('Daily Profitability'!$K$3="All",J65='Daily Profitability'!$K$3),OR('Daily Profitability'!$N$3="All",K65='Daily Profitability'!$N$3)),1,0) -> 0
A66: 20260721-003 | B66: 20260721-003 | C66: 0 | D66: 46224 | E66: July 2026 | F66: Nursery Visit | G66: Rabieh Nursery Visit | H66: Workshops | I66: Workshop & Decoration Supplies | J66: Decoration & Workshop Materials | K66: Event Megastore | L66: Strow, Stone, Farm Animal... | M66: 38.7 | N66: 0 | P66: 21-July | Q66: 7 | R66: OK | S66: 0 | T66: 0 | U66: =IF(AND(OR('Daily Profitability'!$E$3="All",ISNUMBER(SEARCH('Daily Profitability'!$E$3,F66))),OR('Daily Profitability'!$H$3="All",I66='Daily Profitability'!$H$3),OR('Daily Profitability'!$K$3="All",J66='Daily Profitability'!$K$3),OR('Daily Profitability'!$N$3="All",K66='Daily Profitability'!$N$3)),1,0) -> 0
A67: 20260721-004 | B67: 20260721-004 | C67: 0 | D67: 46224 | E67: July 2026 | F67: Nursery Visit | G67: Rabieh Nursery Visit | H67: Workshops | I67: Workshop & Decoration Supplies | J67: Decoration & Workshop Materials | K67: Event Megastore | L67: Bubble Game; Scotch; Glue; Garbage Bags; Glue Big; Washable Acrylic; Scissor; Description not recorded | M67: 27.617978 | N67: 2458000 | O67: 89000 | P67: 21-July | Q67: 8-15 | R67: OK | S67: 0 | T67: 0 | U67: =IF(AND(OR('Daily Profitability'!$E$3="All",ISNUMBER(SEARCH('Daily Profitability'!$E$3,F67))),OR('Daily Profitability'!$H$3="All",I67='Daily Profitability'!$H$3),OR('Daily Profitability'!$K$3="All",J67='Daily Profitability'!$K$3),OR('Daily Profitability'!$N$3="All",K67='Daily Profitability'!$N$3)),1,0) -> 0
A68: 20260721-005 | B68: 20260721-005 | C68: Unrecorded | D68: 46224 | E68: July 2026 | F68: Nursery Visit | G68: Rabieh Nursery Visit | H68: Garden | I68: Garden & Grounds | J68: Garden & Landscaping | K68: Ramel Mgharbal, Trabeh | L68: Ramel Mgharbal,Trabeh | M68: 113 | N68: 0 | P68: 21-July | Q68: 16 | R68: OK | S68: 0 | T68: 0 | U68: =IF(AND(OR('Daily Profitability'!$E$3="All",ISNUMBER(SEARCH('Daily Profitability'!$E$3,F68))),OR('Daily Profitability'!$H$3="All",I68='Daily Profitability'!$H$3),OR('Daily Profitability'!$K$3="All",J68='Daily Profitability'!$K$3),OR('Daily Profitability'!$N$3="All",K68='Daily Profitability'!$N$3)),1,0) -> 0
A69: 20260721-006 | B69: 20260721-006 | C69: 0 | D69: 46224 | E69: July 2026 | F69: Nursery Visit | G69: Rabieh Nursery Visit | H69: Garden | I69: Garden & Grounds | J69: Garden & Landscaping | K69: Asab & Tools For Garden | L69: Asab &Tools For Garden | M69: 139 | N69: 0 | P69: 21-July | Q69: 17 | R69: OK | S69: 0 | T69: 0 | U69: =IF(AND(OR('Daily Profitability'!$E$3="All",ISNUMBER(SEARCH('Daily Profitability'!$E$3,F69))),OR('Daily Profitability'!$H$3="All",I69='Daily Profitability'!$H$3),OR('Daily Profitability'!$K$3="All",J69='Daily Profitability'!$K$3),OR('Daily Profitability'!$N$3="All",K69='Daily Profitability'!$N$3)),1,0) -> 0
A70: 20260721-007 | B70: 20260721-007 | C70: Unrecorded | D70: 46224 | E70: July 2026 | F70: Nursery Visit | G70: Rabieh Nursery Visit | H70: Disposables | I70: Disposables & Packaging | J70: Packaging & Disposables | K70: Unspecified | L70: Bottles, Spoon, Fork, Salad Boat, Meal Box, Pasta Boat, Craft Boat | M70: 86 | N70: 0 | P70: 21-July | Q70: 20 | R70: Supplier not recorded | S70: 0 | T70: 0 | U70: =IF(AND(OR('Daily Profitability'!$E$3="All",ISNUMBER(SEARCH('Daily Profitability'!$E$3,F70))),OR('Daily Profitability'!$H$3="All",I70='Daily Profitability'!$H$3),OR('Daily Profitability'!$K$3="All",J70='Daily Profitability'!$K$3),OR('Daily Profitability'!$N$3="All",K70='Daily Profitability'!$N$3)),1,0) -> 0
A71: 20260723-001 | B71: 20260723-001 | C71: Unrecorded | D71: 46226 | E71: July 2026 | F71: Unspecified | G71: No activity label recorded | H71: Kitchen | I71: Food & Beverage | J71: Food & Beverage | K71: Boucherie Ziad | L71: Mafroume Burger Kebbeh | M71: 93.51 | N71: 0 | P71: 23-July | Q71: 6 | R71: OK | S71: 0 | T71: 0 | U71: =IF(AND(OR('Daily Profitability'!$E$3="All",ISNUMBER(SEARCH('Daily Profitability'!$E$3,F71))),OR('Daily Profitability'!$H$3="All",I71='Daily Profitability'!$H$3),OR('Daily Profitability'!$K$3="All",J71='Daily Profitability'!$K$3),OR('Daily Profitability'!$N$3="All",K71='Daily Profitability'!$N$3)),1,0) -> 1
A72: 20260723-002 | B72: 20260723-002 | C72: Unrecorded | D72: 46226 | E72: July 2026 | F72: Unspecified | G72: No activity label recorded | H72: Office Tools | I72: Equipment & Tools | J72: Kitchen Equipment | K72: Jamil Rezk | L72: Kitchen Tools | M72: 162 | N72: 0 | P72: 23-July | Q72: 8 | R72: OK | S72: 0 | T72: 0 | U72: =IF(AND(OR('Daily Profitability'!$E$3="All",ISNUMBER(SEARCH('Daily Profitability'!$E$3,F72))),OR('Daily Profitability'!$H$3="All",I72='Daily Profitability'!$H$3),OR('Daily Profitability'!$K$3="All",J72='Daily Profitability'!$K$3),OR('Daily Profitability'!$N$3="All",K72='Daily Profitability'!$N$3)),1,0) -> 0
A73: 20260724-001 | B73: 20260724-001 | C73: Unrecorded | D73: 46227 | E73: July 2026 | F73: Unspecified | G73: No activity label recorded | H73: Kitchen | I73: Food & Beverage | J73: Food & Beverage | K73: Panino Bakery | L73: Burgers | M73: 5.6179775 | N73: 500000 | O73: 89000 | P73: 24-July | Q73: 5 | R73: OK | S73: 0 | T73: 0 | U73: =IF(AND(OR('Daily Profitability'!$E$3="All",ISNUMBER(SEARCH('Daily Profitability'!$E$3,F73))),OR('Daily Profitability'!$H$3="All",I73='Daily Profitability'!$H$3),OR('Daily Profitability'!$K$3="All",J73='Daily Profitability'!$K$3),OR('Daily Profitability'!$N$3="All",K73='Daily Profitability'!$N$3)),1,0) -> 1
A74: 20260724-002 | B74: 20260724-002 | C74: 0 | D74: 46227 | E74: July 2026 | F74: Unspecified | G74: No activity label recorded | H74: Kitchen | I74: Food & Beverage | J74: Food & Beverage | K74: Lteif Market | L74: F&V | M74: 8.8764045 | N74: 790000 | O74: 89000 | P74: 24-July | Q74: 6 | R74: OK | S74: 0 | T74: 0 | U74: =IF(AND(OR('Daily Profitability'!$E$3="All",ISNUMBER(SEARCH('Daily Profitability'!$E$3,F74))),OR('Daily Profitability'!$H$3="All",I74='Daily Profitability'!$H$3),OR('Daily Profitability'!$K$3="All",J74='Daily Profitability'!$K$3),OR('Daily Profitability'!$N$3="All",K74='Daily Profitability'!$N$3)),1,0) -> 1
A75: 20260724-003 | B75: 20260724-003 | C75: 0 | D75: 46227 | E75: July 2026 | F75: Unspecified | G75: No activity label recorded | H75: Kitchen | I75: Food & Beverage | J75: Food & Beverage | K75: Le Marche Selectif | L75: F&V, Water, Ice Flour, Sparkling Water | M75: 195 | N75: 0 | P75: 24-July | Q75: 7 | R75: OK | S75: 0 | T75: 0 | U75: =IF(AND(OR('Daily Profitability'!$E$3="All",ISNUMBER(SEARCH('Daily Profitability'!$E$3,F75))),OR('Daily Profitability'!$H$3="All",I75='Daily Profitability'!$H$3),OR('Daily Profitability'!$K$3="All",J75='Daily Profitability'!$K$3),OR('Daily Profitability'!$N$3="All",K75='Daily Profitability'!$N$3)),1,0) -> 1
A76: 20260724-004 | B76: 20260724-004 | C76: 0 | D76: 46227 | E76: July 2026 | F76: Unspecified | G76: No activity label recorded | H76: Kitchen | I76: Food & Beverage | J76: Food & Beverage | K76: Boucherie Ziad | L76: Burger, Mafroume, kebbe | M76: 93.21 | N76: 0 | P76: 24-July | Q76: 8 | R76: OK | S76: 0 | T76: 0 | U76: =IF(AND(OR('Daily Profitability'!$E$3="All",ISNUMBER(SEARCH('Daily Profitability'!$E$3,F76))),OR('Daily Profitability'!$H$3="All",I76='Daily Profitability'!$H$3),OR('Daily Profitability'!$K$3="All",J76='Daily Profitability'!$K$3),OR('Daily Profitability'!$N$3="All",K76='Daily Profitability'!$N$3)),1,0) -> 1
A77: 20260724-005 | B77: 20260724-005 | C77: 0 | D77: 46227 | E77: July 2026 | F77: Unspecified | G77: No activity label recorded | H77: Kitchen | I77: Food & Beverage | J77: Food & Beverage | K77: Le Charcutier | L77: Balkis Orange Juice | M77: 46.23 | N77: 0 | P77: 24-July | Q77: 9 | R77: OK | S77: 0 | T77: 0 | U77: =IF(AND(OR('Daily Profitability'!$E$3="All",ISNUMBER(SEARCH('Daily Profitability'!$E$3,F77))),OR('Daily Profitability'!$H$3="All",I77='Daily Profitability'!$H$3),OR('Daily Profitability'!$K$3="All",J77='Daily Profitability'!$K$3),OR('Daily Profitability'!$N$3="All",K77='Daily Profitability'!$N$3)),1,0) -> 1
A78: 20260724-006 | B78: 20260724-006 | C78: 0 | D78: 46227 | E78: July 2026 | F78: Unspecified | G78: No activity label recorded | H78: Workshops | I78: Workshop & Decoration Supplies | J78: Decoration & Workshop Materials | K78: Librairie Mallah | L78: Peinture 1000 ml; Peinture 500ml; Canson A4 Red; pele; Feutre | M78: 47.4 | N78: 0 | P78: 24-July | Q78: 11-15 | R78: OK | S78: 0 | T78: 0 | U78: =IF(AND(OR('Daily Profitability'!$E$3="All",ISNUMBER(SEARCH('Daily Profitability'!$E$3,F78))),OR('Daily Profitability'!$H$3="All",I78='Daily Profitability'!$H$3),OR('Daily Profitability'!$K$3="All",J78='Daily Profitability'!$K$3),OR('Daily Profitability'!$N$3="All",K78='Daily Profitability'!$N$3)),1,0) -> 0
A79: 20260724-007 | B79: 20260724-007 | C79: 0 | D79: 46227 | E79: July 2026 | F79: Unspecified | G79: No activity label recorded | H79: Workshops | I79: Workshop & Decoration Supplies | J79: Decoration & Workshop Materials | K79: Event Megastore | L79: Divers | M79: 18 | N79: 0 | P79: 24-July | Q79: 17 | R79: OK | S79: 0 | T79: 0 | U79: =IF(AND(OR('Daily Profitability'!$E$3="All",ISNUMBER(SEARCH('Daily Profitability'!$E$3,F79))),OR('Daily Profitability'!$H$3="All",I79='Daily Profitability'!$H$3),OR('Daily Profitability'!$K$3="All",J79='Daily Profitability'!$K$3),OR('Daily Profitability'!$N$3="All",K79='Daily Profitability'!$N$3)),1,0) -> 0
A80: 20260725-001 | B80: 20260725-001 | C80: Unrecorded | D80: 46228 | E80: July 2026 | F80: Unspecified | G80: No activity label recorded | H80: Kitchen | I80: Food & Beverage | J80: Food & Beverage | K80: Boucherie Ziad | L80: Mafrome, kebbe, Burgers | M80: 39 | N80: 0 | P80: 25-July | Q80: 3 | R80: OK | S80: 0 | T80: 0 | U80: =IF(AND(OR('Daily Profitability'!$E$3="All",ISNUMBER(SEARCH('Daily Profitability'!$E$3,F80))),OR('Daily Profitability'!$H$3="All",I80='Daily Profitability'!$H$3),OR('Daily Profitability'!$K$3="All",J80='Daily Profitability'!$K$3),OR('Daily Profitability'!$N$3="All",K80='Daily Profitability'!$N$3)),1,0) -> 1
A81: 20260725-002 | B81: 20260725-002 | C81: 0 | D81: 46228 | E81: July 2026 | F81: Birthday | G81: Inferred from source description: Food & B For Birthday | H81: Kitchen | I81: Food & Beverage | J81: Food & Beverage | K81: Spinneys | L81: Food & B For Birthday | M81: 160 | N81: 0 | P81: 25-July | Q81: 4 | R81: Activity inferred from description | S81: 0 | T81: 0 | U81: =IF(AND(OR('Daily Profitability'!$E$3="All",ISNUMBER(SEARCH('Daily Profitability'!$E$3,F81))),OR('Daily Profitability'!$H$3="All",I81='Daily Profitability'!$H$3),OR('Daily Profitability'!$K$3="All",J81='Daily Profitability'!$K$3),OR('Daily Profitability'!$N$3="All",K81='Daily Profitability'!$N$3)),1,0) -> 1
A82: 20260725-003 | B82: 20260725-003 | C82: 0 | D82: 46228 | E82: July 2026 | F82: Unspecified | G82: No activity label recorded | H82: Kitchen | I82: Food & Beverage | J82: Food & Beverage | K82: Panino Bakery | L82: Mini Burgers; Bassal | M82: 41.949438 | N82: 3600000 | O82: 85817.597 | P82: 25-July | Q82: 5-7 | R82: OK | S82: 0 | T82: 0 | U82: =IF(AND(OR('Daily Profitability'!$E$3="All",ISNUMBER(SEARCH('Daily Profitability'!$E$3,F82))),OR('Daily Profitability'!$H$3="All",I82='Daily Profitability'!$H$3),OR('Daily Profitability'!$K$3="All",J82='Daily Profitability'!$K$3),OR('Daily Profitability'!$N$3="All",K82='Daily Profitability'!$N$3)),1,0) -> 1
A83: 20260725-004 | B83: 20260725-004 | C83: 0 | D83: 46228 | E83: July 2026 | F83: Unspecified | G83: No activity label recorded | H83: Disposables | I83: Workshop & Decoration Supplies | J83: Decoration & Workshop Materials | K83: Fairco International | L83: Design Block Pad; Mozanit Board; Scissors; Ballons; Brush Set Pack of 6; Clay; Paper Color; Curves; Tapes; Silicon Mol Unicorn; Mazonite Board; Plastic Btl; Markers; Crepe Paper | M83: 120.44 | N83: 9369299.9 | O83: 77792.261 | P83: 25-July | Q83: 8-23 | R83: OK | S83: 0 | T83: 0 | U83: =IF(AND(OR('Daily Profitability'!$E$3="All",ISNUMBER(SEARCH('Daily Profitability'!$E$3,F83))),OR('Daily Profitability'!$H$3="All",I83='Daily Profitability'!$H$3),OR('Daily Profitability'!$K$3="All",J83='Daily Profitability'!$K$3),OR('Daily Profitability'!$N$3="All",K83='Daily Profitability'!$N$3)),1,0) -> 0
A84: 20260725-005 | B84: 20260725-005 | C84: Unrecorded | D84: 46228 | E84: July 2026 | F84: Unspecified | G84: No activity label recorded | H84: Office Expenses | I84: Utilities & Office | J84: Other / Office | K84: Luicci | L84: Divers | M84: 28 | N84: 0 | P84: 25-July | Q84: 25 | R84: OK | S84: 0 | T84: 0 | U84: =IF(AND(OR('Daily Profitability'!$E$3="All",ISNUMBER(SEARCH('Daily Profitability'!$E$3,F84))),OR('Daily Profitability'!$H$3="All",I84='Daily Profitability'!$H$3),OR('Daily Profitability'!$K$3="All",J84='Daily Profitability'!$K$3),OR('Daily Profitability'!$N$3="All",K84='Daily Profitability'!$N$3)),1,0) -> 0
A85: 20260725-006 | B85: 20260725-006 | C85: 0 | D85: 46228 | E85: July 2026 | F85: Unspecified | G85: No activity label recorded | I85: Food & Beverage | J85: Food & Beverage | K85: Karam Bake | L85: Description not recorded | M85: 110.94 | N85: 0 | P85: 25-July | Q85: 27 | R85: Source fields shifted; supplier recovered from item column | S85: 0 | T85: 0 | U85: =IF(AND(OR('Daily Profitability'!$E$3="All",ISNUMBER(SEARCH('Daily Profitability'!$E$3,F85))),OR('Daily Profitability'!$H$3="All",I85='Daily Profitability'!$H$3),OR('Daily Profitability'!$K$3="All",J85='Daily Profitability'!$K$3),OR('Daily Profitability'!$N$3="All",K85='Daily Profitability'!$N$3)),1,0) -> 1
A86: 20260727-001 | B86: 20260727-001 | C86: 0 | D86: 46230 | E86: July 2026 | F86: Unspecified | G86: No activity label recorded | H86: Workshop | I86: Workshop & Decoration Supplies | J86: Decoration & Workshop Materials | K86: Fairco International | L86: Wrapping paper; clay | M86: 25.96 | N86: 0 | P86: 27-July | Q86: 4-5 | R86: OK | S86: 0 | T86: 0 | U86: =IF(AND(OR('Daily Profitability'!$E$3="All",ISNUMBER(SEARCH('Daily Profitability'!$E$3,F86))),OR('Daily Profitability'!$H$3="All",I86='Daily Profitability'!$H$3),OR('Daily Profitability'!$K$3="All",J86='Daily Profitability'!$K$3),OR('Daily Profitability'!$N$3="All",K86='Daily Profitability'!$N$3)),1,0) -> 0
A87: 20260727-002 | B87: 20260727-002 | C87: 0 | D87: 46230 | E87: July 2026 | F87: Unspecified | G87: No activity label recorded | H87: Workshop | I87: Workshop & Decoration Supplies | J87: Decoration & Workshop Materials | K87: Event Megastore | L87: Party Candels,Dry Flowers,Painting Stand..... | M87: 78.544 | N87: 0 | P87: 27-July | Q87: 6 | R87: OK | S87: 0 | T87: 0 | U87: =IF(AND(OR('Daily Profitability'!$E$3="All",ISNUMBER(SEARCH('Daily Profitability'!$E$3,F87))),OR('Daily Profitability'!$H$3="All",I87='Daily Profitability'!$H$3),OR('Daily Profitability'!$K$3="All",J87='Daily Profitability'!$K$3),OR('Daily Profitability'!$N$3="All",K87='Daily Profitability'!$N$3)),1,0) -> 0
A88: 20260727-003 | B88: 20260727-003 | C88: Unrecorded | D88: 46230 | E88: July 2026 | F88: Birthday | G88: Birthday | H88: Birthday | I88: Food & Beverage | J88: Food & Beverage | K88: Karam Bake | L88: Mou3ajanet | M88: 74.84 | N88: 0 | P88: 27-July | Q88: 14 | R88: OK | S88: 0 | T88: 0 | U88: =IF(AND(OR('Daily Profitability'!$E$3="All",ISNUMBER(SEARCH('Daily Profitability'!$E$3,F88))),OR('Daily Profitability'!$H$3="All",I88='Daily Profitability'!$H$3),OR('Daily Profitability'!$K$3="All",J88='Daily Profitability'!$K$3),OR('Daily Profitability'!$N$3="All",K88='Daily Profitability'!$N$3)),1,0) -> 1
A89: 20260727-004 | B89: 20260727-004 | C89: Unrecorded | D89: 46230 | E89: July 2026 | F89: Unspecified | G89: No activity label recorded | H89: Kitchen | I89: Food & Beverage | J89: Food & Beverage | K89: Spinneys | L89: Fruits,Veg,Sparkling Water, Milk,pasta | M89: 400 | N89: 0 | P89: 27-July | Q89: 16 | R89: OK | S89: 0 | T89: 0 | U89: =IF(AND(OR('Daily Profitability'!$E$3="All",ISNUMBER(SEARCH('Daily Profitability'!$E$3,F89))),OR('Daily Profitability'!$H$3="All",I89='Daily Profitability'!$H$3),OR('Daily Profitability'!$K$3="All",J89='Daily Profitability'!$K$3),OR('Daily Profitability'!$N$3="All",K89='Daily Profitability'!$N$3)),1,0) -> 1
A90: 20260727-005 | B90: 20260727-005 | C90: 0 | D90: 46230 | E90: July 2026 | F90: Unspecified | G90: No activity label recorded | H90: Kitchen | I90: Food & Beverage | J90: Food & Beverage | K90: Forn Zakhia | L90: Manakich | M90: 41 | N90: 0 | P90: 27-July | Q90: 17 | R90: OK | S90: 0 | T90: 0 | U90: =IF(AND(OR('Daily Profitability'!$E$3="All",ISNUMBER(SEARCH('Daily Profitability'!$E$3,F90))),OR('Daily Profitability'!$H$3="All",I90='Daily Profitability'!$H$3),OR('Daily Profitability'!$K$3="All",J90='Daily Profitability'!$K$3),OR('Daily Profitability'!$N$3="All",K90='Daily Profitability'!$N$3)),1,0) -> 1
A91: 20260727-006 | B91: 20260727-006 | C91: 0 | D91: 46230 | E91: July 2026 | F91: Unspecified | G91: No activity label recorded | H91: Kitchen | I91: Food & Beverage | J91: Food & Beverage | K91: Storium | L91: Oil, Vinegar, Balkis,Saly,.... | M91: 144.66 | N91: 0 | P91: 27-July | Q91: 19 | R91: OK | S91: 0 | T91: 0 | U91: =IF(AND(OR('Daily Profitability'!$E$3="All",ISNUMBER(SEARCH('Daily Profitability'!$E$3,F91))),OR('Daily Profitability'!$H$3="All",I91='Daily Profitability'!$H$3),OR('Daily Profitability'!$K$3="All",J91='Daily Profitability'!$K$3),OR('Daily Profitability'!$N$3="All",K91='Daily Profitability'!$N$3)),1,0) -> 1
A92: 20260727-007 | B92: 20260727-007 | C92: 0 | D92: 46230 | E92: July 2026 | F92: Unspecified | G92: No activity label recorded | H92: Kitchen | I92: Food & Beverage | J92: Food & Beverage | K92: Le Marche Selectif | L92: F&V, Water, Trash Bags Baking Soda, Cheese, Beer | M92: 288 | N92: 0 | P92: 27-July | Q92: 21 | R92: OK | S92: 0 | T92: 0 | U92: =IF(AND(OR('Daily Profitability'!$E$3="All",ISNUMBER(SEARCH('Daily Profitability'!$E$3,F92))),OR('Daily Profitability'!$H$3="All",I92='Daily Profitability'!$H$3),OR('Daily Profitability'!$K$3="All",J92='Daily Profitability'!$K$3),OR('Daily Profitability'!$N$3="All",K92='Daily Profitability'!$N$3)),1,0) -> 1
A93: 20260729-001 | B93: 20260729-001 | C93: Unrecorded | D93: 46232 | E93: July 2026 | F93: Birthday | G93: Birthday | H93: Kitchen | I93: Food & Beverage | J93: Food & Beverage | K93: Panino Bakery | L93: Mini Burgers | M93: 6.74 | N93: 0 | P93: 29-July | Q93: 4 | R93: OK | S93: 0 | T93: 0 | U93: =IF(AND(OR('Daily Profitability'!$E$3="All",ISNUMBER(SEARCH('Daily Profitability'!$E$3,F93))),OR('Daily Profitability'!$H$3="All",I93='Daily Profitability'!$H$3),OR('Daily Profitability'!$K$3="All",J93='Daily Profitability'!$K$3),OR('Daily Profitability'!$N$3="All",K93='Daily Profitability'!$N$3)),1,0) -> 1
A94: 20260729-002 | B94: 20260729-002 | C94: 0 | D94: 46232 | E94: July 2026 | F94: Birthday | G94: Birthday | H94: Kitchen | I94: Food & Beverage | J94: Food & Beverage | K94: Boucherie Ziad | L94: Mafroume, Burgers Kebbe | M94: 75 | N94: 0 | P94: 29-July | Q94: 5 | R94: OK | S94: 0 | T94: 0 | U94: =IF(AND(OR('Daily Profitability'!$E$3="All",ISNUMBER(SEARCH('Daily Profitability'!$E$3,F94))),OR('Daily Profitability'!$H$3="All",I94='Daily Profitability'!$H$3),OR('Daily Profitability'!$K$3="All",J94='Daily Profitability'!$K$3),OR('Daily Profitability'!$N$3="All",K94='Daily Profitability'!$N$3)),1,0) -> 1
A95: 20260729-003 | B95: 20260729-003 | C95: 0 | D95: 46232 | E95: July 2026 | F95: Birthday | G95: Birthday | H95: Kitchen | I95: Food & Beverage | J95: Food & Beverage | K95: Spinneys | L95: Sparkling Water, Lemon, Fruits,Veg, Odex | M95: 68 | N95: 0 | P95: 29-July | Q95: 6 | R95: OK | S95: 0 | T95: 0 | U95: =IF(AND(OR('Daily Profitability'!$E$3="All",ISNUMBER(SEARCH('Daily Profitability'!$E$3,F95))),OR('Daily Profitability'!$H$3="All",I95='Daily Profitability'!$H$3),OR('Daily Profitability'!$K$3="All",J95='Daily Profitability'!$K$3),OR('Daily Profitability'!$N$3="All",K95='Daily Profitability'!$N$3)),1,0) -> 1
A96: 20260729-004 | B96: 20260729-004 | C96: 0 | D96: 46232 | E96: July 2026 | F96: Birthday | G96: Birthday | H96: Kitchen | I96: Food & Beverage | J96: Food & Beverage | K96: Le Marche Selectif | L96: F&V, LAban, Ice | M96: 104 | N96: 0 | P96: 29-July | Q96: 7 | R96: OK | S96: 0 | T96: 0 | U96: =IF(AND(OR('Daily Profitability'!$E$3="All",ISNUMBER(SEARCH('Daily Profitability'!$E$3,F96))),OR('Daily Profitability'!$H$3="All",I96='Daily Profitability'!$H$3),OR('Daily Profitability'!$K$3="All",J96='Daily Profitability'!$K$3),OR('Daily Profitability'!$N$3="All",K96='Daily Profitability'!$N$3)),1,0) -> 1
A97: 20260731-001 | B97: 20260731-001 | C97: 0 | D97: 46234 | E97: July 2026 | F97: Unspecified | G97: No activity label recorded | H97: Kitchen | I97: Food & Beverage | J97: Food & Beverage | K97: Spinneys | L97: Fruits baking soda,Vinigair, pasta Paper Cup; Emmental, Mozarella, olive Oil,dark Chocolate | M97: 98.08 | N97: 0 | P97: 31-July | Q97: 4-5 | R97: OK | S97: 0 | T97: 0 | U97: =IF(AND(OR('Daily Profitability'!$E$3="All",ISNUMBER(SEARCH('Daily Profitability'!$E$3,F97))),OR('Daily Profitability'!$H$3="All",I97='Daily Profitability'!$H$3),OR('Daily Profitability'!$K$3="All",J97='Daily Profitability'!$K$3),OR('Daily Profitability'!$N$3="All",K97='Daily Profitability'!$N$3)),1,0) -> 1
A98: 20260731-002 | B98: 20260731-002 | C98: Unrecorded | D98: 46234 | E98: July 2026 | F98: Unspecified | G98: No activity label recorded | H98: Garden | I98: Garden & Grounds | J98: Garden & Landscaping | K98: Agaric | L98: Assab | M98: 56 | N98: 0 | P98: 31-July | Q98: 7 | R98: OK | S98: 0 | T98: 0 | U98: =IF(AND(OR('Daily Profitability'!$E$3="All",ISNUMBER(SEARCH('Daily Profitability'!$E$3,F98))),OR('Daily Profitability'!$H$3="All",I98='Daily Profitability'!$H$3),OR('Daily Profitability'!$K$3="All",J98='Daily Profitability'!$K$3),OR('Daily Profitability'!$N$3="All",K98='Daily Profitability'!$N$3)),1,0) -> 0
A99: 20260802-001 | B99: 20260802-B001 | C99: 676400 | D99: 46236 | E99: August 2026 | F99: Birthday; Walk-in; Workshop; Event | G99: Birthday & Walk-in | H99: Workshops Birthday – Walk-in & Event | I99: Workshop & Decoration Supplies | J99: Decoration & Workshop Materials | K99: Event Megastore | L99: Extra Large Blocks; Toys Mul; Beach Toys Hero Small; Stainless Slott; Toys Dee Ball; Beach Toys T-84; Sport Toys k-47; Sport Toys k-51; Kitchen Untensil C-50; Dumpling Moull; Plastic Teperware | M99: 74.337079 | N99: 6616000 | O99: 89000 | P99: 2-8-2026 | Q99: 4-14 | R99: OK | S99: 1 | T99: 1 | U99: =IF(AND(OR('Daily Profitability'!$E$3="All",ISNUMBER(SEARCH('Daily Profitability'!$E$3,F99))),OR('Daily Profitability'!$H$3="All",I99='Daily Profitability'!$H$3),OR('Daily Profitability'!$K$3="All",J99='Daily Profitability'!$K$3),OR('Daily Profitability'!$N$3="All",K99='Daily Profitability'!$N$3)),1,0) -> 0
A100: 20260802-002 | B100: 20260802-B002 | C100: 46090 | D100: 46236 | E100: August 2026 | F100: Birthday | G100: Birthday | H100: Food & Beverage | I100: Food & Beverage | J100: Food & Beverage | K100: Le Marche Selectif | L100: F&V; Bamboo | M100: 11.988764 | N100: 1067000 | O100: 89000 | P100: 2-8-2026 | Q100: 16-17 | R100: OK | S100: 1 | T100: 1 | U100: =IF(AND(OR('Daily Profitability'!$E$3="All",ISNUMBER(SEARCH('Daily Profitability'!$E$3,F100))),OR('Daily Profitability'!$H$3="All",I100='Daily Profitability'!$H$3),OR('Daily Profitability'!$K$3="All",J100='Daily Profitability'!$K$3),OR('Daily Profitability'!$N$3="All",K100='Daily Profitability'!$N$3)),1,0) -> 1
A101: 20260802-003 | B101: 20260802-B003 | C101: Unrecorded | D101: 46236 | E101: August 2026 | F101: General Operations | G101: Office Expenses | H101: Not recorded | I101: Utilities & Office | J101: Maintenance | K101: Unspecified | L101: Moteur; Description not recorded | M101: 310 | N101: 0 | P101: 2-8-2026 | Q101: 18-19 | R101: Invoice number not recorded in source; Supplier not recorded | S101: 1 | T101: 1 | U101: =IF(AND(OR('Daily Profitability'!$E$3="All",ISNUMBER(SEARCH('Daily Profitability'!$E$3,F101))),OR('Daily Profitability'!$H$3="All",I101='Daily Profitability'!$H$3),OR('Daily Profitability'!$K$3="All",J101='Daily Profitability'!$K$3),OR('Daily Profitability'!$N$3="All",K101='Daily Profitability'!$N$3)),1,0) -> 0
A102: 20260802-004 | B102: 20260802-B004 | C102: Unrecorded | D102: 46236 | E102: August 2026 | F102: General Operations | G102: Office Expenses | H102: Not recorded | I102: Utilities & Office | J102: Water | K102: Unspecified | L102: Citern water | M102: 80 | N102: 0 | P102: 2-8-2026 | Q102: 20 | R102: Invoice number not recorded in source; Source date normalized to 2026-08-02; raw date preserved; Supplier not recorded | S102: 1 | T102: 1 | U102: =IF(AND(OR('Daily Profitability'!$E$3="All",ISNUMBER(SEARCH('Daily Profitability'!$E$3,F102))),OR('Daily Profitability'!$H$3="All",I102='Daily Profitability'!$H$3),OR('Daily Profitability'!$K$3="All",J102='Daily Profitability'!$K$3),OR('Daily Profitability'!$N$3="All",K102='Daily Profitability'!$N$3)),1,0) -> 0
A103: 20260802-005 | B103: 20260802-B005 | C103: Unrecorded | D103: 46236 | E103: August 2026 | F103: Birthday | G103: Birthday | H103: Food & Beverage | I103: Food & Beverage | J103: Food & Beverage | K103: Karam Bake | L103: Mou3ajanet | M103: 60.116 | N103: 5410440 | O103: 90000 | P103: 2-8-2026 | Q103: 21 | R103: Invoice number not recorded in source | S103: 1 | T103: 1 | U103: =IF(AND(OR('Daily Profitability'!$E$3="All",ISNUMBER(SEARCH('Daily Profitability'!$E$3,F103))),OR('Daily Profitability'!$H$3="All",I103='Daily Profitability'!$H$3),OR('Daily Profitability'!$K$3="All",J103='Daily Profitability'!$K$3),OR('Daily Profitability'!$N$3="All",K103='Daily Profitability'!$N$3)),1,0) -> 1
A104: 20260802-006 | B104: 20260802-B006 | C104: Unrecorded | D104: 46236 | E104: August 2026 | F104: Birthday | G104: Birthday | H104: Food & Beverage | I104: Food & Beverage | J104: Food & Beverage | K104: Spinneys | L104: F&V | M104: 30.497222 | N104: 2744750 | O104: 90000 | P104: 2-8-2026 | Q104: 23 | R104: Invoice number not recorded in source | S104: 1 | T104: 1 | U104: =IF(AND(OR('Daily Profitability'!$E$3="All",ISNUMBER(SEARCH('Daily Profitability'!$E$3,F104))),OR('Daily Profitability'!$H$3="All",I104='Daily Profitability'!$H$3),OR('Daily Profitability'!$K$3="All",J104='Daily Profitability'!$K$3),OR('Daily Profitability'!$N$3="All",K104='Daily Profitability'!$N$3)),1,0) -> 1
A105: 20260801-001 | B105: 20260801-B001 | C105: 5768 | D105: 46235 | E105: August 2026 | F105: General Operations | G105: Monthly Expenses | H105: Imaco | I105: Cleaning & Waste | J105: Waste Removal | K105: Imaco | L105: Garbege | M105: 30 | N105: 0 | P105: 7-August | Q105: 5 | R105: OK | S105: 1 | T105: 1 | U105: =IF(AND(OR('Daily Profitability'!$E$3="All",ISNUMBER(SEARCH('Daily Profitability'!$E$3,F105))),OR('Daily Profitability'!$H$3="All",I105='Daily Profitability'!$H$3),OR('Daily Profitability'!$K$3="All",J105='Daily Profitability'!$K$3),OR('Daily Profitability'!$N$3="All",K105='Daily Profitability'!$N$3)),1,0) -> 0
A106: 20260807-001 | B106: 20260807-B001 | C106: 71 | D106: 46241 | E106: August 2026 | F106: General Operations | G106: Garden | H106: Unspecified | I106: Garden & Grounds | J106: Garden & Landscaping | K106: Unspecified | L106: Ramel & Jafsin | M106: 14 | N106: 0 | P106: 7-August | Q106: 6 | R106: Supplier not recorded | S106: 1 | T106: 1 | U106: =IF(AND(OR('Daily Profitability'!$E$3="All",ISNUMBER(SEARCH('Daily Profitability'!$E$3,F106))),OR('Daily Profitability'!$H$3="All",I106='Daily Profitability'!$H$3),OR('Daily Profitability'!$K$3="All",J106='Daily Profitability'!$K$3),OR('Daily Profitability'!$N$3="All",K106='Daily Profitability'!$N$3)),1,0) -> 0
A107: 20260807-002 | B107: 20260807-B002 | C107: 46315 | D107: 46241 | E107: August 2026 | F107: Birthday | G107: Birthday | H107: Food & Beverage | I107: Food & Beverage | J107: Food & Beverage | K107: Le Marche Selectif | L107: F&V | M107: 10.925843 | N107: 972400 | O107: 89000 | P107: 7-August | Q107: 8 | R107: OK | S107: 1 | T107: 1 | U107: =IF(AND(OR('Daily Profitability'!$E$3="All",ISNUMBER(SEARCH('Daily Profitability'!$E$3,F107))),OR('Daily Profitability'!$H$3="All",I107='Daily Profitability'!$H$3),OR('Daily Profitability'!$K$3="All",J107='Daily Profitability'!$K$3),OR('Daily Profitability'!$N$3="All",K107='Daily Profitability'!$N$3)),1,0) -> 1
A108: 20260807-003 | B108: 20260807-B003 | C108: 46350 | D108: 46241 | E108: August 2026 | F108: Birthday | G108: Birthday | H108: Food & Beverage | I108: Food & Beverage | J108: Food & Beverage | K108: Unspecified | L108: F&V | M108: 68.876404 | N108: 6130000 | O108: 89000 | P108: 7-August | Q108: 9-12 | R108: Supplier not recorded | S108: 1 | T108: 1 | U108: =IF(AND(OR('Daily Profitability'!$E$3="All",ISNUMBER(SEARCH('Daily Profitability'!$E$3,F108))),OR('Daily Profitability'!$H$3="All",I108='Daily Profitability'!$H$3),OR('Daily Profitability'!$K$3="All",J108='Daily Profitability'!$K$3),OR('Daily Profitability'!$N$3="All",K108='Daily Profitability'!$N$3)),1,0) -> 1
A109: 20260807-004 | B109: 20260807-B004 | C109: 46485 | D109: 46241 | E109: August 2026 | F109: Birthday | G109: Birthday | H109: Food & Beverage | I109: Food & Beverage | J109: Food & Beverage | K109: Le Marche Selectif | L109: F&V; Water; Cold Ice 2 k | M109: 29.78427 | N109: 2650800 | O109: 89000 | P109: 7-August | Q109: 14-17 | R109: OK | S109: 1 | T109: 1 | U109: =IF(AND(OR('Daily Profitability'!$E$3="All",ISNUMBER(SEARCH('Daily Profitability'!$E$3,F109))),OR('Daily Profitability'!$H$3="All",I109='Daily Profitability'!$H$3),OR('Daily Profitability'!$K$3="All",J109='Daily Profitability'!$K$3),OR('Daily Profitability'!$N$3="All",K109='Daily Profitability'!$N$3)),1,0) -> 1
A110: 20260807-005 | B110: 20260807-B005 | C110: 70270012400106 | D110: 46241 | E110: August 2026 | F110: Birthday; Walk-in; Workshop; Event | G110: Workshops Activity | H110: Birthday & Walk-in | I110: Workshop & Decoration Supplies | J110: Decoration & Workshop Materials | K110: Fairco International | L110: Stamps,wodden sticks,Craft,AnimalToys, Ribbon | M110: 103.83775 | N110: 9241560 | O110: 89000 | P110: 7-August | Q110: 19 | R110: OK | S110: 1 | T110: 1 | U110: =IF(AND(OR('Daily Profitability'!$E$3="All",ISNUMBER(SEARCH('Daily Profitability'!$E$3,F110))),OR('Daily Profitability'!$H$3="All",I110='Daily Profitability'!$H$3),OR('Daily Profitability'!$K$3="All",J110='Daily Profitability'!$K$3),OR('Daily Profitability'!$N$3="All",K110='Daily Profitability'!$N$3)),1,0) -> 0
A111: 20260807-006 | B111: 20260807-B006 | C111: 22000215631 | D111: 46241 | E111: August 2026 | F111: Birthday; Walk-in; Workshop; Event | G111: Workshops Activity &Hygiene | H111: Birthday & Walk-in | I111: Cleaning & Waste | J111: Cleaning & Sanitation | K111: Spinneys | L111: Spontex, wipes,sunflower oil, Food Coloring | M111: 79.741573 | N111: 7097000 | O111: 89000 | P111: 7-August | Q111: 21 | R111: OK | S111: 1 | T111: 1 | U111: =IF(AND(OR('Daily Profitability'!$E$3="All",ISNUMBER(SEARCH('Daily Profitability'!$E$3,F111))),OR('Daily Profitability'!$H$3="All",I111='Daily Profitability'!$H$3),OR('Daily Profitability'!$K$3="All",J111='Daily Profitability'!$K$3),OR('Daily Profitability'!$N$3="All",K111='Daily Profitability'!$N$3)),1,0) -> 0
A112: 20260808-001 | B112: 20260808-B001 | C112: 46531 | D112: 46242 | E112: August 2026 | F112: Birthday | G112: Birthday | H112: Food & Beverage | I112: Food & Beverage | J112: Food & Beverage | K112: Le Marche Selectif | L112: Najjar Gold; Ice 2kg; F& V | M112: 14.820225 | N112: 1319000 | O112: 89000 | P112: 8-August | Q112: 4-6 | R112: OK | S112: 1 | T112: 1 | U112: =IF(AND(OR('Daily Profitability'!$E$3="All",ISNUMBER(SEARCH('Daily Profitability'!$E$3,F112))),OR('Daily Profitability'!$H$3="All",I112='Daily Profitability'!$H$3),OR('Daily Profitability'!$K$3="All",J112='Daily Profitability'!$K$3),OR('Daily Profitability'!$N$3="All",K112='Daily Profitability'!$N$3)),1,0) -> 1
A113: 20260808-002 | B113: 20260808-B002 | C113: 46573 | D113: 46242 | E113: August 2026 | F113: Birthday | G113: Birthday | H113: Food & Beverage | I113: Food & Beverage | J113: Food & Beverage | K113: Le Marche Selectif | L113: Rim water; Sodium Bicarbonate; Ice 2kg; F& V; Baygon Barghach | M113: 42.359551 | N113: 3770000 | O113: 89000 | P113: 8-August | Q113: 7-11 | R113: OK | S113: 1 | T113: 1 | U113: =IF(AND(OR('Daily Profitability'!$E$3="All",ISNUMBER(SEARCH('Daily Profitability'!$E$3,F113))),OR('Daily Profitability'!$H$3="All",I113='Daily Profitability'!$H$3),OR('Daily Profitability'!$K$3="All",J113='Daily Profitability'!$K$3),OR('Daily Profitability'!$N$3="All",K113='Daily Profitability'!$N$3)),1,0) -> 1
A114: 20260808-003 | B114: 20260808-B003 | C114: 46579 | D114: 46242 | E114: August 2026 | F114: Birthday | G114: Birthday | H114: Food & Beverage | I114: Food & Beverage | J114: Food & Beverage | K114: Le Marche Selectif | L114: Energizer Battery | M114: 7.1910112 | N114: 640000 | O114: 89000 | P114: 8-August | Q114: 12 | R114: OK | S114: 1 | T114: 1 | U114: =IF(AND(OR('Daily Profitability'!$E$3="All",ISNUMBER(SEARCH('Daily Profitability'!$E$3,F114))),OR('Daily Profitability'!$H$3="All",I114='Daily Profitability'!$H$3),OR('Daily Profitability'!$K$3="All",J114='Daily Profitability'!$K$3),OR('Daily Profitability'!$N$3="All",K114='Daily Profitability'!$N$3)),1,0) -> 1
A115: 20260808-004 | B115: 20260808-B004 | C115: Unrecorded | D115: 46242 | E115: August 2026 | F115: Birthday | G115: Birthday | H115: Food & Beverage | I115: Food & Beverage | J115: Food & Beverage | K115: Boucherie Ziad | L115: Burger | M115: 18.27 | N115: 0 | P115: 8-August | Q115: 13 | R115: Invoice number not recorded in source | S115: 1 | T115: 1 | U115: =IF(AND(OR('Daily Profitability'!$E$3="All",ISNUMBER(SEARCH('Daily Profitability'!$E$3,F115))),OR('Daily Profitability'!$H$3="All",I115='Daily Profitability'!$H$3),OR('Daily Profitability'!$K$3="All",J115='Daily Profitability'!$K$3),OR('Daily Profitability'!$N$3="All",K115='Daily Profitability'!$N$3)),1,0) -> 1
A116: 20260808-005 | B116: 20260808-B005 | C116: Unrecorded | D116: 46242 | E116: August 2026 | F116: Birthday | G116: Birthday | H116: Food & Beverage | I116: Food & Beverage | J116: Food & Beverage | K116: Panino Bakery | L116: burger Bread | M116: 6.741573 | N116: 600000 | O116: 89000 | P116: 8-August | Q116: 14 | R116: Invoice number not recorded in source; Source date normalized to 2026-08-08; raw date preserved | S116: 1 | T116: 1 | U116: =IF(AND(OR('Daily Profitability'!$E$3="All",ISNUMBER(SEARCH('Daily Profitability'!$E$3,F116))),OR('Daily Profitability'!$H$3="All",I116='Daily Profitability'!$H$3),OR('Daily Profitability'!$K$3="All",J116='Daily Profitability'!$K$3),OR('Daily Profitability'!$N$3="All",K116='Daily Profitability'!$N$3)),1,0) -> 1
A117: 20260808-006 | B117: 20260808-B006 | C117: Unrecorded | D117: 46242 | E117: August 2026 | F117: Birthday | G117: Birthday | H117: Food & Beverage | I117: Food & Beverage | J117: Food & Beverage | K117: Fresh & More | L117: F&V | M117: 118.17978 | N117: 10518000 | O117: 89000 | P117: 8-August | Q117: 15 | R117: Invoice number not recorded in source; Source date normalized to 2026-08-08; raw date preserved | S117: 1 | T117: 1 | U117: =IF(AND(OR('Daily Profitability'!$E$3="All",ISNUMBER(SEARCH('Daily Profitability'!$E$3,F117))),OR('Daily Profitability'!$H$3="All",I117='Daily Profitability'!$H$3),OR('Daily Profitability'!$K$3="All",J117='Daily Profitability'!$K$3),OR('Daily Profitability'!$N$3="All",K117='Daily Profitability'!$N$3)),1,0) -> 1
A118: 20260809-001 | B118: 20260809-B001 | C118: 46627 | D118: 46243 | E118: August 2026 | F118: Birthday | G118: Birthday | H118: Food & Beverage | I118: Food & Beverage | J118: Food & Beverage | K118: Le Marche Selectif | L118: Beirut beer; F&V; Fahem Colombie; Oil | M118: 26.808989 | N118: 2386000 | O118: 89000 | P118: 9-August | Q118: 3, 6-8 | R118: OK | S118: 1 | T118: 1 | U118: =IF(AND(OR('Daily Profitability'!$E$3="All",ISNUMBER(SEARCH('Daily Profitability'!$E$3,F118))),OR('Daily Profitability'!$H$3="All",I118='Daily Profitability'!$H$3),OR('Daily Profitability'!$K$3="All",J118='Daily Profitability'!$K$3),OR('Daily Profitability'!$N$3="All",K118='Daily Profitability'!$N$3)),1,0) -> 1
A119: 20260809-002 | B119: 20260809-B001 | C119: 46627 | D119: 46243 | E119: August 2026 | F119: Birthday; Walk-in; Workshop; Event | G119: Birthday & Walk-in | H119: Workshops Birthday – Walk-in & Event | I119: Workshop & Decoration Supplies | J119: Decoration & Workshop Materials | K119: Le Marche Selectif | L119: Ice 2kg | M119: 6.741573 | N119: 600000 | O119: 89000 | P119: 9-August | Q119: 4 | R119: OK | S119: 1 | T119: 0 | U119: =IF(AND(OR('Daily Profitability'!$E$3="All",ISNUMBER(SEARCH('Daily Profitability'!$E$3,F119))),OR('Daily Profitability'!$H$3="All",I119='Daily Profitability'!$H$3),OR('Daily Profitability'!$K$3="All",J119='Daily Profitability'!$K$3),OR('Daily Profitability'!$N$3="All",K119='Daily Profitability'!$N$3)),1,0) -> 0
A120: 20260809-003 | B120: 20260809-B001 | C120: 46627 | D120: 46243 | E120: August 2026 | F120: Birthday; Walk-in | G120: Birthday & Walk-in | H120: Drink | I120: Food & Beverage | J120: Food & Beverage | K120: Le Marche Selectif | L120: Sparkling water | M120: 3.0337079 | N120: 270000 | O120: 89000 | P120: 9-August | Q120: 5 | R120: OK | S120: 1 | T120: 0 | U120: =IF(AND(OR('Daily Profitability'!$E$3="All",ISNUMBER(SEARCH('Daily Profitability'!$E$3,F120))),OR('Daily Profitability'!$H$3="All",I120='Daily Profitability'!$H$3),OR('Daily Profitability'!$K$3="All",J120='Daily Profitability'!$K$3),OR('Daily Profitability'!$N$3="All",K120='Daily Profitability'!$N$3)),1,0) -> 1
A121: 20260809-004 | B121: 20260809-B002 | C121: 46759 | D121: 46243 | E121: August 2026 | F121: Birthday | G121: Birthday | H121: Food & Beverage | I121: Food & Beverage | J121: Food & Beverage | K121: Le Marche Selectif | L121: Flour 1kg; F&V | M121: 13.033708 | N121: 1160000 | O121: 89000 | P121: 9-August | Q121: 9-10 | R121: OK | S121: 1 | T121: 1 | U121: =IF(AND(OR('Daily Profitability'!$E$3="All",ISNUMBER(SEARCH('Daily Profitability'!$E$3,F121))),OR('Daily Profitability'!$H$3="All",I121='Daily Profitability'!$H$3),OR('Daily Profitability'!$K$3="All",J121='Daily Profitability'!$K$3),OR('Daily Profitability'!$N$3="All",K121='Daily Profitability'!$N$3)),1,0) -> 1
A122: 20260809-005 | B122: 20260809-B003 | C122: 46657 | D122: 46243 | E122: August 2026 | F122: Birthday | G122: Birthday | H122: Food & Beverage; Not recorded | I122: Food & Beverage | J122: Food & Beverage | K122: Le Marche Selectif | L122: Domo Baking Soda; F&V | M122: 19.452809 | N122: 1731300 | O122: 89000 | P122: 9-August | Q122: 11, 16-17 | R122: OK | S122: 1 | T122: 1 | U122: =IF(AND(OR('Daily Profitability'!$E$3="All",ISNUMBER(SEARCH('Daily Profitability'!$E$3,F122))),OR('Daily Profitability'!$H$3="All",I122='Daily Profitability'!$H$3),OR('Daily Profitability'!$K$3="All",J122='Daily Profitability'!$K$3),OR('Daily Profitability'!$N$3="All",K122='Daily Profitability'!$N$3)),1,0) -> 1
A123: 20260809-006 | B123: 20260809-B003 | C123: 46657 | D123: 46243 | E123: August 2026 | F123: Birthday; Workshop | G123: Birthday | H123: Birthday Activity | I123: Workshop & Decoration Supplies | J123: Decoration & Workshop Materials | K123: Le Marche Selectif | L123: Domo Vanilla; Cotton | M123: 8.5617978 | N123: 762000 | O123: 89000 | P123: 9-August | Q123: 12-13 | R123: OK | S123: 1 | T123: 0 | U123: =IF(AND(OR('Daily Profitability'!$E$3="All",ISNUMBER(SEARCH('Daily Profitability'!$E$3,F123))),OR('Daily Profitability'!$H$3="All",I123='Daily Profitability'!$H$3),OR('Daily Profitability'!$K$3="All",J123='Daily Profitability'!$K$3),OR('Daily Profitability'!$N$3="All",K123='Daily Profitability'!$N$3)),1,0) -> 0
A124: 20260809-007 | B124: 20260809-B003 | C124: 46657 | D124: 46243 | E124: August 2026 | F124: Birthday | G124: Birthday | H124: Not recorded | I124: Utilities & Office | J124: Other / Office | K124: Le Marche Selectif | L124: Trash Bags L | M124: 15.337079 | N124: 1365000 | O124: 89000 | P124: 9-August | Q124: 14-15 | R124: OK | S124: 1 | T124: 0 | U124: =IF(AND(OR('Daily Profitability'!$E$3="All",ISNUMBER(SEARCH('Daily Profitability'!$E$3,F124))),OR('Daily Profitability'!$H$3="All",I124='Daily Profitability'!$H$3),OR('Daily Profitability'!$K$3="All",J124='Daily Profitability'!$K$3),OR('Daily Profitability'!$N$3="All",K124='Daily Profitability'!$N$3)),1,0) -> 0
...
